Workbook
Name Alcohol_and_Tobacco: Reference!$H$2:$H$3
Name Clothing_and_Footwear: Reference!$I$2:$I$5
Name DS_Country_List: Reference!$C$2:$C$206
Name DS_Currency_List: Reference!$D$2:$D$206
Name DSCountry: 'Data Table'!$C$3
Name Education: Reference!$J$2:$J$16
Name Food_and_Non_Alcoholic_Beverages: Reference!$K$2:$K$3
Name Furniture_Household_and_Routine_Home_Maintenance: Reference!$L$2:$L$9
Name FXRatesTable: 'FX Rates'!$A$1:$BQ$152
Name GroupList: [1]Reference!$N$1:$N$14
Name Health_Out_of_Pocket: Reference!$M$2:$M$6
Name Housing: Reference!$N$2:$N$3
Name Information_and_Communication: Reference!$O$2:$O$3
Name InsideOutside: [1]Reference!$K$1:$K$2
Name InsideOutsideList: Reference!$E$2:$E$3
Name Insurance_and_Financial_Services: Reference!$P$2:$P$5
Name ISOCodeList: 'FX Rates'!$A$2:$A$152
Name ISOList: [1]Reference!$AH$1:$AH$152
Name Item_List: Reference!$Y$2:$Y$80
Name Item_List_Number: Reference!$W$2:$W$80
Name ItemCategoryList: Reference!$G$2:$G$15
Name Month_List: Reference!$B$2:$B$13
Name Month_Number: Reference!$A$2:$A$13
Name Other: Reference!$Q$2:$Q$4
Name Personal_and_Miscellaneous_Goods_and_Services: Reference!$R$2:$R$8
Name Recreation_and_Culture: Reference!$S$2:$S$11
Name Restaurants_and_Accommodation_Services: Reference!$T$2:$T$4
Name Summary_View_Explainer: Reference!$AB$2:$AB$7
Name Summary_View_List: Reference!$AA$2:$AA$7
Name SummaryTableToggleTable: 'Summary Table Toggle'!$B$4:$H$18
Name SummaryToggleAllTime: 'Summary Table Toggle'!$E$4:$E$18
Name SummaryToggleAllTimeLC: 'Summary Table Toggle'!$F$4:$F$18
Name SummaryToggleCategory: 'Summary Table Toggle'!$B$4:$B$18
Name SummaryToggleEstimatedMonth: 'Summary Table Toggle'!$G$4:$G$18
Name SummaryToggleEstimatedMonthLC: 'Summary Table Toggle'!$H$4:$H$18
Name SummaryTogglePast30: 'Summary Table Toggle'!$C$4:$C$18
Name SummaryTogglePast30LC: 'Summary Table Toggle'!$D$4:$D$18
Name SummaryView: Summary!$C$4
Name Time_Span: Reference!$X$2:$X$80
Name Transport: Reference!$U$2:$U$13

Sheet Data Table
D1: Instructions 1. Indicate the country of duty station. 2. Record expenses in the yellow fields of the table below. The item category must be specified before selecting the item subcategory. 3. The summary tab displays a summary of expenses with the option of three different views. 4. The "Monthly Expenses", "Yearly and Education Expenses" and "Infrequent Expenses" tabs display expenses formatted in accordance with the cost-of-living survey.
C2: COUNTRY OF DUTY STATION
C3: Australia
C4: =IF(ISBLANK(DSCountry),"Select duty station above","Local Currency: "&(_xlfn.XLOOKUP(DSCountry,DS_Country_List,DS_Currency_List))) -> Local Currency: AUD
D6: ICSC Electronic Diary: Itemized List of All Expenditures | G6: ="Exchange rate conversions are based on history of UN Treasury rates from Jan 2021 through "&_xlfn.XLOOKUP(MONTH(MAX('FX Rates'!1:1)),Month_Number,Month_List)& " "&YEAR(MAX('FX Rates'!1:1)) -> Exchange rate conversions are based on history of UN Treasury rates from Jan 2021 through Aug 2026
B7: DATE | C7: ITEM CATEGORY | D7: ITEM SUBCATEGORY | E7: ITEM DESCRIPTION (Optional) | F7: Inside/Outside Duty Station | G7: AMOUNT | H7: CURRENCY | I7: TIME SPAN | J7: AMOUNT in USD
B8: 46249 | C8: Food and Non Alcoholic Beverages | D8: Food Purchased in Markets | E8: Example | F8: Inside | G8: 200 | H8: AUD | I8: =IF(ISBLANK($D8),"",_xlfn.XLOOKUP($D8,Item_List,Time_Span,"",0)) -> M | J8: =IF(ISBLANK($H8),"",IF(VLOOKUP($H8,'FX Rates'!$A$1:$BQ$152,_xlfn.XMATCH($B8,'FX Rates'!$A$1:$BQ$1,-1,1),0)=0,"No Exch Rate Data",IF($G8=0,"",$G8/VLOOKUP($H8,'FX Rates'!$A$1:$BQ$152,_xlfn.XMATCH($B8,'FX Rates'!$A$1:$BQ$1,-1,1),0)))) -> 141.14326
I9: =IF(ISBLANK($D9),"",_xlfn.XLOOKUP($D9,Item_List,Time_Span,"",0)) | J9: =IF(ISBLANK($H9),"",IF(VLOOKUP($H9,'FX Rates'!$A$1:$BQ$152,_xlfn.XMATCH($B9,'FX Rates'!$A$1:$BQ$1,-1,1),0)=0,"No Exch Rate Data",IF($G9=0,"",$G9/VLOOKUP($H9,'FX Rates'!$A$1:$BQ$152,_xlfn.XMATCH($B9,'FX Rates'!$A$1:$BQ$1,-1,1),0))))
I10: =IF(ISBLANK($D10),"",_xlfn.XLOOKUP($D10,Item_List,Time_Span,"",0)) | J10: =IF(ISBLANK($H10),"",IF(VLOOKUP($H10,'FX Rates'!$A$1:$BQ$152,_xlfn.XMATCH($B10,'FX Rates'!$A$1:$BQ$1,-1,1),0)=0,"No Exch Rate Data",IF($G10=0,"",$G10/VLOOKUP($H10,'FX Rates'!$A$1:$BQ$152,_xlfn.XMATCH($B10,'FX Rates'!$A$1:$BQ$1,-1,1),0))))
I11: =IF(ISBLANK($D11),"",_xlfn.XLOOKUP($D11,Item_List,Time_Span,"",0)) | J11: =IF(ISBLANK($H11),"",IF(VLOOKUP($H11,'FX Rates'!$A$1:$BQ$152,_xlfn.XMATCH($B11,'FX Rates'!$A$1:$BQ$1,-1,1),0)=0,"No Exch Rate Data",IF($G11=0,"",$G11/VLOOKUP($H11,'FX Rates'!$A$1:$BQ$152,_xlfn.XMATCH($B11,'FX Rates'!$A$1:$BQ$1,-1,1),0))))
I12: =IF(ISBLANK($D12),"",_xlfn.XLOOKUP($D12,Item_List,Time_Span,"",0)) | J12: =IF(ISBLANK($H12),"",IF(VLOOKUP($H12,'FX Rates'!$A$1:$BQ$152,_xlfn.XMATCH($B12,'FX Rates'!$A$1:$BQ$1,-1,1),0)=0,"No Exch Rate Data",IF($G12=0,"",$G12/VLOOKUP($H12,'FX Rates'!$A$1:$BQ$152,_xlfn.XMATCH($B12,'FX Rates'!$A$1:$BQ$1,-1,1),0))))
I13: =IF(ISBLANK($D13),"",_xlfn.XLOOKUP($D13,Item_List,Time_Span,"",0)) | J13: =IF(ISBLANK($H13),"",IF(VLOOKUP($H13,'FX Rates'!$A$1:$BQ$152,_xlfn.XMATCH($B13,'FX Rates'!$A$1:$BQ$1,-1,1),0)=0,"No Exch Rate Data",IF($G13=0,"",$G13/VLOOKUP($H13,'FX Rates'!$A$1:$BQ$152,_xlfn.XMATCH($B13,'FX Rates'!$A$1:$BQ$1,-1,1),0))))
I14: =IF(ISBLANK($D14),"",_xlfn.XLOOKUP($D14,Item_List,Time_Span,"",0)) | J14: =IF(ISBLANK($H14),"",IF(VLOOKUP($H14,'FX Rates'!$A$1:$BQ$152,_xlfn.XMATCH($B14,'FX Rates'!$A$1:$BQ$1,-1,1),0)=0,"No Exch Rate Data",IF($G14=0,"",$G14/VLOOKUP($H14,'FX Rates'!$A$1:$BQ$152,_xlfn.XMATCH($B14,'FX Rates'!$A$1:$BQ$1,-1,1),0))))
I15: =IF(ISBLANK($D15),"",_xlfn.XLOOKUP($D15,Item_List,Time_Span,"",0)) | J15: =IF(ISBLANK($H15),"",IF(VLOOKUP($H15,'FX Rates'!$A$1:$BQ$152,_xlfn.XMATCH($B15,'FX Rates'!$A$1:$BQ$1,-1,1),0)=0,"No Exch Rate Data",IF($G15=0,"",$G15/VLOOKUP($H15,'FX Rates'!$A$1:$BQ$152,_xlfn.XMATCH($B15,'FX Rates'!$A$1:$BQ$1,-1,1),0))))
I16: =IF(ISBLANK($D16),"",_xlfn.XLOOKUP($D16,Item_List,Time_Span,"",0)) | J16: =IF(ISBLANK($H16),"",IF(VLOOKUP($H16,'FX Rates'!$A$1:$BQ$152,_xlfn.XMATCH($B16,'FX Rates'!$A$1:$BQ$1,-1,1),0)=0,"No Exch Rate Data",IF($G16=0,"",$G16/VLOOKUP($H16,'FX Rates'!$A$1:$BQ$152,_xlfn.XMATCH($B16,'FX Rates'!$A$1:$BQ$1,-1,1),0))))
I17: =IF(ISBLANK($D17),"",_xlfn.XLOOKUP($D17,Item_List,Time_Span,"",0)) | J17: =IF(ISBLANK($H17),"",IF(VLOOKUP($H17,'FX Rates'!$A$1:$BQ$152,_xlfn.XMATCH($B17,'FX Rates'!$A$1:$BQ$1,-1,1),0)=0,"No Exch Rate Data",IF($G17=0,"",$G17/VLOOKUP($H17,'FX Rates'!$A$1:$BQ$152,_xlfn.XMATCH($B17,'FX Rates'!$A$1:$BQ$1,-1,1),0))))
I18: =IF(ISBLANK($D18),"",_xlfn.XLOOKUP($D18,Item_List,Time_Span,"",0)) | J18: =IF(ISBLANK($H18),"",IF(VLOOKUP($H18,'FX Rates'!$A$1:$BQ$152,_xlfn.XMATCH($B18,'FX Rates'!$A$1:$BQ$1,-1,1),0)=0,"No Exch Rate Data",IF($G18=0,"",$G18/VLOOKUP($H18,'FX Rates'!$A$1:$BQ$152,_xlfn.XMATCH($B18,'FX Rates'!$A$1:$BQ$1,-1,1),0))))
I19: =IF(ISBLANK($D19),"",_xlfn.XLOOKUP($D19,Item_List,Time_Span,"",0)) | J19: =IF(ISBLANK($H19),"",IF(VLOOKUP($H19,'FX Rates'!$A$1:$BQ$152,_xlfn.XMATCH($B19,'FX Rates'!$A$1:$BQ$1,-1,1),0)=0,"No Exch Rate Data",IF($G19=0,"",$G19/VLOOKUP($H19,'FX Rates'!$A$1:$BQ$152,_xlfn.XMATCH($B19,'FX Rates'!$A$1:$BQ$1,-1,1),0))))
I20: =IF(ISBLANK($D20),"",_xlfn.XLOOKUP($D20,Item_List,Time_Span,"",0)) | J20: =IF(ISBLANK($H20),"",IF(VLOOKUP($H20,'FX Rates'!$A$1:$BQ$152,_xlfn.XMATCH($B20,'FX Rates'!$A$1:$BQ$1,-1,1),0)=0,"No Exch Rate Data",IF($G20=0,"",$G20/VLOOKUP($H20,'FX Rates'!$A$1:$BQ$152,_xlfn.XMATCH($B20,'FX Rates'!$A$1:$BQ$1,-1,1),0))))
... I1000: =IF(ISBLANK($D1000),"",_xlfn.XLOOKUP($D1000,Item_List,Time_Span,"",0)) | J1000: =IF(ISBLANK($H1000),"",IF(VLOOKUP($H1000,'FX Rates'!$A$1:$BQ$152,_xlfn.XMATCH($B1000,'FX Rates'!$A$1:$BQ$1,-1,1),0)=0,"No Exch Rate Data",IF($G1000=0,"",$G1000/VLOOKUP($H1000,'FX Rates'!$A$1:$BQ$152,_xlfn.XMATCH($B1000,'FX Rates'!$A$1:$BQ$1,-1,1),0))))

Sheet Summary
B2: ICSC ELECTRONIC DIARY: Summary of Expenses
C3: Select Summary View Option from Dropdown | D3: =_xlfn.XLOOKUP(SummaryView,Summary_View_List,Summary_View_Explainer) -> Values displayed are the total of all expenses entered in the Data Table
C4: All Expenditures (USD)
C6: ="Exchange rate conversions are based on history of UN Treasury rates from Jan 2021 through "&_xlfn.XLOOKUP(MONTH(MAX('FX Rates'!$1:$1)),Month_Number,Month_List)& " "&YEAR(MAX('FX Rates'!$1:$1)) -> Exchange rate conversions are based on history of UN Treasury rates from Jan 2021 through Aug 2026 | D6: =IF(RIGHT(SummaryView,16)="(Local Currency)",LEFT(SummaryView,LEN(SummaryView)-16)&"("&(_xlfn.XLOOKUP(DSCountry,DS_Country_List,DS_Currency_List))&")",SummaryView) -> All Expenditures (USD)
D7: Category | F7: Total Expense | G7: As Percentage
C8: =IF((RIGHT(SummaryView,5))="(USD)","Expenditures from Last 30 Days (USD)","Expenditures from Last 30 Days ("&(_xlfn.XLOOKUP(DSCountry,DS_Country_List,DS_Currency_List))&")") -> Expenditures from Last 30 Days (USD) | D8: Food and Non Alcoholic Beverages | F8: =VLOOKUP($D8,SummaryTableToggleTable,_xlfn.XMATCH(SummaryView,Summary_View_List,0)+1,FALSE) -> 141.14326 | G8: =IF($F8=0,0,$F8/$F$22) -> 1
C9: =IF((RIGHT(SummaryView,5))="(USD)",SUMIF('Data Table'!B:B,"<="&TODAY(),'Data Table'!J:J)-SUMIF('Data Table'!B:B,"<="&(TODAY()-30),'Data Table'!J:J),(SUMIF('Data Table'!B:B,"<="&TODAY(),'Data Table'!J:J)-SUMIF('Data Table'!B:B,"<="&(TODAY()-30),'Data Table'!J:J))*(VLOOKUP((_xlfn.XLOOKUP(DSCountry,DS_Country_List,DS_Currency_List)),'FX Rates'!$A$1:$BQ$152,2))) -> 141.14326 | D9: Alcohol and Tobacco | F9: =VLOOKUP($D9,SummaryTableToggleTable,_xlfn.XMATCH(SummaryView,Summary_View_List,0)+1,FALSE) -> 0 | G9: =IF($F9=0,0,$F9/$F$22) -> 0
D10: Clothing and Footwear | F10: =VLOOKUP($D10,SummaryTableToggleTable,_xlfn.XMATCH(SummaryView,Summary_View_List,0)+1,FALSE) -> 0 | G10: =IF($F10=0,0,$F10/$F$22) -> 0
D11: Housing | F11: =VLOOKUP($D11,SummaryTableToggleTable,_xlfn.XMATCH(SummaryView,Summary_View_List,0)+1,FALSE) -> 0 | G11: =IF($F11=0,0,$F11/$F$22) -> 0
D12: Furniture Household and Routine Home Maintenance | F12: =VLOOKUP($D12,SummaryTableToggleTable,_xlfn.XMATCH(SummaryView,Summary_View_List,0)+1,FALSE) -> 0 | G12: =IF($F12=0,0,$F12/$F$22) -> 0
C13: =IF((RIGHT(SummaryView,5))="(USD)","Sum of All Expenditures (USD)","Sum of All Expenditures ("&(_xlfn.XLOOKUP(DSCountry,DS_Country_List,DS_Currency_List))&")") -> Sum of All Expenditures (USD) | D13: Health Out of Pocket | F13: =VLOOKUP($D13,SummaryTableToggleTable,_xlfn.XMATCH(SummaryView,Summary_View_List,0)+1,FALSE) -> 0 | G13: =IF($F13=0,0,$F13/$F$22) -> 0
C14: =IF((RIGHT(SummaryView,5))="(USD)",SUM('Data Table'!J:J),SUM('Data Table'!J:J)*(VLOOKUP((_xlfn.XLOOKUP(DSCountry,DS_Country_List,DS_Currency_List)),'FX Rates'!$A$1:$BQ$152,2))) -> 141.14326 | D14: Transport | F14: =VLOOKUP($D14,SummaryTableToggleTable,_xlfn.XMATCH(SummaryView,Summary_View_List,0)+1,FALSE) -> 0 | G14: =IF($F14=0,0,$F14/$F$22) -> 0
D15: Information and Communication | F15: =VLOOKUP($D15,SummaryTableToggleTable,_xlfn.XMATCH(SummaryView,Summary_View_List,0)+1,FALSE) -> 0 | G15: =IF($F15=0,0,$F15/$F$22) -> 0
D16: Recreation and Culture | F16: =VLOOKUP($D16,SummaryTableToggleTable,_xlfn.XMATCH(SummaryView,Summary_View_List,0)+1,FALSE) -> 0 | G16: =IF($F16=0,0,$F16/$F$22) -> 0
D17: Education | F17: =VLOOKUP($D17,SummaryTableToggleTable,_xlfn.XMATCH(SummaryView,Summary_View_List,0)+1,FALSE) -> 0 | G17: =IF($F17=0,0,$F17/$F$22) -> 0
C18: =IF((RIGHT(SummaryView,5))="(USD)","Estimated Monthly Expenditures (USD)","Estimated Monthly Expenditures ("&(_xlfn.XLOOKUP(DSCountry,DS_Country_List,DS_Currency_List))&")") -> Estimated Monthly Expenditures (USD) | D18: Restaurants and Accommodation Services | F18: =VLOOKUP($D18,SummaryTableToggleTable,_xlfn.XMATCH(SummaryView,Summary_View_List,0)+1,FALSE) -> 0 | G18: =IF($F18=0,0,$F18/$F$22) -> 0
C19: =IF((RIGHT(SummaryView,5))="(USD)",SUMIFS('Data Table'!J:J,'Data Table'!B:B,"<="&TODAY(),'Data Table'!I:I,"M")-SUMIFS('Data Table'!J:J,'Data Table'!B:B,"<="&(TODAY()-30),'Data Table'!I:I,"M")+(SUMIFS('Data Table'!J:J,'Data Table'!B:B,"<="&TODAY(),'Data Table'!I:I,"Y")/12)-(SUMIFS('Data Table'!J:J,'Data Table'!B:B,"<="&(TODAY()-360),'Data Table'!I:I,"Y")/12)+(SUMIFS('Data Table'!J:J,'Data Table'!B:B,"<="&TODAY(),'Data Table'!I:I,"5Y")/60-SUMIFS('Data Table'!J:J,'Data Table'!B:B,"<="&(TODAY()-1826),'Data Table'!I:I,"5Y")/60),'Summary Table Toggle'!$H$18) -> 141.14326 | D19: Insurance and Financial Services | F19: =VLOOKUP($D19,SummaryTableToggleTable,_xlfn.XMATCH(SummaryView,Summary_View_List,0)+1,FALSE) -> 0 | G19: =IF($F19=0,0,$F19/$F$22) -> 0
D20: Personal and Miscellaneous Goods and Services | F20: =VLOOKUP($D20,SummaryTableToggleTable,_xlfn.XMATCH(SummaryView,Summary_View_List,0)+1,FALSE) -> 0 | G20: =IF($F20=0,0,$F20/$F$22) -> 0
D21: Other | F21: =VLOOKUP($D21,SummaryTableToggleTable,_xlfn.XMATCH(SummaryView,Summary_View_List,0)+1,FALSE) -> 0 | G21: =IF($F21=0,0,$F21/$F$22) -> 0
D22: TOTAL | F22: =VLOOKUP($D22,SummaryTableToggleTable,_xlfn.XMATCH(SummaryView,Summary_View_List,0)+1,FALSE) -> 141.14326 | G22: =SUM(G8:G21) -> 1

Sheet Monthly Expenses
D2: ICSC Electronic Diary for Monthly Expenditures | E2: INSIDE COUNTRY OF DUTY STATION | H2: OUTSIDE COUNTRY OF DUTY STATION
E3: =IF(ISBLANK(DSCountry),"Specify country in Data Table","Amount Spent in Local Currency ("&(_xlfn.XLOOKUP(DSCountry,DS_Country_List,DS_Currency_List))&")") -> Amount Spent in Local Currency (AUD) | F3: Amount Spent in Other Currency (Expressed in USD) | H3: Amount Spent (Expressed in USD)
C4: Food and Non-Alcoholic Beverages
C5: 1 | D5: Food purchased in supermarkets, stores, markets | E5: =SUMIFS('Data Table'!$G$8:$G$1000,'Data Table'!$D$8:$D$1000,_xlfn.XLOOKUP($C5,Item_List_Number,Item_List,"",0),'Data Table'!$F$8:$F$1000,"Inside",'Data Table'!$H$8:$H$1000,_xlfn.XLOOKUP(DSCountry,DS_Country_List,DS_Currency_List)) -> 200 | F5: =SUMIFS('Data Table'!$J$8:$J$1000,'Data Table'!$D$8:$D$1000,_xlfn.XLOOKUP($C5,Item_List_Number,Item_List,"",0),'Data Table'!$F$8:$F$1000,"Inside",'Data Table'!$H$8:$H$1000,"<>"&_xlfn.XLOOKUP(DSCountry,DS_Country_List,DS_Currency_List)) -> 0 | G5: USD | H5: =SUMIFS('Data Table'!$J$8:$J$1000,'Data Table'!$D$8:$D$1000,_xlfn.XLOOKUP($C5,Item_List_Number,Item_List,"",0),'Data Table'!$F$8:$F$1000,"Outside") -> 0 | I5: USD
C6: 2 | D6: Non-alcoholic beverages | E6: =SUMIFS('Data Table'!$G$8:$G$1000,'Data Table'!$D$8:$D$1000,'Monthly Expenses'!$J6,'Data Table'!$F$8:$F$1000,"Inside",'Data Table'!$H$8:$H$1000,_xlfn.XLOOKUP(DSCountry,DS_Country_List,DS_Currency_List)) -> 0 | F6: =SUMIFS('Data Table'!$J$8:$J$1000,'Data Table'!$D$8:$D$1000,'Monthly Expenses'!$J6,'Data Table'!$F$8:$F$1000,"Inside",'Data Table'!$H$8:$H$1000,"<>"&_xlfn.XLOOKUP(DSCountry,DS_Country_List,DS_Currency_List)) -> 0 | G6: USD | H6: =SUMIFS('Data Table'!$J$8:$J$1000,'Data Table'!$D$8:$D$1000,'Monthly Expenses'!$J6,'Data Table'!$F$8:$F$1000,"Outside") -> 0 | I6: USD
C7: Alcohol and Tobacco
C8: 3 | D8: Alcoholic beverages | E8: =SUMIFS('Data Table'!$G$8:$G$1000,'Data Table'!$D$8:$D$1000,_xlfn.XLOOKUP($C8,Item_List_Number,Item_List,"",0),'Data Table'!$F$8:$F$1000,"Inside",'Data Table'!$H$8:$H$1000,_xlfn.XLOOKUP(DSCountry,DS_Country_List,DS_Currency_List)) -> 0 | F8: =SUMIFS('Data Table'!$J$8:$J$1000,'Data Table'!$D$8:$D$1000,_xlfn.XLOOKUP($C8,Item_List_Number,Item_List,"",0),'Data Table'!$F$8:$F$1000,"Inside",'Data Table'!$H$8:$H$1000,"<>"&_xlfn.XLOOKUP(DSCountry,DS_Country_List,DS_Currency_List)) -> 0 | G8: USD | H8: =SUMIFS('Data Table'!$J$8:$J$1000,'Data Table'!$D$8:$D$1000,_xlfn.XLOOKUP($C8,Item_List_Number,Item_List,"",0),'Data Table'!$F$8:$F$1000,"Outside") -> 0 | I8: USD
C9: 4 | D9: Tobacco and tobacco products | E9: =SUMIFS('Data Table'!$G$8:$G$1000,'Data Table'!$D$8:$D$1000,_xlfn.XLOOKUP($C9,Item_List_Number,Item_List,"",0),'Data Table'!$F$8:$F$1000,"Inside",'Data Table'!$H$8:$H$1000,_xlfn.XLOOKUP(DSCountry,DS_Country_List,DS_Currency_List)) -> 0 | F9: =SUMIFS('Data Table'!$J$8:$J$1000,'Data Table'!$D$8:$D$1000,_xlfn.XLOOKUP($C9,Item_List_Number,Item_List,"",0),'Data Table'!$F$8:$F$1000,"Inside",'Data Table'!$H$8:$H$1000,"<>"&_xlfn.XLOOKUP(DSCountry,DS_Country_List,DS_Currency_List)) -> 0 | G9: USD | H9: =SUMIFS('Data Table'!$J$8:$J$1000,'Data Table'!$D$8:$D$1000,_xlfn.XLOOKUP($C9,Item_List_Number,Item_List,"",0),'Data Table'!$F$8:$F$1000,"Outside") -> 0 | I9: USD
C10: Clothing and Footwear
C11: 5 | D11: Cleaning, repair and tailoring of clothing | E11: =SUMIFS('Data Table'!$G$8:$G$1000,'Data Table'!$D$8:$D$1000,_xlfn.XLOOKUP($C11,Item_List_Number,Item_List,"",0),'Data Table'!$F$8:$F$1000,"Inside",'Data Table'!$H$8:$H$1000,_xlfn.XLOOKUP(DSCountry,DS_Country_List,DS_Currency_List)) -> 0 | F11: =SUMIFS('Data Table'!$J$8:$J$1000,'Data Table'!$D$8:$D$1000,_xlfn.XLOOKUP($C11,Item_List_Number,Item_List,"",0),'Data Table'!$F$8:$F$1000,"Inside",'Data Table'!$H$8:$H$1000,"<>"&_xlfn.XLOOKUP(DSCountry,DS_Country_List,DS_Currency_List)) -> 0 | G11: USD | H11: =SUMIFS('Data Table'!$J$8:$J$1000,'Data Table'!$D$8:$D$1000,_xlfn.XLOOKUP($C11,Item_List_Number,Item_List,"",0),'Data Table'!$F$8:$F$1000,"Outside") -> 0 | I11: USD
C12: Furniture, Household Equipment and Home Maintenance
C13: 6 | D13: Non-durable household goods | E13: =SUMIFS('Data Table'!$G$8:$G$1000,'Data Table'!$D$8:$D$1000,_xlfn.XLOOKUP($C13,Item_List_Number,Item_List,"",0),'Data Table'!$F$8:$F$1000,"Inside",'Data Table'!$H$8:$H$1000,_xlfn.XLOOKUP(DSCountry,DS_Country_List,DS_Currency_List)) -> 0 | F13: =SUMIFS('Data Table'!$J$8:$J$1000,'Data Table'!$D$8:$D$1000,_xlfn.XLOOKUP($C13,Item_List_Number,Item_List,"",0),'Data Table'!$F$8:$F$1000,"Inside",'Data Table'!$H$8:$H$1000,"<>"&_xlfn.XLOOKUP(DSCountry,DS_Country_List,DS_Currency_List)) -> 0 | G13: USD | H13: =SUMIFS('Data Table'!$J$8:$J$1000,'Data Table'!$D$8:$D$1000,_xlfn.XLOOKUP($C13,Item_List_Number,Item_List,"",0),'Data Table'!$F$8:$F$1000,"Outside") -> 0 | I13: USD
C14: Health (Not Covered by Insurance, Out-of-Pocket)
C15: 7 | D15: Medicine | E15: =SUMIFS('Data Table'!$G$8:$G$1000,'Data Table'!$D$8:$D$1000,_xlfn.XLOOKUP($C15,Item_List_Number,Item_List,"",0),'Data Table'!$F$8:$F$1000,"Inside",'Data Table'!$H$8:$H$1000,_xlfn.XLOOKUP(DSCountry,DS_Country_List,DS_Currency_List)) -> 0 | F15: =SUMIFS('Data Table'!$J$8:$J$1000,'Data Table'!$D$8:$D$1000,_xlfn.XLOOKUP($C15,Item_List_Number,Item_List,"",0),'Data Table'!$F$8:$F$1000,"Inside",'Data Table'!$H$8:$H$1000,"<>"&_xlfn.XLOOKUP(DSCountry,DS_Country_List,DS_Currency_List)) -> 0 | G15: USD | H15: =SUMIFS('Data Table'!$J$8:$J$1000,'Data Table'!$D$8:$D$1000,_xlfn.XLOOKUP($C15,Item_List_Number,Item_List,"",0),'Data Table'!$F$8:$F$1000,"Outside") -> 0 | I15: USD
C16: Transport Purchases
C17: 8 | D17: Fuels and lubricants for personal transport | E17: =SUMIFS('Data Table'!$G$8:$G$1000,'Data Table'!$D$8:$D$1000,_xlfn.XLOOKUP($C17,Item_List_Number,Item_List,"",0),'Data Table'!$F$8:$F$1000,"Inside",'Data Table'!$H$8:$H$1000,_xlfn.XLOOKUP(DSCountry,DS_Country_List,DS_Currency_List)) -> 0 | F17: =SUMIFS('Data Table'!$J$8:$J$1000,'Data Table'!$D$8:$D$1000,_xlfn.XLOOKUP($C17,Item_List_Number,Item_List,"",0),'Data Table'!$F$8:$F$1000,"Inside",'Data Table'!$H$8:$H$1000,"<>"&_xlfn.XLOOKUP(DSCountry,DS_Country_List,DS_Currency_List)) -> 0 | G17: USD | H17: =SUMIFS('Data Table'!$J$8:$J$1000,'Data Table'!$D$8:$D$1000,_xlfn.XLOOKUP($C17,Item_List_Number,Item_List,"",0),'Data Table'!$F$8:$F$1000,"Outside") -> 0 | I17: USD
C18: 9 | D18: Public transport and taxi services | E18: =SUMIFS('Data Table'!$G$8:$G$1000,'Data Table'!$D$8:$D$1000,_xlfn.XLOOKUP($C18,Item_List_Number,Item_List,"",0),'Data Table'!$F$8:$F$1000,"Inside",'Data Table'!$H$8:$H$1000,_xlfn.XLOOKUP(DSCountry,DS_Country_List,DS_Currency_List)) -> 0 | F18: =SUMIFS('Data Table'!$J$8:$J$1000,'Data Table'!$D$8:$D$1000,_xlfn.XLOOKUP($C18,Item_List_Number,Item_List,"",0),'Data Table'!$F$8:$F$1000,"Inside",'Data Table'!$H$8:$H$1000,"<>"&_xlfn.XLOOKUP(DSCountry,DS_Country_List,DS_Currency_List)) -> 0 | G18: USD | H18: =SUMIFS('Data Table'!$J$8:$J$1000,'Data Table'!$D$8:$D$1000,_xlfn.XLOOKUP($C18,Item_List_Number,Item_List,"",0),'Data Table'!$F$8:$F$1000,"Outside") -> 0 | I18: USD
C19: 10 | D19: Postal and courier services | E19: =SUMIFS('Data Table'!$G$8:$G$1000,'Data Table'!$D$8:$D$1000,_xlfn.XLOOKUP($C19,Item_List_Number,Item_List,"",0),'Data Table'!$F$8:$F$1000,"Inside",'Data Table'!$H$8:$H$1000,_xlfn.XLOOKUP(DSCountry,DS_Country_List,DS_Currency_List)) -> 0 | F19: =SUMIFS('Data Table'!$J$8:$J$1000,'Data Table'!$D$8:$D$1000,_xlfn.XLOOKUP($C19,Item_List_Number,Item_List,"",0),'Data Table'!$F$8:$F$1000,"Inside",'Data Table'!$H$8:$H$1000,"<>"&_xlfn.XLOOKUP(DSCountry,DS_Country_List,DS_Currency_List)) -> 0 | G19: USD | H19: =SUMIFS('Data Table'!$J$8:$J$1000,'Data Table'!$D$8:$D$1000,_xlfn.XLOOKUP($C19,Item_List_Number,Item_List,"",0),'Data Table'!$F$8:$F$1000,"Outside") -> 0 | I19: USD
C20: 11 | D20: Other transport of goods (removal and storage services, delivery, etc) | E20: =SUMIFS('Data Table'!$G$8:$G$1000,'Data Table'!$D$8:$D$1000,_xlfn.XLOOKUP($C20,Item_List_Number,Item_List,"",0),'Data Table'!$F$8:$F$1000,"Inside",'Data Table'!$H$8:$H$1000,_xlfn.XLOOKUP(DSCountry,DS_Country_List,DS_Currency_List)) -> 0 | F20: =SUMIFS('Data Table'!$J$8:$J$1000,'Data Table'!$D$8:$D$1000,_xlfn.XLOOKUP($C20,Item_List_Number,Item_List,"",0),'Data Table'!$F$8:$F$1000,"Inside",'Data Table'!$H$8:$H$1000,"<>"&_xlfn.XLOOKUP(DSCountry,DS_Country_List,DS_Currency_List)) -> 0 | G20: USD | H20: =SUMIFS('Data Table'!$J$8:$J$1000,'Data Table'!$D$8:$D$1000,_xlfn.XLOOKUP($C20,Item_List_Number,Item_List,"",0),'Data Table'!$F$8:$F$1000,"Outside") -> 0 | I20: USD
C21: Information and Communication
C22: 12 | D22: Information and communication services | E22: =SUMIFS('Data Table'!$G$8:$G$1000,'Data Table'!$D$8:$D$1000,_xlfn.XLOOKUP($C22,Item_List_Number,Item_List,"",0),'Data Table'!$F$8:$F$1000,"Inside",'Data Table'!$H$8:$H$1000,_xlfn.XLOOKUP(DSCountry,DS_Country_List,DS_Currency_List)) -> 0 | F22: =SUMIFS('Data Table'!$J$8:$J$1000,'Data Table'!$D$8:$D$1000,_xlfn.XLOOKUP($C22,Item_List_Number,Item_List,"",0),'Data Table'!$F$8:$F$1000,"Inside",'Data Table'!$H$8:$H$1000,"<>"&_xlfn.XLOOKUP(DSCountry,DS_Country_List,DS_Currency_List)) -> 0 | G22: USD | H22: =SUMIFS('Data Table'!$J$8:$J$1000,'Data Table'!$D$8:$D$1000,_xlfn.XLOOKUP($C22,Item_List_Number,Item_List,"",0),'Data Table'!$F$8:$F$1000,"Outside") -> 0 | I22: USD
C23: Recreation, Sport and Culture
C24: 13 | D24: Pets and pet products | E24: =SUMIFS('Data Table'!$G$8:$G$1000,'Data Table'!$D$8:$D$1000,_xlfn.XLOOKUP($C24,Item_List_Number,Item_List,"",0),'Data Table'!$F$8:$F$1000,"Inside",'Data Table'!$H$8:$H$1000,_xlfn.XLOOKUP(DSCountry,DS_Country_List,DS_Currency_List)) -> 0 | F24: =SUMIFS('Data Table'!$J$8:$J$1000,'Data Table'!$D$8:$D$1000,_xlfn.XLOOKUP($C24,Item_List_Number,Item_List,"",0),'Data Table'!$F$8:$F$1000,"Inside",'Data Table'!$H$8:$H$1000,"<>"&_xlfn.XLOOKUP(DSCountry,DS_Country_List,DS_Currency_List)) -> 0 | G24: USD | H24: =SUMIFS('Data Table'!$J$8:$J$1000,'Data Table'!$D$8:$D$1000,_xlfn.XLOOKUP($C24,Item_List_Number,Item_List,"",0),'Data Table'!$F$8:$F$1000,"Outside") -> 0 | I24: USD
C25: 14 | D25: Veterinary and other services for pets | E25: =SUMIFS('Data Table'!$G$8:$G$1000,'Data Table'!$D$8:$D$1000,_xlfn.XLOOKUP($C25,Item_List_Number,Item_List,"",0),'Data Table'!$F$8:$F$1000,"Inside",'Data Table'!$H$8:$H$1000,_xlfn.XLOOKUP(DSCountry,DS_Country_List,DS_Currency_List)) -> 0 | F25: =SUMIFS('Data Table'!$J$8:$J$1000,'Data Table'!$D$8:$D$1000,_xlfn.XLOOKUP($C25,Item_List_Number,Item_List,"",0),'Data Table'!$F$8:$F$1000,"Inside",'Data Table'!$H$8:$H$1000,"<>"&_xlfn.XLOOKUP(DSCountry,DS_Country_List,DS_Currency_List)) -> 0 | G25: USD | H25: =SUMIFS('Data Table'!$J$8:$J$1000,'Data Table'!$D$8:$D$1000,_xlfn.XLOOKUP($C25,Item_List_Number,Item_List,"",0),'Data Table'!$F$8:$F$1000,"Outside") -> 0 | I25: USD
C26: 15 | D26: Cultural services | E26: =SUMIFS('Data Table'!$G$8:$G$1000,'Data Table'!$D$8:$D$1000,_xlfn.XLOOKUP($C26,Item_List_Number,Item_List,"",0),'Data Table'!$F$8:$F$1000,"Inside",'Data Table'!$H$8:$H$1000,_xlfn.XLOOKUP(DSCountry,DS_Country_List,DS_Currency_List)) -> 0 | F26: =SUMIFS('Data Table'!$J$8:$J$1000,'Data Table'!$D$8:$D$1000,_xlfn.XLOOKUP($C26,Item_List_Number,Item_List,"",0),'Data Table'!$F$8:$F$1000,"Inside",'Data Table'!$H$8:$H$1000,"<>"&_xlfn.XLOOKUP(DSCountry,DS_Country_List,DS_Currency_List)) -> 0 | G26: USD | H26: =SUMIFS('Data Table'!$J$8:$J$1000,'Data Table'!$D$8:$D$1000,_xlfn.XLOOKUP($C26,Item_List_Number,Item_List,"",0),'Data Table'!$F$8:$F$1000,"Outside") -> 0 | I26: USD
C27: 16 | D27: Recreational and sporting services | E27: =SUMIFS('Data Table'!$G$8:$G$1000,'Data Table'!$D$8:$D$1000,_xlfn.XLOOKUP($C27,Item_List_Number,Item_List,"",0),'Data Table'!$F$8:$F$1000,"Inside",'Data Table'!$H$8:$H$1000,_xlfn.XLOOKUP(DSCountry,DS_Country_List,DS_Currency_List)) -> 0 | F27: =SUMIFS('Data Table'!$J$8:$J$1000,'Data Table'!$D$8:$D$1000,_xlfn.XLOOKUP($C27,Item_List_Number,Item_List,"",0),'Data Table'!$F$8:$F$1000,"Inside",'Data Table'!$H$8:$H$1000,"<>"&_xlfn.XLOOKUP(DSCountry,DS_Country_List,DS_Currency_List)) -> 0 | G27: USD | H27: =SUMIFS('Data Table'!$J$8:$J$1000,'Data Table'!$D$8:$D$1000,_xlfn.XLOOKUP($C27,Item_List_Number,Item_List,"",0),'Data Table'!$F$8:$F$1000,"Outside") -> 0 | I27: USD
C28: 17 | D28: Newspapers, books and stationery | E28: =SUMIFS('Data Table'!$G$8:$G$1000,'Data Table'!$D$8:$D$1000,_xlfn.XLOOKUP($C28,Item_List_Number,Item_List,"",0),'Data Table'!$F$8:$F$1000,"Inside",'Data Table'!$H$8:$H$1000,_xlfn.XLOOKUP(DSCountry,DS_Country_List,DS_Currency_List)) -> 0 | F28: =SUMIFS('Data Table'!$J$8:$J$1000,'Data Table'!$D$8:$D$1000,_xlfn.XLOOKUP($C28,Item_List_Number,Item_List,"",0),'Data Table'!$F$8:$F$1000,"Inside",'Data Table'!$H$8:$H$1000,"<>"&_xlfn.XLOOKUP(DSCountry,DS_Country_List,DS_Currency_List)) -> 0 | G28: USD | H28: =SUMIFS('Data Table'!$J$8:$J$1000,'Data Table'!$D$8:$D$1000,_xlfn.XLOOKUP($C28,Item_List_Number,Item_List,"",0),'Data Table'!$F$8:$F$1000,"Outside") -> 0 | I28: USD
C29: Restaurants and Accommodation Services
C30: 18 | D30: Restaurants, cafes and similar eating facilities | E30: =SUMIFS('Data Table'!$G$8:$G$1000,'Data Table'!$D$8:$D$1000,_xlfn.XLOOKUP($C30,Item_List_Number,Item_List,"",0),'Data Table'!$F$8:$F$1000,"Inside",'Data Table'!$H$8:$H$1000,_xlfn.XLOOKUP(DSCountry,DS_Country_List,DS_Currency_List)) -> 0 | F30: =SUMIFS('Data Table'!$J$8:$J$1000,'Data Table'!$D$8:$D$1000,_xlfn.XLOOKUP($C30,Item_List_Number,Item_List,"",0),'Data Table'!$F$8:$F$1000,"Inside",'Data Table'!$H$8:$H$1000,"<>"&_xlfn.XLOOKUP(DSCountry,DS_Country_List,DS_Currency_List)) -> 0 | G30: USD | H30: =SUMIFS('Data Table'!$J$8:$J$1000,'Data Table'!$D$8:$D$1000,_xlfn.XLOOKUP($C30,Item_List_Number,Item_List,"",0),'Data Table'!$F$8:$F$1000,"Outside") -> 0 | I30: USD
C31: 19 | D31: Canteens, cafeterias and refectories | E31: =SUMIFS('Data Table'!$G$8:$G$1000,'Data Table'!$D$8:$D$1000,_xlfn.XLOOKUP($C31,Item_List_Number,Item_List,"",0),'Data Table'!$F$8:$F$1000,"Inside",'Data Table'!$H$8:$H$1000,_xlfn.XLOOKUP(DSCountry,DS_Country_List,DS_Currency_List)) -> 0 | F31: =SUMIFS('Data Table'!$J$8:$J$1000,'Data Table'!$D$8:$D$1000,_xlfn.XLOOKUP($C31,Item_List_Number,Item_List,"",0),'Data Table'!$F$8:$F$1000,"Inside",'Data Table'!$H$8:$H$1000,"<>"&_xlfn.XLOOKUP(DSCountry,DS_Country_List,DS_Currency_List)) -> 0 | G31: USD | H31: =SUMIFS('Data Table'!$J$8:$J$1000,'Data Table'!$D$8:$D$1000,_xlfn.XLOOKUP($C31,Item_List_Number,Item_List,"",0),'Data Table'!$F$8:$F$1000,"Outside") -> 0 | I31: USD
C32: Insurance and Financial Services
C33: 20 | D33: Insurance connected with health (supplementary medical insurance) | E33: =SUMIFS('Data Table'!$G$8:$G$1000,'Data Table'!$D$8:$D$1000,_xlfn.XLOOKUP($C33,Item_List_Number,Item_List,"",0),'Data Table'!$F$8:$F$1000,"Inside",'Data Table'!$H$8:$H$1000,_xlfn.XLOOKUP(DSCountry,DS_Country_List,DS_Currency_List)) -> 0 | F33: =SUMIFS('Data Table'!$J$8:$J$1000,'Data Table'!$D$8:$D$1000,_xlfn.XLOOKUP($C33,Item_List_Number,Item_List,"",0),'Data Table'!$F$8:$F$1000,"Inside",'Data Table'!$H$8:$H$1000,"<>"&_xlfn.XLOOKUP(DSCountry,DS_Country_List,DS_Currency_List)) -> 0 | G33: USD | H33: =SUMIFS('Data Table'!$J$8:$J$1000,'Data Table'!$D$8:$D$1000,_xlfn.XLOOKUP($C33,Item_List_Number,Item_List,"",0),'Data Table'!$F$8:$F$1000,"Outside") -> 0 | I33: USD
C34: 21 | D34: Insurance connected with transport | E34: =SUMIFS('Data Table'!$G$8:$G$1000,'Data Table'!$D$8:$D$1000,_xlfn.XLOOKUP($C34,Item_List_Number,Item_List,"",0),'Data Table'!$F$8:$F$1000,"Inside",'Data Table'!$H$8:$H$1000,_xlfn.XLOOKUP(DSCountry,DS_Country_List,DS_Currency_List)) -> 0 | F34: =SUMIFS('Data Table'!$J$8:$J$1000,'Data Table'!$D$8:$D$1000,_xlfn.XLOOKUP($C34,Item_List_Number,Item_List,"",0),'Data Table'!$F$8:$F$1000,"Inside",'Data Table'!$H$8:$H$1000,"<>"&_xlfn.XLOOKUP(DSCountry,DS_Country_List,DS_Currency_List)) -> 0 | G34: USD | H34: =SUMIFS('Data Table'!$J$8:$J$1000,'Data Table'!$D$8:$D$1000,_xlfn.XLOOKUP($C34,Item_List_Number,Item_List,"",0),'Data Table'!$F$8:$F$1000,"Outside") -> 0 | I34: USD
C35: 22 | D35: Insurance connected with dwelling | E35: =SUMIFS('Data Table'!$G$8:$G$1000,'Data Table'!$D$8:$D$1000,_xlfn.XLOOKUP($C35,Item_List_Number,Item_List,"",0),'Data Table'!$F$8:$F$1000,"Inside",'Data Table'!$H$8:$H$1000,_xlfn.XLOOKUP(DSCountry,DS_Country_List,DS_Currency_List)) -> 0 | F35: =SUMIFS('Data Table'!$J$8:$J$1000,'Data Table'!$D$8:$D$1000,_xlfn.XLOOKUP($C35,Item_List_Number,Item_List,"",0),'Data Table'!$F$8:$F$1000,"Inside",'Data Table'!$H$8:$H$1000,"<>"&_xlfn.XLOOKUP(DSCountry,DS_Country_List,DS_Currency_List)) -> 0 | G35: USD | H35: =SUMIFS('Data Table'!$J$8:$J$1000,'Data Table'!$D$8:$D$1000,_xlfn.XLOOKUP($C35,Item_List_Number,Item_List,"",0),'Data Table'!$F$8:$F$1000,"Outside") -> 0 | I35: USD
C36: Personal Care, Social Protection and Miscellaneous Goods and Services
C37: 23 | D37: Hairdressing salons and personal grooming establishments | E37: =SUMIFS('Data Table'!$G$8:$G$1000,'Data Table'!$D$8:$D$1000,_xlfn.XLOOKUP($C37,Item_List_Number,Item_List,"",0),'Data Table'!$F$8:$F$1000,"Inside",'Data Table'!$H$8:$H$1000,_xlfn.XLOOKUP(DSCountry,DS_Country_List,DS_Currency_List)) -> 0 | F37: =SUMIFS('Data Table'!$J$8:$J$1000,'Data Table'!$D$8:$D$1000,_xlfn.XLOOKUP($C37,Item_List_Number,Item_List,"",0),'Data Table'!$F$8:$F$1000,"Inside",'Data Table'!$H$8:$H$1000,"<>"&_xlfn.XLOOKUP(DSCountry,DS_Country_List,DS_Currency_List)) -> 0 | G37: USD | H37: =SUMIFS('Data Table'!$J$8:$J$1000,'Data Table'!$D$8:$D$1000,_xlfn.XLOOKUP($C37,Item_List_Number,Item_List,"",0),'Data Table'!$F$8:$F$1000,"Outside") -> 0 | I37: USD
C38: Other Expenditures
C39: 24 | D39: Remittances except medical and educational expenses | E39: =SUMIFS('Data Table'!$G$8:$G$1000,'Data Table'!$D$8:$D$1000,_xlfn.XLOOKUP($C39,Item_List_Number,Item_List,"",0),'Data Table'!$F$8:$F$1000,"Inside",'Data Table'!$H$8:$H$1000,_xlfn.XLOOKUP(DSCountry,DS_Country_List,DS_Currency_List)) -> 0 | F39: =SUMIFS('Data Table'!$J$8:$J$1000,'Data Table'!$D$8:$D$1000,_xlfn.XLOOKUP($C39,Item_List_Number,Item_List,"",0),'Data Table'!$F$8:$F$1000,"Inside",'Data Table'!$H$8:$H$1000,"<>"&_xlfn.XLOOKUP(DSCountry,DS_Country_List,DS_Currency_List)) -> 0 | G39: USD | H39: =SUMIFS('Data Table'!$J$8:$J$1000,'Data Table'!$D$8:$D$1000,_xlfn.XLOOKUP($C39,Item_List_Number,Item_List,"",0),'Data Table'!$F$8:$F$1000,"Outside") -> 0 | I39: USD
C40: 25 | D40: Other monthly expenditures | E40: =SUMIFS('Data Table'!$G$8:$G$1000,'Data Table'!$D$8:$D$1000,_xlfn.XLOOKUP($C40,Item_List_Number,Item_List,"",0),'Data Table'!$F$8:$F$1000,"Inside",'Data Table'!$H$8:$H$1000,_xlfn.XLOOKUP(DSCountry,DS_Country_List,DS_Currency_List)) -> 0 | F40: =SUMIFS('Data Table'!$J$8:$J$1000,'Data Table'!$D$8:$D$1000,_xlfn.XLOOKUP($C40,Item_List_Number,Item_List,"",0),'Data Table'!$F$8:$F$1000,"Inside",'Data Table'!$H$8:$H$1000,"<>"&_xlfn.XLOOKUP(DSCountry,DS_Country_List,DS_Currency_List)) -> 0 | G40: USD | H40: =SUMIFS('Data Table'!$J$8:$J$1000,'Data Table'!$D$8:$D$1000,_xlfn.XLOOKUP($C40,Item_List_Number,Item_List,"",0),'Data Table'!$F$8:$F$1000,"Outside") -> 0 | I40: USD
C41: Housing Expenditures and Domestic and Security Services
C42: H.D | D42: Domestic and security services | E42: =SUMIFS('Data Table'!$G$8:$G$1000,'Data Table'!$D$8:$D$1000,_xlfn.XLOOKUP($C42,Item_List_Number,Item_List,"",0),'Data Table'!$F$8:$F$1000,"Inside",'Data Table'!$H$8:$H$1000,_xlfn.XLOOKUP(DSCountry,DS_Country_List,DS_Currency_List)) -> 0 | F42: =SUMIFS('Data Table'!$J$8:$J$1000,'Data Table'!$D$8:$D$1000,_xlfn.XLOOKUP($C42,Item_List_Number,Item_List,"",0),'Data Table'!$F$8:$F$1000,"Inside",'Data Table'!$H$8:$H$1000,"<>"&_xlfn.XLOOKUP(DSCountry,DS_Country_List,DS_Currency_List)) -> 0 | G42: USD | H42: =SUMIFS('Data Table'!$J$8:$J$1000,'Data Table'!$D$8:$D$1000,_xlfn.XLOOKUP($C42,Item_List_Number,Item_List,"",0),'Data Table'!$F$8:$F$1000,"Outside") -> 0 | I42: USD
C43: H.R | D43: Rent or rent equivalent (if homeowner) | E43: =SUMIFS('Data Table'!$G$8:$G$1000,'Data Table'!$D$8:$D$1000,_xlfn.XLOOKUP($C43,Item_List_Number,Item_List,"",0),'Data Table'!$F$8:$F$1000,"Inside",'Data Table'!$H$8:$H$1000,_xlfn.XLOOKUP(DSCountry,DS_Country_List,DS_Currency_List)) -> 0 | F43: =SUMIFS('Data Table'!$J$8:$J$1000,'Data Table'!$D$8:$D$1000,_xlfn.XLOOKUP($C43,Item_List_Number,Item_List,"",0),'Data Table'!$F$8:$F$1000,"Inside",'Data Table'!$H$8:$H$1000,"<>"&_xlfn.XLOOKUP(DSCountry,DS_Country_List,DS_Currency_List)) -> 0 | G43: USD | H43: =SUMIFS('Data Table'!$J$8:$J$1000,'Data Table'!$D$8:$D$1000,_xlfn.XLOOKUP($C43,Item_List_Number,Item_List,"",0),'Data Table'!$F$8:$F$1000,"Outside") -> 0 | I43: USD
C44: H.U | D44: Utilities and other dwelling costs NOT included in rent | E44: =SUMIFS('Data Table'!$G$8:$G$1000,'Data Table'!$D$8:$D$1000,_xlfn.XLOOKUP($C44,Item_List_Number,Item_List,"",0),'Data Table'!$F$8:$F$1000,"Inside",'Data Table'!$H$8:$H$1000,_xlfn.XLOOKUP(DSCountry,DS_Country_List,DS_Currency_List)) -> 0 | F44: =SUMIFS('Data Table'!$J$8:$J$1000,'Data Table'!$D$8:$D$1000,_xlfn.XLOOKUP($C44,Item_List_Number,Item_List,"",0),'Data Table'!$F$8:$F$1000,"Inside",'Data Table'!$H$8:$H$1000,"<>"&_xlfn.XLOOKUP(DSCountry,DS_Country_List,DS_Currency_List)) -> 0 | G44: USD | H44: =SUMIFS('Data Table'!$J$8:$J$1000,'Data Table'!$D$8:$D$1000,_xlfn.XLOOKUP($C44,Item_List_Number,Item_List,"",0),'Data Table'!$F$8:$F$1000,"Outside") -> 0 | I44: USD

Sheet Yearly and Education Expenses
D2: ICSC Electronic Diary for Yearly Expenditures and Education | E2: INSIDE COUNTRY OF DUTY STATION | H2: OUTSIDE COUNTRY OF DUTY STATION
E3: =IF(ISBLANK(DSCountry),"Specify country in Data Table","Amount Spent in Local Currency ("&(_xlfn.XLOOKUP(DSCountry,DS_Country_List,DS_Currency_List))&")") -> Amount Spent in Local Currency (AUD) | F3: Amount Spent in Other Currency (Expressed in USD) | H3: Amount Spent (Expressed in USD)
C4: Clothing and Footwear
C5: 26 | D5: Clothing garments | E5: =SUMIFS('Data Table'!$G$8:$G$1000,'Data Table'!$D$8:$D$1000,_xlfn.XLOOKUP($C5,Item_List_Number,Item_List,"",0),'Data Table'!$F$8:$F$1000,"Inside",'Data Table'!$H$8:$H$1000,_xlfn.XLOOKUP(DSCountry,DS_Country_List,DS_Currency_List)) -> 0 | F5: =SUMIFS('Data Table'!$J$8:$J$1000,'Data Table'!$D$8:$D$1000,_xlfn.XLOOKUP($C5,Item_List_Number,Item_List,"",0),'Data Table'!$F$8:$F$1000,"Inside",'Data Table'!$H$8:$H$1000,"<>"&_xlfn.XLOOKUP(DSCountry,DS_Country_List,DS_Currency_List)) -> 0 | G5: USD | H5: =SUMIFS('Data Table'!$J$8:$J$1000,'Data Table'!$D$8:$D$1000,_xlfn.XLOOKUP($C5,Item_List_Number,Item_List,"",0),'Data Table'!$F$8:$F$1000,"Outside") -> 0 | I5: USD
C6: 27 | D6: Other articles of clothing and clothing accessories | E6: =SUMIFS('Data Table'!$G$8:$G$1000,'Data Table'!$D$8:$D$1000,_xlfn.XLOOKUP($C6,Item_List_Number,Item_List,"",0),'Data Table'!$F$8:$F$1000,"Inside",'Data Table'!$H$8:$H$1000,_xlfn.XLOOKUP(DSCountry,DS_Country_List,DS_Currency_List)) -> 0 | F6: =SUMIFS('Data Table'!$J$8:$J$1000,'Data Table'!$D$8:$D$1000,_xlfn.XLOOKUP($C6,Item_List_Number,Item_List,"",0),'Data Table'!$F$8:$F$1000,"Inside",'Data Table'!$H$8:$H$1000,"<>"&_xlfn.XLOOKUP(DSCountry,DS_Country_List,DS_Currency_List)) -> 0 | G6: USD | H6: =SUMIFS('Data Table'!$J$8:$J$1000,'Data Table'!$D$8:$D$1000,_xlfn.XLOOKUP($C6,Item_List_Number,Item_List,"",0),'Data Table'!$F$8:$F$1000,"Outside") -> 0 | I6: USD
C7: 28 | D7: Shoes and other footwear | E7: =SUMIFS('Data Table'!$G$8:$G$1000,'Data Table'!$D$8:$D$1000,_xlfn.XLOOKUP($C7,Item_List_Number,Item_List,"",0),'Data Table'!$F$8:$F$1000,"Inside",'Data Table'!$H$8:$H$1000,_xlfn.XLOOKUP(DSCountry,DS_Country_List,DS_Currency_List)) -> 0 | F7: =SUMIFS('Data Table'!$J$8:$J$1000,'Data Table'!$D$8:$D$1000,_xlfn.XLOOKUP($C7,Item_List_Number,Item_List,"",0),'Data Table'!$F$8:$F$1000,"Inside",'Data Table'!$H$8:$H$1000,"<>"&_xlfn.XLOOKUP(DSCountry,DS_Country_List,DS_Currency_List)) -> 0 | G7: USD | H7: =SUMIFS('Data Table'!$J$8:$J$1000,'Data Table'!$D$8:$D$1000,_xlfn.XLOOKUP($C7,Item_List_Number,Item_List,"",0),'Data Table'!$F$8:$F$1000,"Outside") -> 0 | I7: USD
C8: Furniture, Household Equipment, Maintenance
C9: 29 | D9: Furniture, furnishings and loose carpets | E9: =SUMIFS('Data Table'!$G$8:$G$1000,'Data Table'!$D$8:$D$1000,_xlfn.XLOOKUP($C9,Item_List_Number,Item_List,"",0),'Data Table'!$F$8:$F$1000,"Inside",'Data Table'!$H$8:$H$1000,_xlfn.XLOOKUP(DSCountry,DS_Country_List,DS_Currency_List)) -> 0 | F9: =SUMIFS('Data Table'!$J$8:$J$1000,'Data Table'!$D$8:$D$1000,_xlfn.XLOOKUP($C9,Item_List_Number,Item_List,"",0),'Data Table'!$F$8:$F$1000,"Inside",'Data Table'!$H$8:$H$1000,"<>"&_xlfn.XLOOKUP(DSCountry,DS_Country_List,DS_Currency_List)) -> 0 | G9: USD | H9: =SUMIFS('Data Table'!$J$8:$J$1000,'Data Table'!$D$8:$D$1000,_xlfn.XLOOKUP($C9,Item_List_Number,Item_List,"",0),'Data Table'!$F$8:$F$1000,"Outside") -> 0 | I9: USD
C10: 30 | D10: Households textiles | E10: =SUMIFS('Data Table'!$G$8:$G$1000,'Data Table'!$D$8:$D$1000,_xlfn.XLOOKUP($C10,Item_List_Number,Item_List,"",0),'Data Table'!$F$8:$F$1000,"Inside",'Data Table'!$H$8:$H$1000,_xlfn.XLOOKUP(DSCountry,DS_Country_List,DS_Currency_List)) -> 0 | F10: =SUMIFS('Data Table'!$J$8:$J$1000,'Data Table'!$D$8:$D$1000,_xlfn.XLOOKUP($C10,Item_List_Number,Item_List,"",0),'Data Table'!$F$8:$F$1000,"Inside",'Data Table'!$H$8:$H$1000,"<>"&_xlfn.XLOOKUP(DSCountry,DS_Country_List,DS_Currency_List)) -> 0 | G10: USD | H10: =SUMIFS('Data Table'!$J$8:$J$1000,'Data Table'!$D$8:$D$1000,_xlfn.XLOOKUP($C10,Item_List_Number,Item_List,"",0),'Data Table'!$F$8:$F$1000,"Outside") -> 0 | I10: USD
C11: 31 | D11: Small household appliances | E11: =SUMIFS('Data Table'!$G$8:$G$1000,'Data Table'!$D$8:$D$1000,_xlfn.XLOOKUP($C11,Item_List_Number,Item_List,"",0),'Data Table'!$F$8:$F$1000,"Inside",'Data Table'!$H$8:$H$1000,_xlfn.XLOOKUP(DSCountry,DS_Country_List,DS_Currency_List)) -> 0 | F11: =SUMIFS('Data Table'!$J$8:$J$1000,'Data Table'!$D$8:$D$1000,_xlfn.XLOOKUP($C11,Item_List_Number,Item_List,"",0),'Data Table'!$F$8:$F$1000,"Inside",'Data Table'!$H$8:$H$1000,"<>"&_xlfn.XLOOKUP(DSCountry,DS_Country_List,DS_Currency_List)) -> 0 | G11: USD | H11: =SUMIFS('Data Table'!$J$8:$J$1000,'Data Table'!$D$8:$D$1000,_xlfn.XLOOKUP($C11,Item_List_Number,Item_List,"",0),'Data Table'!$F$8:$F$1000,"Outside") -> 0 | I11: USD
C12: 32 | D12: Glassware, tableware and household utensils | E12: =SUMIFS('Data Table'!$G$8:$G$1000,'Data Table'!$D$8:$D$1000,_xlfn.XLOOKUP($C12,Item_List_Number,Item_List,"",0),'Data Table'!$F$8:$F$1000,"Inside",'Data Table'!$H$8:$H$1000,_xlfn.XLOOKUP(DSCountry,DS_Country_List,DS_Currency_List)) -> 0 | F12: =SUMIFS('Data Table'!$J$8:$J$1000,'Data Table'!$D$8:$D$1000,_xlfn.XLOOKUP($C12,Item_List_Number,Item_List,"",0),'Data Table'!$F$8:$F$1000,"Inside",'Data Table'!$H$8:$H$1000,"<>"&_xlfn.XLOOKUP(DSCountry,DS_Country_List,DS_Currency_List)) -> 0 | G12: USD | H12: =SUMIFS('Data Table'!$J$8:$J$1000,'Data Table'!$D$8:$D$1000,_xlfn.XLOOKUP($C12,Item_List_Number,Item_List,"",0),'Data Table'!$F$8:$F$1000,"Outside") -> 0 | I12: USD
C13: 33 | D13: Tools and equipment for house and garden | E13: =SUMIFS('Data Table'!$G$8:$G$1000,'Data Table'!$D$8:$D$1000,_xlfn.XLOOKUP($C13,Item_List_Number,Item_List,"",0),'Data Table'!$F$8:$F$1000,"Inside",'Data Table'!$H$8:$H$1000,_xlfn.XLOOKUP(DSCountry,DS_Country_List,DS_Currency_List)) -> 0 | F13: =SUMIFS('Data Table'!$J$8:$J$1000,'Data Table'!$D$8:$D$1000,_xlfn.XLOOKUP($C13,Item_List_Number,Item_List,"",0),'Data Table'!$F$8:$F$1000,"Inside",'Data Table'!$H$8:$H$1000,"<>"&_xlfn.XLOOKUP(DSCountry,DS_Country_List,DS_Currency_List)) -> 0 | G13: USD | H13: =SUMIFS('Data Table'!$J$8:$J$1000,'Data Table'!$D$8:$D$1000,_xlfn.XLOOKUP($C13,Item_List_Number,Item_List,"",0),'Data Table'!$F$8:$F$1000,"Outside") -> 0 | I13: USD
C14: Health (Not Covered by Insurance, Out-of-Pocket)
C15: 34 | D15: Medical products | E15: =SUMIFS('Data Table'!$G$8:$G$1000,'Data Table'!$D$8:$D$1000,_xlfn.XLOOKUP($C15,Item_List_Number,Item_List,"",0),'Data Table'!$F$8:$F$1000,"Inside",'Data Table'!$H$8:$H$1000,_xlfn.XLOOKUP(DSCountry,DS_Country_List,DS_Currency_List)) -> 0 | F15: =SUMIFS('Data Table'!$J$8:$J$1000,'Data Table'!$D$8:$D$1000,_xlfn.XLOOKUP($C15,Item_List_Number,Item_List,"",0),'Data Table'!$F$8:$F$1000,"Inside",'Data Table'!$H$8:$H$1000,"<>"&_xlfn.XLOOKUP(DSCountry,DS_Country_List,DS_Currency_List)) -> 0 | G15: USD | H15: =SUMIFS('Data Table'!$J$8:$J$1000,'Data Table'!$D$8:$D$1000,_xlfn.XLOOKUP($C15,Item_List_Number,Item_List,"",0),'Data Table'!$F$8:$F$1000,"Outside") -> 0 | I15: USD
C16: 35 | D16: Assistive products | E16: =SUMIFS('Data Table'!$G$8:$G$1000,'Data Table'!$D$8:$D$1000,_xlfn.XLOOKUP($C16,Item_List_Number,Item_List,"",0),'Data Table'!$F$8:$F$1000,"Inside",'Data Table'!$H$8:$H$1000,_xlfn.XLOOKUP(DSCountry,DS_Country_List,DS_Currency_List)) -> 0 | F16: =SUMIFS('Data Table'!$J$8:$J$1000,'Data Table'!$D$8:$D$1000,_xlfn.XLOOKUP($C16,Item_List_Number,Item_List,"",0),'Data Table'!$F$8:$F$1000,"Inside",'Data Table'!$H$8:$H$1000,"<>"&_xlfn.XLOOKUP(DSCountry,DS_Country_List,DS_Currency_List)) -> 0 | G16: USD | H16: =SUMIFS('Data Table'!$J$8:$J$1000,'Data Table'!$D$8:$D$1000,_xlfn.XLOOKUP($C16,Item_List_Number,Item_List,"",0),'Data Table'!$F$8:$F$1000,"Outside") -> 0 | I16: USD
C17: 36 | D17: Outpatient care services | E17: =SUMIFS('Data Table'!$G$8:$G$1000,'Data Table'!$D$8:$D$1000,_xlfn.XLOOKUP($C17,Item_List_Number,Item_List,"",0),'Data Table'!$F$8:$F$1000,"Inside",'Data Table'!$H$8:$H$1000,_xlfn.XLOOKUP(DSCountry,DS_Country_List,DS_Currency_List)) -> 0 | F17: =SUMIFS('Data Table'!$J$8:$J$1000,'Data Table'!$D$8:$D$1000,_xlfn.XLOOKUP($C17,Item_List_Number,Item_List,"",0),'Data Table'!$F$8:$F$1000,"Inside",'Data Table'!$H$8:$H$1000,"<>"&_xlfn.XLOOKUP(DSCountry,DS_Country_List,DS_Currency_List)) -> 0 | G17: USD | H17: =SUMIFS('Data Table'!$J$8:$J$1000,'Data Table'!$D$8:$D$1000,_xlfn.XLOOKUP($C17,Item_List_Number,Item_List,"",0),'Data Table'!$F$8:$F$1000,"Outside") -> 0 | I17: USD
C18: 37 | D18: In-patient care services | E18: =SUMIFS('Data Table'!$G$8:$G$1000,'Data Table'!$D$8:$D$1000,_xlfn.XLOOKUP($C18,Item_List_Number,Item_List,"",0),'Data Table'!$F$8:$F$1000,"Inside",'Data Table'!$H$8:$H$1000,_xlfn.XLOOKUP(DSCountry,DS_Country_List,DS_Currency_List)) -> 0 | F18: =SUMIFS('Data Table'!$J$8:$J$1000,'Data Table'!$D$8:$D$1000,_xlfn.XLOOKUP($C18,Item_List_Number,Item_List,"",0),'Data Table'!$F$8:$F$1000,"Inside",'Data Table'!$H$8:$H$1000,"<>"&_xlfn.XLOOKUP(DSCountry,DS_Country_List,DS_Currency_List)) -> 0 | G18: USD | H18: =SUMIFS('Data Table'!$J$8:$J$1000,'Data Table'!$D$8:$D$1000,_xlfn.XLOOKUP($C18,Item_List_Number,Item_List,"",0),'Data Table'!$F$8:$F$1000,"Outside") -> 0 | I18: USD
C19: Transport Purchases
C20: 38 | D20: Parts and accessories for personal transport equipment | E20: =SUMIFS('Data Table'!$G$8:$G$1000,'Data Table'!$D$8:$D$1000,_xlfn.XLOOKUP($C20,Item_List_Number,Item_List,"",0),'Data Table'!$F$8:$F$1000,"Inside",'Data Table'!$H$8:$H$1000,_xlfn.XLOOKUP(DSCountry,DS_Country_List,DS_Currency_List)) -> 0 | F20: =SUMIFS('Data Table'!$J$8:$J$1000,'Data Table'!$D$8:$D$1000,_xlfn.XLOOKUP($C20,Item_List_Number,Item_List,"",0),'Data Table'!$F$8:$F$1000,"Inside",'Data Table'!$H$8:$H$1000,"<>"&_xlfn.XLOOKUP(DSCountry,DS_Country_List,DS_Currency_List)) -> 0 | G20: USD | H20: =SUMIFS('Data Table'!$J$8:$J$1000,'Data Table'!$D$8:$D$1000,_xlfn.XLOOKUP($C20,Item_List_Number,Item_List,"",0),'Data Table'!$F$8:$F$1000,"Outside") -> 0 | I20: USD
C21: 39 | D21: Maintenance and repair of personal transport equipment | E21: =SUMIFS('Data Table'!$G$8:$G$1000,'Data Table'!$D$8:$D$1000,_xlfn.XLOOKUP($C21,Item_List_Number,Item_List,"",0),'Data Table'!$F$8:$F$1000,"Inside",'Data Table'!$H$8:$H$1000,_xlfn.XLOOKUP(DSCountry,DS_Country_List,DS_Currency_List)) -> 0 | F21: =SUMIFS('Data Table'!$J$8:$J$1000,'Data Table'!$D$8:$D$1000,_xlfn.XLOOKUP($C21,Item_List_Number,Item_List,"",0),'Data Table'!$F$8:$F$1000,"Inside",'Data Table'!$H$8:$H$1000,"<>"&_xlfn.XLOOKUP(DSCountry,DS_Country_List,DS_Currency_List)) -> 0 | G21: USD | H21: =SUMIFS('Data Table'!$J$8:$J$1000,'Data Table'!$D$8:$D$1000,_xlfn.XLOOKUP($C21,Item_List_Number,Item_List,"",0),'Data Table'!$F$8:$F$1000,"Outside") -> 0 | I21: USD
C22: 40 | D22: Other services related to personal transport equipment | E22: =SUMIFS('Data Table'!$G$8:$G$1000,'Data Table'!$D$8:$D$1000,_xlfn.XLOOKUP($C22,Item_List_Number,Item_List,"",0),'Data Table'!$F$8:$F$1000,"Inside",'Data Table'!$H$8:$H$1000,_xlfn.XLOOKUP(DSCountry,DS_Country_List,DS_Currency_List)) -> 0 | F22: =SUMIFS('Data Table'!$J$8:$J$1000,'Data Table'!$D$8:$D$1000,_xlfn.XLOOKUP($C22,Item_List_Number,Item_List,"",0),'Data Table'!$F$8:$F$1000,"Inside",'Data Table'!$H$8:$H$1000,"<>"&_xlfn.XLOOKUP(DSCountry,DS_Country_List,DS_Currency_List)) -> 0 | G22: USD | H22: =SUMIFS('Data Table'!$J$8:$J$1000,'Data Table'!$D$8:$D$1000,_xlfn.XLOOKUP($C22,Item_List_Number,Item_List,"",0),'Data Table'!$F$8:$F$1000,"Outside") -> 0 | I22: USD
C23: 41 | D23: Air Travel | E23: =SUMIFS('Data Table'!$G$8:$G$1000,'Data Table'!$D$8:$D$1000,_xlfn.XLOOKUP($C23,Item_List_Number,Item_List,"",0),'Data Table'!$F$8:$F$1000,"Inside",'Data Table'!$H$8:$H$1000,_xlfn.XLOOKUP(DSCountry,DS_Country_List,DS_Currency_List)) -> 0 | F23: =SUMIFS('Data Table'!$J$8:$J$1000,'Data Table'!$D$8:$D$1000,_xlfn.XLOOKUP($C23,Item_List_Number,Item_List,"",0),'Data Table'!$F$8:$F$1000,"Inside",'Data Table'!$H$8:$H$1000,"<>"&_xlfn.XLOOKUP(DSCountry,DS_Country_List,DS_Currency_List)) -> 0 | G23: USD | H23: =SUMIFS('Data Table'!$J$8:$J$1000,'Data Table'!$D$8:$D$1000,_xlfn.XLOOKUP($C23,Item_List_Number,Item_List,"",0),'Data Table'!$F$8:$F$1000,"Outside") -> 0 | I23: USD
C24: Information and Communication
C25: 42 | D25: Information and communication equipment | E25: =SUMIFS('Data Table'!$G$8:$G$1000,'Data Table'!$D$8:$D$1000,_xlfn.XLOOKUP($C25,Item_List_Number,Item_List,"",0),'Data Table'!$F$8:$F$1000,"Inside",'Data Table'!$H$8:$H$1000,_xlfn.XLOOKUP(DSCountry,DS_Country_List,DS_Currency_List)) -> 0 | F25: =SUMIFS('Data Table'!$J$8:$J$1000,'Data Table'!$D$8:$D$1000,_xlfn.XLOOKUP($C25,Item_List_Number,Item_List,"",0),'Data Table'!$F$8:$F$1000,"Inside",'Data Table'!$H$8:$H$1000,"<>"&_xlfn.XLOOKUP(DSCountry,DS_Country_List,DS_Currency_List)) -> 0 | G25: USD | H25: =SUMIFS('Data Table'!$J$8:$J$1000,'Data Table'!$D$8:$D$1000,_xlfn.XLOOKUP($C25,Item_List_Number,Item_List,"",0),'Data Table'!$F$8:$F$1000,"Outside") -> 0 | I25: USD
C26: Recreation and Culture
C27: 43 | D27: Sport, camping and open-air equipment | E27: =SUMIFS('Data Table'!$G$8:$G$1000,'Data Table'!$D$8:$D$1000,_xlfn.XLOOKUP($C27,Item_List_Number,Item_List,"",0),'Data Table'!$F$8:$F$1000,"Inside",'Data Table'!$H$8:$H$1000,_xlfn.XLOOKUP(DSCountry,DS_Country_List,DS_Currency_List)) -> 0 | F27: =SUMIFS('Data Table'!$J$8:$J$1000,'Data Table'!$D$8:$D$1000,_xlfn.XLOOKUP($C27,Item_List_Number,Item_List,"",0),'Data Table'!$F$8:$F$1000,"Inside",'Data Table'!$H$8:$H$1000,"<>"&_xlfn.XLOOKUP(DSCountry,DS_Country_List,DS_Currency_List)) -> 0 | G27: USD | H27: =SUMIFS('Data Table'!$J$8:$J$1000,'Data Table'!$D$8:$D$1000,_xlfn.XLOOKUP($C27,Item_List_Number,Item_List,"",0),'Data Table'!$F$8:$F$1000,"Outside") -> 0 | I27: USD
C28: 44 | D28: Games, toys and hobby-related articles | E28: =SUMIFS('Data Table'!$G$8:$G$1000,'Data Table'!$D$8:$D$1000,_xlfn.XLOOKUP($C28,Item_List_Number,Item_List,"",0),'Data Table'!$F$8:$F$1000,"Inside",'Data Table'!$H$8:$H$1000,_xlfn.XLOOKUP(DSCountry,DS_Country_List,DS_Currency_List)) -> 0 | F28: =SUMIFS('Data Table'!$J$8:$J$1000,'Data Table'!$D$8:$D$1000,_xlfn.XLOOKUP($C28,Item_List_Number,Item_List,"",0),'Data Table'!$F$8:$F$1000,"Inside",'Data Table'!$H$8:$H$1000,"<>"&_xlfn.XLOOKUP(DSCountry,DS_Country_List,DS_Currency_List)) -> 0 | G28: USD | H28: =SUMIFS('Data Table'!$J$8:$J$1000,'Data Table'!$D$8:$D$1000,_xlfn.XLOOKUP($C28,Item_List_Number,Item_List,"",0),'Data Table'!$F$8:$F$1000,"Outside") -> 0 | I28: USD
C29: 45 | D29: Garden products, plants and flowers | E29: =SUMIFS('Data Table'!$G$8:$G$1000,'Data Table'!$D$8:$D$1000,_xlfn.XLOOKUP($C29,Item_List_Number,Item_List,"",0),'Data Table'!$F$8:$F$1000,"Inside",'Data Table'!$H$8:$H$1000,_xlfn.XLOOKUP(DSCountry,DS_Country_List,DS_Currency_List)) -> 0 | F29: =SUMIFS('Data Table'!$J$8:$J$1000,'Data Table'!$D$8:$D$1000,_xlfn.XLOOKUP($C29,Item_List_Number,Item_List,"",0),'Data Table'!$F$8:$F$1000,"Inside",'Data Table'!$H$8:$H$1000,"<>"&_xlfn.XLOOKUP(DSCountry,DS_Country_List,DS_Currency_List)) -> 0 | G29: USD | H29: =SUMIFS('Data Table'!$J$8:$J$1000,'Data Table'!$D$8:$D$1000,_xlfn.XLOOKUP($C29,Item_List_Number,Item_List,"",0),'Data Table'!$F$8:$F$1000,"Outside") -> 0 | I29: USD
C30: 46 | D30: Package holidays | E30: =SUMIFS('Data Table'!$G$8:$G$1000,'Data Table'!$D$8:$D$1000,_xlfn.XLOOKUP($C30,Item_List_Number,Item_List,"",0),'Data Table'!$F$8:$F$1000,"Inside",'Data Table'!$H$8:$H$1000,_xlfn.XLOOKUP(DSCountry,DS_Country_List,DS_Currency_List)) -> 0 | F30: =SUMIFS('Data Table'!$J$8:$J$1000,'Data Table'!$D$8:$D$1000,_xlfn.XLOOKUP($C30,Item_List_Number,Item_List,"",0),'Data Table'!$F$8:$F$1000,"Inside",'Data Table'!$H$8:$H$1000,"<>"&_xlfn.XLOOKUP(DSCountry,DS_Country_List,DS_Currency_List)) -> 0 | G30: USD | H30: =SUMIFS('Data Table'!$J$8:$J$1000,'Data Table'!$D$8:$D$1000,_xlfn.XLOOKUP($C30,Item_List_Number,Item_List,"",0),'Data Table'!$F$8:$F$1000,"Outside") -> 0 | I30: USD
C31: Restaurants and Accommodation Services
C32: 47 | D32: Accommodation services | E32: =SUMIFS('Data Table'!$G$8:$G$1000,'Data Table'!$D$8:$D$1000,_xlfn.XLOOKUP($C32,Item_List_Number,Item_List,"",0),'Data Table'!$F$8:$F$1000,"Inside",'Data Table'!$H$8:$H$1000,_xlfn.XLOOKUP(DSCountry,DS_Country_List,DS_Currency_List)) -> 0 | F32: =SUMIFS('Data Table'!$J$8:$J$1000,'Data Table'!$D$8:$D$1000,_xlfn.XLOOKUP($C32,Item_List_Number,Item_List,"",0),'Data Table'!$F$8:$F$1000,"Inside",'Data Table'!$H$8:$H$1000,"<>"&_xlfn.XLOOKUP(DSCountry,DS_Country_List,DS_Currency_List)) -> 0 | G32: USD | H32: =SUMIFS('Data Table'!$J$8:$J$1000,'Data Table'!$D$8:$D$1000,_xlfn.XLOOKUP($C32,Item_List_Number,Item_List,"",0),'Data Table'!$F$8:$F$1000,"Outside") -> 0 | I32: USD
C33: Insurance and Financial Services
C34: 48 | D34: Financial services | E34: =SUMIFS('Data Table'!$G$8:$G$1000,'Data Table'!$D$8:$D$1000,_xlfn.XLOOKUP($C34,Item_List_Number,Item_List,"",0),'Data Table'!$F$8:$F$1000,"Inside",'Data Table'!$H$8:$H$1000,_xlfn.XLOOKUP(DSCountry,DS_Country_List,DS_Currency_List)) -> 0 | F34: =SUMIFS('Data Table'!$J$8:$J$1000,'Data Table'!$D$8:$D$1000,_xlfn.XLOOKUP($C34,Item_List_Number,Item_List,"",0),'Data Table'!$F$8:$F$1000,"Inside",'Data Table'!$H$8:$H$1000,"<>"&_xlfn.XLOOKUP(DSCountry,DS_Country_List,DS_Currency_List)) -> 0 | G34: USD | H34: =SUMIFS('Data Table'!$J$8:$J$1000,'Data Table'!$D$8:$D$1000,_xlfn.XLOOKUP($C34,Item_List_Number,Item_List,"",0),'Data Table'!$F$8:$F$1000,"Outside") -> 0 | I34: USD
C35: Personal Care, Social Protection and Miscellaneous Goods and Services
C36: 49a | D36: Electric appliances for personal care | E36: =SUMIFS('Data Table'!$G$8:$G$1000,'Data Table'!$D$8:$D$1000,_xlfn.XLOOKUP($C36,Item_List_Number,Item_List,"",0),'Data Table'!$F$8:$F$1000,"Inside",'Data Table'!$H$8:$H$1000,_xlfn.XLOOKUP(DSCountry,DS_Country_List,DS_Currency_List)) -> 0 | F36: =SUMIFS('Data Table'!$J$8:$J$1000,'Data Table'!$D$8:$D$1000,_xlfn.XLOOKUP($C36,Item_List_Number,Item_List,"",0),'Data Table'!$F$8:$F$1000,"Inside",'Data Table'!$H$8:$H$1000,"<>"&_xlfn.XLOOKUP(DSCountry,DS_Country_List,DS_Currency_List)) -> 0 | G36: USD | H36: =SUMIFS('Data Table'!$J$8:$J$1000,'Data Table'!$D$8:$D$1000,_xlfn.XLOOKUP($C36,Item_List_Number,Item_List,"",0),'Data Table'!$F$8:$F$1000,"Outside") -> 0 | I36: USD
C37: 49b | D37: Other appliances, articles and products for personal care | E37: =SUMIFS('Data Table'!$G$8:$G$1000,'Data Table'!$D$8:$D$1000,_xlfn.XLOOKUP($C37,Item_List_Number,Item_List,"",0),'Data Table'!$F$8:$F$1000,"Inside",'Data Table'!$H$8:$H$1000,_xlfn.XLOOKUP(DSCountry,DS_Country_List,DS_Currency_List)) -> 0 | F37: =SUMIFS('Data Table'!$J$8:$J$1000,'Data Table'!$D$8:$D$1000,_xlfn.XLOOKUP($C37,Item_List_Number,Item_List,"",0),'Data Table'!$F$8:$F$1000,"Inside",'Data Table'!$H$8:$H$1000,"<>"&_xlfn.XLOOKUP(DSCountry,DS_Country_List,DS_Currency_List)) -> 0 | G37: USD | H37: =SUMIFS('Data Table'!$J$8:$J$1000,'Data Table'!$D$8:$D$1000,_xlfn.XLOOKUP($C37,Item_List_Number,Item_List,"",0),'Data Table'!$F$8:$F$1000,"Outside") -> 0 | I37: USD
C38: 50a | D38: Social protection | E38: =SUMIFS('Data Table'!$G$8:$G$1000,'Data Table'!$D$8:$D$1000,_xlfn.XLOOKUP($C38,Item_List_Number,Item_List,"",0),'Data Table'!$F$8:$F$1000,"Inside",'Data Table'!$H$8:$H$1000,_xlfn.XLOOKUP(DSCountry,DS_Country_List,DS_Currency_List)) -> 0 | F38: =SUMIFS('Data Table'!$J$8:$J$1000,'Data Table'!$D$8:$D$1000,_xlfn.XLOOKUP($C38,Item_List_Number,Item_List,"",0),'Data Table'!$F$8:$F$1000,"Inside",'Data Table'!$H$8:$H$1000,"<>"&_xlfn.XLOOKUP(DSCountry,DS_Country_List,DS_Currency_List)) -> 0 | G38: USD | H38: =SUMIFS('Data Table'!$J$8:$J$1000,'Data Table'!$D$8:$D$1000,_xlfn.XLOOKUP($C38,Item_List_Number,Item_List,"",0),'Data Table'!$F$8:$F$1000,"Outside") -> 0 | I38: USD
C39: 50b | D39: Other personal effects | E39: =SUMIFS('Data Table'!$G$8:$G$1000,'Data Table'!$D$8:$D$1000,_xlfn.XLOOKUP($C39,Item_List_Number,Item_List,"",0),'Data Table'!$F$8:$F$1000,"Inside",'Data Table'!$H$8:$H$1000,_xlfn.XLOOKUP(DSCountry,DS_Country_List,DS_Currency_List)) -> 0 | F39: =SUMIFS('Data Table'!$J$8:$J$1000,'Data Table'!$D$8:$D$1000,_xlfn.XLOOKUP($C39,Item_List_Number,Item_List,"",0),'Data Table'!$F$8:$F$1000,"Inside",'Data Table'!$H$8:$H$1000,"<>"&_xlfn.XLOOKUP(DSCountry,DS_Country_List,DS_Currency_List)) -> 0 | G39: USD | H39: =SUMIFS('Data Table'!$J$8:$J$1000,'Data Table'!$D$8:$D$1000,_xlfn.XLOOKUP($C39,Item_List_Number,Item_List,"",0),'Data Table'!$F$8:$F$1000,"Outside") -> 0 | I39: USD
C40: 50c | D40: Other services | E40: =SUMIFS('Data Table'!$G$8:$G$1000,'Data Table'!$D$8:$D$1000,_xlfn.XLOOKUP($C40,Item_List_Number,Item_List,"",0),'Data Table'!$F$8:$F$1000,"Inside",'Data Table'!$H$8:$H$1000,_xlfn.XLOOKUP(DSCountry,DS_Country_List,DS_Currency_List)) -> 0 | F40: =SUMIFS('Data Table'!$J$8:$J$1000,'Data Table'!$D$8:$D$1000,_xlfn.XLOOKUP($C40,Item_List_Number,Item_List,"",0),'Data Table'!$F$8:$F$1000,"Inside",'Data Table'!$H$8:$H$1000,"<>"&_xlfn.XLOOKUP(DSCountry,DS_Country_List,DS_Currency_List)) -> 0 | G40: USD | H40: =SUMIFS('Data Table'!$J$8:$J$1000,'Data Table'!$D$8:$D$1000,_xlfn.XLOOKUP($C40,Item_List_Number,Item_List,"",0),'Data Table'!$F$8:$F$1000,"Outside") -> 0 | I40: USD
C41: Other
C42: 51 | D42: Other yearly expenditures | E42: =SUMIFS('Data Table'!$G$8:$G$1000,'Data Table'!$D$8:$D$1000,_xlfn.XLOOKUP($C42,Item_List_Number,Item_List,"",0),'Data Table'!$F$8:$F$1000,"Inside",'Data Table'!$H$8:$H$1000,_xlfn.XLOOKUP(DSCountry,DS_Country_List,DS_Currency_List)) -> 0 | F42: =SUMIFS('Data Table'!$J$8:$J$1000,'Data Table'!$D$8:$D$1000,_xlfn.XLOOKUP($C42,Item_List_Number,Item_List,"",0),'Data Table'!$F$8:$F$1000,"Inside",'Data Table'!$H$8:$H$1000,"<>"&_xlfn.XLOOKUP(DSCountry,DS_Country_List,DS_Currency_List)) -> 0 | G42: USD | H42: =SUMIFS('Data Table'!$J$8:$J$1000,'Data Table'!$D$8:$D$1000,_xlfn.XLOOKUP($C42,Item_List_Number,Item_List,"",0),'Data Table'!$F$8:$F$1000,"Outside") -> 0 | I42: USD
C43: Education Services: Tuition and Enrollment Fees for Education Other than Tertiary Level
C44: 52a | D44: Tuition and enrolment fees excluding capital assessment/surcharges | E44: =SUMIFS('Data Table'!$G$8:$G$1000,'Data Table'!$D$8:$D$1000,_xlfn.XLOOKUP($C44,Item_List_Number,Item_List,"",0),'Data Table'!$F$8:$F$1000,"Inside",'Data Table'!$H$8:$H$1000,_xlfn.XLOOKUP(DSCountry,DS_Country_List,DS_Currency_List)) -> 0 | F44: =SUMIFS('Data Table'!$J$8:$J$1000,'Data Table'!$D$8:$D$1000,_xlfn.XLOOKUP($C44,Item_List_Number,Item_List,"",0),'Data Table'!$F$8:$F$1000,"Inside",'Data Table'!$H$8:$H$1000,"<>"&_xlfn.XLOOKUP(DSCountry,DS_Country_List,DS_Currency_List)) -> 0 | G44: USD | H44: =SUMIFS('Data Table'!$J$8:$J$1000,'Data Table'!$D$8:$D$1000,_xlfn.XLOOKUP($C44,Item_List_Number,Item_List,"",0),'Data Table'!$F$8:$F$1000,"Outside") -> 0 | I44: USD
C45: 52b | D45: Accommodation services of boarding schools and other educational establishments | E45: =SUMIFS('Data Table'!$G$8:$G$1000,'Data Table'!$D$8:$D$1000,_xlfn.XLOOKUP($C45,Item_List_Number,Item_List,"",0),'Data Table'!$F$8:$F$1000,"Inside",'Data Table'!$H$8:$H$1000,_xlfn.XLOOKUP(DSCountry,DS_Country_List,DS_Currency_List)) -> 0 | F45: =SUMIFS('Data Table'!$J$8:$J$1000,'Data Table'!$D$8:$D$1000,_xlfn.XLOOKUP($C45,Item_List_Number,Item_List,"",0),'Data Table'!$F$8:$F$1000,"Inside",'Data Table'!$H$8:$H$1000,"<>"&_xlfn.XLOOKUP(DSCountry,DS_Country_List,DS_Currency_List)) -> 0 | G45: USD | H45: =SUMIFS('Data Table'!$J$8:$J$1000,'Data Table'!$D$8:$D$1000,_xlfn.XLOOKUP($C45,Item_List_Number,Item_List,"",0),'Data Table'!$F$8:$F$1000,"Outside") -> 0 | I45: USD
C46: 52c | D46: Canteens and cafeterias of universities, schools and kindergartens | E46: =SUMIFS('Data Table'!$G$8:$G$1000,'Data Table'!$D$8:$D$1000,_xlfn.XLOOKUP($C46,Item_List_Number,Item_List,"",0),'Data Table'!$F$8:$F$1000,"Inside",'Data Table'!$H$8:$H$1000,_xlfn.XLOOKUP(DSCountry,DS_Country_List,DS_Currency_List)) -> 0 | F46: =SUMIFS('Data Table'!$J$8:$J$1000,'Data Table'!$D$8:$D$1000,_xlfn.XLOOKUP($C46,Item_List_Number,Item_List,"",0),'Data Table'!$F$8:$F$1000,"Inside",'Data Table'!$H$8:$H$1000,"<>"&_xlfn.XLOOKUP(DSCountry,DS_Country_List,DS_Currency_List)) -> 0 | G46: USD | H46: =SUMIFS('Data Table'!$J$8:$J$1000,'Data Table'!$D$8:$D$1000,_xlfn.XLOOKUP($C46,Item_List_Number,Item_List,"",0),'Data Table'!$F$8:$F$1000,"Outside") -> 0 | I46: USD
C47: 52d | D47: Educational books and textbooks | E47: =SUMIFS('Data Table'!$G$8:$G$1000,'Data Table'!$D$8:$D$1000,_xlfn.XLOOKUP($C47,Item_List_Number,Item_List,"",0),'Data Table'!$F$8:$F$1000,"Inside",'Data Table'!$H$8:$H$1000,_xlfn.XLOOKUP(DSCountry,DS_Country_List,DS_Currency_List)) -> 0 | F47: =SUMIFS('Data Table'!$J$8:$J$1000,'Data Table'!$D$8:$D$1000,_xlfn.XLOOKUP($C47,Item_List_Number,Item_List,"",0),'Data Table'!$F$8:$F$1000,"Inside",'Data Table'!$H$8:$H$1000,"<>"&_xlfn.XLOOKUP(DSCountry,DS_Country_List,DS_Currency_List)) -> 0 | G47: USD | H47: =SUMIFS('Data Table'!$J$8:$J$1000,'Data Table'!$D$8:$D$1000,_xlfn.XLOOKUP($C47,Item_List_Number,Item_List,"",0),'Data Table'!$F$8:$F$1000,"Outside") -> 0 | I47: USD
C48: 52e | D48: Passenger transport for students to and from school | E48: =SUMIFS('Data Table'!$G$8:$G$1000,'Data Table'!$D$8:$D$1000,_xlfn.XLOOKUP($C48,Item_List_Number,Item_List,"",0),'Data Table'!$F$8:$F$1000,"Inside",'Data Table'!$H$8:$H$1000,_xlfn.XLOOKUP(DSCountry,DS_Country_List,DS_Currency_List)) -> 0 | F48: =SUMIFS('Data Table'!$J$8:$J$1000,'Data Table'!$D$8:$D$1000,_xlfn.XLOOKUP($C48,Item_List_Number,Item_List,"",0),'Data Table'!$F$8:$F$1000,"Inside",'Data Table'!$H$8:$H$1000,"<>"&_xlfn.XLOOKUP(DSCountry,DS_Country_List,DS_Currency_List)) -> 0 | G48: USD | H48: =SUMIFS('Data Table'!$J$8:$J$1000,'Data Table'!$D$8:$D$1000,_xlfn.XLOOKUP($C48,Item_List_Number,Item_List,"",0),'Data Table'!$F$8:$F$1000,"Outside") -> 0 | I48: USD
C49: 52f | D49: Childcare services | E49: =SUMIFS('Data Table'!$G$8:$G$1000,'Data Table'!$D$8:$D$1000,_xlfn.XLOOKUP($C49,Item_List_Number,Item_List,"",0),'Data Table'!$F$8:$F$1000,"Inside",'Data Table'!$H$8:$H$1000,_xlfn.XLOOKUP(DSCountry,DS_Country_List,DS_Currency_List)) -> 0 | F49: =SUMIFS('Data Table'!$J$8:$J$1000,'Data Table'!$D$8:$D$1000,_xlfn.XLOOKUP($C49,Item_List_Number,Item_List,"",0),'Data Table'!$F$8:$F$1000,"Inside",'Data Table'!$H$8:$H$1000,"<>"&_xlfn.XLOOKUP(DSCountry,DS_Country_List,DS_Currency_List)) -> 0 | G49: USD | H49: =SUMIFS('Data Table'!$J$8:$J$1000,'Data Table'!$D$8:$D$1000,_xlfn.XLOOKUP($C49,Item_List_Number,Item_List,"",0),'Data Table'!$F$8:$F$1000,"Outside") -> 0 | I49: USD
C50: 52g | D50: Recreational and leisure services and other cultural services | E50: =SUMIFS('Data Table'!$G$8:$G$1000,'Data Table'!$D$8:$D$1000,_xlfn.XLOOKUP($C50,Item_List_Number,Item_List,"",0),'Data Table'!$F$8:$F$1000,"Inside",'Data Table'!$H$8:$H$1000,_xlfn.XLOOKUP(DSCountry,DS_Country_List,DS_Currency_List)) -> 0 | F50: =SUMIFS('Data Table'!$J$8:$J$1000,'Data Table'!$D$8:$D$1000,_xlfn.XLOOKUP($C50,Item_List_Number,Item_List,"",0),'Data Table'!$F$8:$F$1000,"Inside",'Data Table'!$H$8:$H$1000,"<>"&_xlfn.XLOOKUP(DSCountry,DS_Country_List,DS_Currency_List)) -> 0 | G50: USD | H50: =SUMIFS('Data Table'!$J$8:$J$1000,'Data Table'!$D$8:$D$1000,_xlfn.XLOOKUP($C50,Item_List_Number,Item_List,"",0),'Data Table'!$F$8:$F$1000,"Outside") -> 0 | I50: USD
C51: Tertiary Education
C52: 53a | D52: Tuition and enrolment fees excluding capital assessment/surcharges | E52: =SUMIFS('Data Table'!$G$8:$G$1000,'Data Table'!$D$8:$D$1000,_xlfn.XLOOKUP($C52,Item_List_Number,Item_List,"",0),'Data Table'!$F$8:$F$1000,"Inside",'Data Table'!$H$8:$H$1000,_xlfn.XLOOKUP(DSCountry,DS_Country_List,DS_Currency_List)) -> 0 | F52: =SUMIFS('Data Table'!$J$8:$J$1000,'Data Table'!$D$8:$D$1000,_xlfn.XLOOKUP($C52,Item_List_Number,Item_List,"",0),'Data Table'!$F$8:$F$1000,"Inside",'Data Table'!$H$8:$H$1000,"<>"&_xlfn.XLOOKUP(DSCountry,DS_Country_List,DS_Currency_List)) -> 0 | G52: USD | H52: =SUMIFS('Data Table'!$J$8:$J$1000,'Data Table'!$D$8:$D$1000,_xlfn.XLOOKUP($C52,Item_List_Number,Item_List,"",0),'Data Table'!$F$8:$F$1000,"Outside") -> 0 | I52: USD
C53: 53b | D53: Accommodation services of boarding schools, universities, etc | E53: =SUMIFS('Data Table'!$G$8:$G$1000,'Data Table'!$D$8:$D$1000,_xlfn.XLOOKUP($C53,Item_List_Number,Item_List,"",0),'Data Table'!$F$8:$F$1000,"Inside",'Data Table'!$H$8:$H$1000,_xlfn.XLOOKUP(DSCountry,DS_Country_List,DS_Currency_List)) -> 0 | F53: =SUMIFS('Data Table'!$J$8:$J$1000,'Data Table'!$D$8:$D$1000,_xlfn.XLOOKUP($C53,Item_List_Number,Item_List,"",0),'Data Table'!$F$8:$F$1000,"Inside",'Data Table'!$H$8:$H$1000,"<>"&_xlfn.XLOOKUP(DSCountry,DS_Country_List,DS_Currency_List)) -> 0 | G53: USD | H53: =SUMIFS('Data Table'!$J$8:$J$1000,'Data Table'!$D$8:$D$1000,_xlfn.XLOOKUP($C53,Item_List_Number,Item_List,"",0),'Data Table'!$F$8:$F$1000,"Outside") -> 0 | I53: USD
C54: 53c | D54: Canteens and cafeterias of universities, schools and kindergartens | E54: =SUMIFS('Data Table'!$G$8:$G$1000,'Data Table'!$D$8:$D$1000,_xlfn.XLOOKUP($C54,Item_List_Number,Item_List,"",0),'Data Table'!$F$8:$F$1000,"Inside",'Data Table'!$H$8:$H$1000,_xlfn.XLOOKUP(DSCountry,DS_Country_List,DS_Currency_List)) -> 0 | F54: =SUMIFS('Data Table'!$J$8:$J$1000,'Data Table'!$D$8:$D$1000,_xlfn.XLOOKUP($C54,Item_List_Number,Item_List,"",0),'Data Table'!$F$8:$F$1000,"Inside",'Data Table'!$H$8:$H$1000,"<>"&_xlfn.XLOOKUP(DSCountry,DS_Country_List,DS_Currency_List)) -> 0 | G54: USD | H54: =SUMIFS('Data Table'!$J$8:$J$1000,'Data Table'!$D$8:$D$1000,_xlfn.XLOOKUP($C54,Item_List_Number,Item_List,"",0),'Data Table'!$F$8:$F$1000,"Outside") -> 0 | I54: USD
C55: 53d | D55: Educational books and textbooks | E55: =SUMIFS('Data Table'!$G$8:$G$1000,'Data Table'!$D$8:$D$1000,_xlfn.XLOOKUP($C55,Item_List_Number,Item_List,"",0),'Data Table'!$F$8:$F$1000,"Inside",'Data Table'!$H$8:$H$1000,_xlfn.XLOOKUP(DSCountry,DS_Country_List,DS_Currency_List)) -> 0 | F55: =SUMIFS('Data Table'!$J$8:$J$1000,'Data Table'!$D$8:$D$1000,_xlfn.XLOOKUP($C55,Item_List_Number,Item_List,"",0),'Data Table'!$F$8:$F$1000,"Inside",'Data Table'!$H$8:$H$1000,"<>"&_xlfn.XLOOKUP(DSCountry,DS_Country_List,DS_Currency_List)) -> 0 | G55: USD | H55: =SUMIFS('Data Table'!$J$8:$J$1000,'Data Table'!$D$8:$D$1000,_xlfn.XLOOKUP($C55,Item_List_Number,Item_List,"",0),'Data Table'!$F$8:$F$1000,"Outside") -> 0 | I55: USD
C56: 53e | D56: Passenger transport for students to and from school | E56: =SUMIFS('Data Table'!$G$8:$G$1000,'Data Table'!$D$8:$D$1000,_xlfn.XLOOKUP($C56,Item_List_Number,Item_List,"",0),'Data Table'!$F$8:$F$1000,"Inside",'Data Table'!$H$8:$H$1000,_xlfn.XLOOKUP(DSCountry,DS_Country_List,DS_Currency_List)) -> 0 | F56: =SUMIFS('Data Table'!$J$8:$J$1000,'Data Table'!$D$8:$D$1000,_xlfn.XLOOKUP($C56,Item_List_Number,Item_List,"",0),'Data Table'!$F$8:$F$1000,"Inside",'Data Table'!$H$8:$H$1000,"<>"&_xlfn.XLOOKUP(DSCountry,DS_Country_List,DS_Currency_List)) -> 0 | G56: USD | H56: =SUMIFS('Data Table'!$J$8:$J$1000,'Data Table'!$D$8:$D$1000,_xlfn.XLOOKUP($C56,Item_List_Number,Item_List,"",0),'Data Table'!$F$8:$F$1000,"Outside") -> 0 | I56: USD
C57: 53f | D57: Childcare services | E57: =SUMIFS('Data Table'!$G$8:$G$1000,'Data Table'!$D$8:$D$1000,_xlfn.XLOOKUP($C57,Item_List_Number,Item_List,"",0),'Data Table'!$F$8:$F$1000,"Inside",'Data Table'!$H$8:$H$1000,_xlfn.XLOOKUP(DSCountry,DS_Country_List,DS_Currency_List)) -> 0 | F57: =SUMIFS('Data Table'!$J$8:$J$1000,'Data Table'!$D$8:$D$1000,_xlfn.XLOOKUP($C57,Item_List_Number,Item_List,"",0),'Data Table'!$F$8:$F$1000,"Inside",'Data Table'!$H$8:$H$1000,"<>"&_xlfn.XLOOKUP(DSCountry,DS_Country_List,DS_Currency_List)) -> 0 | G57: USD | H57: =SUMIFS('Data Table'!$J$8:$J$1000,'Data Table'!$D$8:$D$1000,_xlfn.XLOOKUP($C57,Item_List_Number,Item_List,"",0),'Data Table'!$F$8:$F$1000,"Outside") -> 0 | I57: USD
C58: 53g | D58: Recreational and leisure services and other cultural services | E58: =SUMIFS('Data Table'!$G$8:$G$1000,'Data Table'!$D$8:$D$1000,_xlfn.XLOOKUP($C58,Item_List_Number,Item_List,"",0),'Data Table'!$F$8:$F$1000,"Inside",'Data Table'!$H$8:$H$1000,_xlfn.XLOOKUP(DSCountry,DS_Country_List,DS_Currency_List)) -> 0 | F58: =SUMIFS('Data Table'!$J$8:$J$1000,'Data Table'!$D$8:$D$1000,_xlfn.XLOOKUP($C58,Item_List_Number,Item_List,"",0),'Data Table'!$F$8:$F$1000,"Inside",'Data Table'!$H$8:$H$1000,"<>"&_xlfn.XLOOKUP(DSCountry,DS_Country_List,DS_Currency_List)) -> 0 | G58: USD | H58: =SUMIFS('Data Table'!$J$8:$J$1000,'Data Table'!$D$8:$D$1000,_xlfn.XLOOKUP($C58,Item_List_Number,Item_List,"",0),'Data Table'!$F$8:$F$1000,"Outside") -> 0 | I58: USD
C59: Unclassified Education
C60: 54a | D60: Tuition and enrolment fees excluding capital assessment/surcharges | E60: =SUMIFS('Data Table'!$G$8:$G$1000,'Data Table'!$D$8:$D$1000,_xlfn.XLOOKUP($C60,Item_List_Number,Item_List,"",0),'Data Table'!$F$8:$F$1000,"Inside",'Data Table'!$H$8:$H$1000,_xlfn.XLOOKUP(DSCountry,DS_Country_List,DS_Currency_List)) -> 0 | F60: =SUMIFS('Data Table'!$J$8:$J$1000,'Data Table'!$D$8:$D$1000,_xlfn.XLOOKUP($C60,Item_List_Number,Item_List,"",0),'Data Table'!$F$8:$F$1000,"Inside",'Data Table'!$H$8:$H$1000,"<>"&_xlfn.XLOOKUP(DSCountry,DS_Country_List,DS_Currency_List)) -> 0 | G60: USD | H60: =SUMIFS('Data Table'!$J$8:$J$1000,'Data Table'!$D$8:$D$1000,_xlfn.XLOOKUP($C60,Item_List_Number,Item_List,"",0),'Data Table'!$F$8:$F$1000,"Outside") -> 0 | I60: USD

Sheet Infrequent Expenses
D2: ICSC Electronic Diary for Infrequent Expenditures within Last Five Years | E2: INSIDE COUNTRY OF DUTY STATION | H2: OUTSIDE COUNTRY OF DUTY STATION
E3: =IF(ISBLANK(DSCountry),"Specify country in Data Table","Amount Spent in Local Currency ("&(_xlfn.XLOOKUP(DSCountry,DS_Country_List,DS_Currency_List))&")") -> Amount Spent in Local Currency (AUD) | F3: Amount Spent in Other Currency (Expressed in USD) | H3: Amount Spent (Expressed in USD)
C4: Furnishings, Household Equipment and Routine Household Maintenance
C5: 55 | D5: Major electric and other household appliances | E5: =SUMIFS('Data Table'!$G$8:$G$1000,'Data Table'!$D$8:$D$1000,_xlfn.XLOOKUP($C5,Item_List_Number,Item_List,"",0),'Data Table'!$F$8:$F$1000,"Inside",'Data Table'!$H$8:$H$1000,_xlfn.XLOOKUP(DSCountry,DS_Country_List,DS_Currency_List)) -> 0 | F5: =SUMIFS('Data Table'!$J$8:$J$1000,'Data Table'!$D$8:$D$1000,_xlfn.XLOOKUP($C5,Item_List_Number,Item_List,"",0),'Data Table'!$F$8:$F$1000,"Inside",'Data Table'!$H$8:$H$1000,"<>"&_xlfn.XLOOKUP(DSCountry,DS_Country_List,DS_Currency_List)) -> 0 | G5: USD | H5: =SUMIFS('Data Table'!$J$8:$J$1000,'Data Table'!$D$8:$D$1000,_xlfn.XLOOKUP($C5,Item_List_Number,Item_List,"",0),'Data Table'!$F$8:$F$1000,"Outside") -> 0 | I5: USD
C6: Recreation, Sport and Culture
C7: 56 | D7: Major recreational durables | E7: =SUMIFS('Data Table'!$G$8:$G$1000,'Data Table'!$D$8:$D$1000,_xlfn.XLOOKUP($C7,Item_List_Number,Item_List,"",0),'Data Table'!$F$8:$F$1000,"Inside",'Data Table'!$H$8:$H$1000,_xlfn.XLOOKUP(DSCountry,DS_Country_List,DS_Currency_List)) -> 0 | F7: =SUMIFS('Data Table'!$J$8:$J$1000,'Data Table'!$D$8:$D$1000,_xlfn.XLOOKUP($C7,Item_List_Number,Item_List,"",0),'Data Table'!$F$8:$F$1000,"Inside",'Data Table'!$H$8:$H$1000,"<>"&_xlfn.XLOOKUP(DSCountry,DS_Country_List,DS_Currency_List)) -> 0 | G7: USD | H7: =SUMIFS('Data Table'!$J$8:$J$1000,'Data Table'!$D$8:$D$1000,_xlfn.XLOOKUP($C7,Item_List_Number,Item_List,"",0),'Data Table'!$F$8:$F$1000,"Outside") -> 0 | I7: USD
C8: Other Personal Effects
C9: 57 | D9: Jewelry and watches | E9: =SUMIFS('Data Table'!$G$8:$G$1000,'Data Table'!$D$8:$D$1000,_xlfn.XLOOKUP($C9,Item_List_Number,Item_List,"",0),'Data Table'!$F$8:$F$1000,"Inside",'Data Table'!$H$8:$H$1000,_xlfn.XLOOKUP(DSCountry,DS_Country_List,DS_Currency_List)) -> 0 | F9: =SUMIFS('Data Table'!$J$8:$J$1000,'Data Table'!$D$8:$D$1000,_xlfn.XLOOKUP($C9,Item_List_Number,Item_List,"",0),'Data Table'!$F$8:$F$1000,"Inside",'Data Table'!$H$8:$H$1000,"<>"&_xlfn.XLOOKUP(DSCountry,DS_Country_List,DS_Currency_List)) -> 0 | G9: USD | H9: =SUMIFS('Data Table'!$J$8:$J$1000,'Data Table'!$D$8:$D$1000,_xlfn.XLOOKUP($C9,Item_List_Number,Item_List,"",0),'Data Table'!$F$8:$F$1000,"Outside") -> 0 | I9: USD
C10: Transport: Purchase and Sale of Vehicles
C11: 58a | D11: Car 1 (Net of Purchase/Sale) | E11: =SUMIFS('Data Table'!$G$8:$G$1000,'Data Table'!$D$8:$D$1000,_xlfn.XLOOKUP($C11,Item_List_Number,Item_List,"",0),'Data Table'!$F$8:$F$1000,"Inside",'Data Table'!$H$8:$H$1000,_xlfn.XLOOKUP(DSCountry,DS_Country_List,DS_Currency_List)) -> 0 | F11: =SUMIFS('Data Table'!$J$8:$J$1000,'Data Table'!$D$8:$D$1000,_xlfn.XLOOKUP($C11,Item_List_Number,Item_List,"",0),'Data Table'!$F$8:$F$1000,"Inside",'Data Table'!$H$8:$H$1000,"<>"&_xlfn.XLOOKUP(DSCountry,DS_Country_List,DS_Currency_List)) -> 0 | G11: USD | H11: =SUMIFS('Data Table'!$J$8:$J$1000,'Data Table'!$D$8:$D$1000,_xlfn.XLOOKUP($C11,Item_List_Number,Item_List,"",0),'Data Table'!$F$8:$F$1000,"Outside") -> 0 | I11: USD
C12: 58b | D12: Car 2 (Net of Purchase/Sale) | E12: =SUMIFS('Data Table'!$G$8:$G$1000,'Data Table'!$D$8:$D$1000,_xlfn.XLOOKUP($C12,Item_List_Number,Item_List,"",0),'Data Table'!$F$8:$F$1000,"Inside",'Data Table'!$H$8:$H$1000,_xlfn.XLOOKUP(DSCountry,DS_Country_List,DS_Currency_List)) -> 0 | F12: =SUMIFS('Data Table'!$J$8:$J$1000,'Data Table'!$D$8:$D$1000,_xlfn.XLOOKUP($C12,Item_List_Number,Item_List,"",0),'Data Table'!$F$8:$F$1000,"Inside",'Data Table'!$H$8:$H$1000,"<>"&_xlfn.XLOOKUP(DSCountry,DS_Country_List,DS_Currency_List)) -> 0 | G12: USD | H12: =SUMIFS('Data Table'!$J$8:$J$1000,'Data Table'!$D$8:$D$1000,_xlfn.XLOOKUP($C12,Item_List_Number,Item_List,"",0),'Data Table'!$F$8:$F$1000,"Outside") -> 0 | I12: USD
C13: 59a | D13: Other vehicle 1 (Net of Purchase/Sale) | E13: =SUMIFS('Data Table'!$G$8:$G$1000,'Data Table'!$D$8:$D$1000,_xlfn.XLOOKUP($C13,Item_List_Number,Item_List,"",0),'Data Table'!$F$8:$F$1000,"Inside",'Data Table'!$H$8:$H$1000,_xlfn.XLOOKUP(DSCountry,DS_Country_List,DS_Currency_List)) -> 0 | F13: =SUMIFS('Data Table'!$J$8:$J$1000,'Data Table'!$D$8:$D$1000,_xlfn.XLOOKUP($C13,Item_List_Number,Item_List,"",0),'Data Table'!$F$8:$F$1000,"Inside",'Data Table'!$H$8:$H$1000,"<>"&_xlfn.XLOOKUP(DSCountry,DS_Country_List,DS_Currency_List)) -> 0 | G13: USD | H13: =SUMIFS('Data Table'!$J$8:$J$1000,'Data Table'!$D$8:$D$1000,_xlfn.XLOOKUP($C13,Item_List_Number,Item_List,"",0),'Data Table'!$F$8:$F$1000,"Outside") -> 0 | I13: USD
C14: 59b | D14: Other vehicle 2 (Net of Purchase/Sale) | E14: =SUMIFS('Data Table'!$G$8:$G$1000,'Data Table'!$D$8:$D$1000,_xlfn.XLOOKUP($C14,Item_List_Number,Item_List,"",0),'Data Table'!$F$8:$F$1000,"Inside",'Data Table'!$H$8:$H$1000,_xlfn.XLOOKUP(DSCountry,DS_Country_List,DS_Currency_List)) -> 0 | F14: =SUMIFS('Data Table'!$J$8:$J$1000,'Data Table'!$D$8:$D$1000,_xlfn.XLOOKUP($C14,Item_List_Number,Item_List,"",0),'Data Table'!$F$8:$F$1000,"Inside",'Data Table'!$H$8:$H$1000,"<>"&_xlfn.XLOOKUP(DSCountry,DS_Country_List,DS_Currency_List)) -> 0 | G14: USD | H14: =SUMIFS('Data Table'!$J$8:$J$1000,'Data Table'!$D$8:$D$1000,_xlfn.XLOOKUP($C14,Item_List_Number,Item_List,"",0),'Data Table'!$F$8:$F$1000,"Outside") -> 0 | I14: USD

Sheet FX Rates
B1: {='UN Treasury'!$B$1:$BQ$1} -> 46249 | C1: 46218 | D1: 46188 | E1: 46157 | F1: 46127 | G1: 46096 | H1: 46068 | I1: 46037 | J1: 46006 | K1: 45976 | L1: 45945 | M1: 45915 | N1: 45884 | O1: 45853 | P1: 45823 | Q1: 45792 | R1: 45762 | S1: 45731 | T1: 45703 | U1: 45672 | V1: 45641 | W1: 45611 | X1: 45580 | Y1: 45550 | Z1: 45519 | AA1: 45488 | AB1: 45458 | AC1: 45427 | AD1: 45397 | AE1: 45366 | AF1: 45337 | AG1: 45306 | AH1: 45275 | AI1: 45245 | AJ1: 45214 | AK1: 45184 | AL1: 45153 | AM1: 45122 | AN1: 45092 | AO1: 45061 | AP1: 45031 | AQ1: 45000 | AR1: 44972 | AS1: 44941 | AT1: 44910 | AU1: 44880 | AV1: 44848 | AW1: 44819 | AX1: 44788 | AY1: 44757 | AZ1: 44727 | BA1: 44694 | BB1: 44665 | BC1: 44635 | BD1: 44607 | BE1: 44575 | BF1: 44545 | BG1: 44515 | BH1: 44470 | BI1: 44454 | BJ1: 44409 | BK1: 44392 | BL1: 44348 | BM1: 44317 | BN1: 44301 | BO1: 44270 | BP1: 44242 | BQ1: 44211
A2: AED | B2: =VLOOKUP($A2,'UN Treasury'!$A$1:$BQ$224,_xlfn.XMATCH(B$1,'UN Treasury'!$A$1:$BQ$1,-1,1),FALSE) -> 3.673 | C2: =VLOOKUP($A2,'UN Treasury'!$A$1:$BQ$224,_xlfn.XMATCH(C$1,'UN Treasury'!$A$1:$BQ$1,-1,1),FALSE) -> 3.673 | D2: =VLOOKUP($A2,'UN Treasury'!$A$1:$BQ$224,_xlfn.XMATCH(D$1,'UN Treasury'!$A$1:$BQ$1,-1,1),FALSE) -> 3.673 | E2: =VLOOKUP($A2,'UN Treasury'!$A$1:$BQ$224,_xlfn.XMATCH(E$1,'UN Treasury'!$A$1:$BQ$1,-1,1),FALSE) -> 3.673 | F2: =VLOOKUP($A2,'UN Treasury'!$A$1:$BQ$224,_xlfn.XMATCH(F$1,'UN Treasury'!$A$1:$BQ$1,-1,1),FALSE) -> 3.673 | G2: =VLOOKUP($A2,'UN Treasury'!$A$1:$BQ$224,_xlfn.XMATCH(G$1,'UN Treasury'!$A$1:$BQ$1,-1,1),FALSE) -> 3.673 | H2: =VLOOKUP($A2,'UN Treasury'!$A$1:$BQ$224,_xlfn.XMATCH(H$1,'UN Treasury'!$A$1:$BQ$1,-1,1),FALSE) -> 3.673 | I2: =VLOOKUP($A2,'UN Treasury'!$A$1:$BQ$224,_xlfn.XMATCH(I$1,'UN Treasury'!$A$1:$BQ$1,-1,1),FALSE) -> 3.673 | ... BQ2: =VLOOKUP($A2,'UN Treasury'!$A$1:$BQ$224,_xlfn.XMATCH(BQ$1,'UN Treasury'!$A$1:$BQ$1,-1,1),FALSE) -> 3.673
A3: AFN | B3: =VLOOKUP($A3,'UN Treasury'!$A$1:$BQ$224,_xlfn.XMATCH(B$1,'UN Treasury'!$A$1:$BQ$1,-1,1),FALSE) -> 65.008 | C3: =VLOOKUP($A3,'UN Treasury'!$A$1:$BQ$224,_xlfn.XMATCH(C$1,'UN Treasury'!$A$1:$BQ$1,-1,1),FALSE) -> 65.446 | D3: =VLOOKUP($A3,'UN Treasury'!$A$1:$BQ$224,_xlfn.XMATCH(D$1,'UN Treasury'!$A$1:$BQ$1,-1,1),FALSE) -> 63.944 | E3: =VLOOKUP($A3,'UN Treasury'!$A$1:$BQ$224,_xlfn.XMATCH(E$1,'UN Treasury'!$A$1:$BQ$1,-1,1),FALSE) -> 64.05 | F3: =VLOOKUP($A3,'UN Treasury'!$A$1:$BQ$224,_xlfn.XMATCH(F$1,'UN Treasury'!$A$1:$BQ$1,-1,1),FALSE) -> 64.394 | G3: =VLOOKUP($A3,'UN Treasury'!$A$1:$BQ$224,_xlfn.XMATCH(G$1,'UN Treasury'!$A$1:$BQ$1,-1,1),FALSE) -> 63.489 | H3: =VLOOKUP($A3,'UN Treasury'!$A$1:$BQ$224,_xlfn.XMATCH(H$1,'UN Treasury'!$A$1:$BQ$1,-1,1),FALSE) -> 63.717 | I3: =VLOOKUP($A3,'UN Treasury'!$A$1:$BQ$224,_xlfn.XMATCH(I$1,'UN Treasury'!$A$1:$BQ$1,-1,1),FALSE) -> 66.079 | ... BQ3: =VLOOKUP($A3,'UN Treasury'!$A$1:$BQ$224,_xlfn.XMATCH(BQ$1,'UN Treasury'!$A$1:$BQ$1,-1,1),FALSE) -> 77.05
A4: ALL | B4: =VLOOKUP($A4,'UN Treasury'!$A$1:$BQ$224,_xlfn.XMATCH(B$1,'UN Treasury'!$A$1:$BQ$1,-1,1),FALSE) -> 80.07 | C4: =VLOOKUP($A4,'UN Treasury'!$A$1:$BQ$224,_xlfn.XMATCH(C$1,'UN Treasury'!$A$1:$BQ$1,-1,1),FALSE) -> 82.08 | D4: =VLOOKUP($A4,'UN Treasury'!$A$1:$BQ$224,_xlfn.XMATCH(D$1,'UN Treasury'!$A$1:$BQ$1,-1,1),FALSE) -> 82 | E4: =VLOOKUP($A4,'UN Treasury'!$A$1:$BQ$224,_xlfn.XMATCH(E$1,'UN Treasury'!$A$1:$BQ$1,-1,1),FALSE) -> 81.08 | F4: =VLOOKUP($A4,'UN Treasury'!$A$1:$BQ$224,_xlfn.XMATCH(F$1,'UN Treasury'!$A$1:$BQ$1,-1,1),FALSE) -> 81.46 | G4: =VLOOKUP($A4,'UN Treasury'!$A$1:$BQ$224,_xlfn.XMATCH(G$1,'UN Treasury'!$A$1:$BQ$1,-1,1),FALSE) -> 82.96 | H4: =VLOOKUP($A4,'UN Treasury'!$A$1:$BQ$224,_xlfn.XMATCH(H$1,'UN Treasury'!$A$1:$BQ$1,-1,1),FALSE) -> 80.69 | I4: =VLOOKUP($A4,'UN Treasury'!$A$1:$BQ$224,_xlfn.XMATCH(I$1,'UN Treasury'!$A$1:$BQ$1,-1,1),FALSE) -> 82.37 | ... BQ4: =VLOOKUP($A4,'UN Treasury'!$A$1:$BQ$224,_xlfn.XMATCH(BQ$1,'UN Treasury'!$A$1:$BQ$1,-1,1),FALSE) -> 98.9
A5: AMD | B5: =VLOOKUP($A5,'UN Treasury'!$A$1:$BQ$224,_xlfn.XMATCH(B$1,'UN Treasury'!$A$1:$BQ$1,-1,1),FALSE) -> 365 | C5: =VLOOKUP($A5,'UN Treasury'!$A$1:$BQ$224,_xlfn.XMATCH(C$1,'UN Treasury'!$A$1:$BQ$1,-1,1),FALSE) -> 366.33 | D5: =VLOOKUP($A5,'UN Treasury'!$A$1:$BQ$224,_xlfn.XMATCH(D$1,'UN Treasury'!$A$1:$BQ$1,-1,1),FALSE) -> 367 | E5: =VLOOKUP($A5,'UN Treasury'!$A$1:$BQ$224,_xlfn.XMATCH(E$1,'UN Treasury'!$A$1:$BQ$1,-1,1),FALSE) -> 367.25 | F5: =VLOOKUP($A5,'UN Treasury'!$A$1:$BQ$224,_xlfn.XMATCH(F$1,'UN Treasury'!$A$1:$BQ$1,-1,1),FALSE) -> 375.13 | G5: =VLOOKUP($A5,'UN Treasury'!$A$1:$BQ$224,_xlfn.XMATCH(G$1,'UN Treasury'!$A$1:$BQ$1,-1,1),FALSE) -> 375.8 | H5: =VLOOKUP($A5,'UN Treasury'!$A$1:$BQ$224,_xlfn.XMATCH(H$1,'UN Treasury'!$A$1:$BQ$1,-1,1),FALSE) -> 376 | I5: =VLOOKUP($A5,'UN Treasury'!$A$1:$BQ$224,_xlfn.XMATCH(I$1,'UN Treasury'!$A$1:$BQ$1,-1,1),FALSE) -> 379.5 | ... BQ5: =VLOOKUP($A5,'UN Treasury'!$A$1:$BQ$224,_xlfn.XMATCH(BQ$1,'UN Treasury'!$A$1:$BQ$1,-1,1),FALSE) -> 519.62
A6: AOA | B6: =VLOOKUP($A6,'UN Treasury'!$A$1:$BQ$224,_xlfn.XMATCH(B$1,'UN Treasury'!$A$1:$BQ$1,-1,1),FALSE) -> 912.792 | C6: =VLOOKUP($A6,'UN Treasury'!$A$1:$BQ$224,_xlfn.XMATCH(C$1,'UN Treasury'!$A$1:$BQ$1,-1,1),FALSE) -> 912.629 | D6: =VLOOKUP($A6,'UN Treasury'!$A$1:$BQ$224,_xlfn.XMATCH(D$1,'UN Treasury'!$A$1:$BQ$1,-1,1),FALSE) -> 913.116 | E6: =VLOOKUP($A6,'UN Treasury'!$A$1:$BQ$224,_xlfn.XMATCH(E$1,'UN Treasury'!$A$1:$BQ$1,-1,1),FALSE) -> 913.116 | F6: =VLOOKUP($A6,'UN Treasury'!$A$1:$BQ$224,_xlfn.XMATCH(F$1,'UN Treasury'!$A$1:$BQ$1,-1,1),FALSE) -> 912.131 | G6: =VLOOKUP($A6,'UN Treasury'!$A$1:$BQ$224,_xlfn.XMATCH(G$1,'UN Treasury'!$A$1:$BQ$1,-1,1),FALSE) -> 912.131 | H6: =VLOOKUP($A6,'UN Treasury'!$A$1:$BQ$224,_xlfn.XMATCH(H$1,'UN Treasury'!$A$1:$BQ$1,-1,1),FALSE) -> 912.253 | I6: =VLOOKUP($A6,'UN Treasury'!$A$1:$BQ$224,_xlfn.XMATCH(I$1,'UN Treasury'!$A$1:$BQ$1,-1,1),FALSE) -> 911.968 | ... BQ6: =VLOOKUP($A6,'UN Treasury'!$A$1:$BQ$224,_xlfn.XMATCH(BQ$1,'UN Treasury'!$A$1:$BQ$1,-1,1),FALSE) -> 650.283
A7: ARS | B7: =VLOOKUP($A7,'UN Treasury'!$A$1:$BQ$224,_xlfn.XMATCH(B$1,'UN Treasury'!$A$1:$BQ$1,-1,1),FALSE) -> 1491.972 | C7: =VLOOKUP($A7,'UN Treasury'!$A$1:$BQ$224,_xlfn.XMATCH(C$1,'UN Treasury'!$A$1:$BQ$1,-1,1),FALSE) -> 1488.32 | D7: =VLOOKUP($A7,'UN Treasury'!$A$1:$BQ$224,_xlfn.XMATCH(D$1,'UN Treasury'!$A$1:$BQ$1,-1,1),FALSE) -> 1426.94 | E7: =VLOOKUP($A7,'UN Treasury'!$A$1:$BQ$224,_xlfn.XMATCH(E$1,'UN Treasury'!$A$1:$BQ$1,-1,1),FALSE) -> 1385.666 | F7: =VLOOKUP($A7,'UN Treasury'!$A$1:$BQ$224,_xlfn.XMATCH(F$1,'UN Treasury'!$A$1:$BQ$1,-1,1),FALSE) -> 1368.873 | G7: =VLOOKUP($A7,'UN Treasury'!$A$1:$BQ$224,_xlfn.XMATCH(G$1,'UN Treasury'!$A$1:$BQ$1,-1,1),FALSE) -> 1399.774 | H7: =VLOOKUP($A7,'UN Treasury'!$A$1:$BQ$224,_xlfn.XMATCH(H$1,'UN Treasury'!$A$1:$BQ$1,-1,1),FALSE) -> 1391.37 | I7: =VLOOKUP($A7,'UN Treasury'!$A$1:$BQ$224,_xlfn.XMATCH(I$1,'UN Treasury'!$A$1:$BQ$1,-1,1),FALSE) -> 1467 | ... BQ7: =VLOOKUP($A7,'UN Treasury'!$A$1:$BQ$224,_xlfn.XMATCH(BQ$1,'UN Treasury'!$A$1:$BQ$1,-1,1),FALSE) -> 84.019
A8: AUD | B8: =VLOOKUP($A8,'UN Treasury'!$A$1:$BQ$224,_xlfn.XMATCH(B$1,'UN Treasury'!$A$1:$BQ$1,-1,1),FALSE) -> 1.417 | C8: =VLOOKUP($A8,'UN Treasury'!$A$1:$BQ$224,_xlfn.XMATCH(C$1,'UN Treasury'!$A$1:$BQ$1,-1,1),FALSE) -> 1.441 | D8: =VLOOKUP($A8,'UN Treasury'!$A$1:$BQ$224,_xlfn.XMATCH(D$1,'UN Treasury'!$A$1:$BQ$1,-1,1),FALSE) -> 1.432 | E8: =VLOOKUP($A8,'UN Treasury'!$A$1:$BQ$224,_xlfn.XMATCH(E$1,'UN Treasury'!$A$1:$BQ$1,-1,1),FALSE) -> 1.38 | F8: =VLOOKUP($A8,'UN Treasury'!$A$1:$BQ$224,_xlfn.XMATCH(F$1,'UN Treasury'!$A$1:$BQ$1,-1,1),FALSE) -> 1.415 | G8: =VLOOKUP($A8,'UN Treasury'!$A$1:$BQ$224,_xlfn.XMATCH(G$1,'UN Treasury'!$A$1:$BQ$1,-1,1),FALSE) -> 1.408 | H8: =VLOOKUP($A8,'UN Treasury'!$A$1:$BQ$224,_xlfn.XMATCH(H$1,'UN Treasury'!$A$1:$BQ$1,-1,1),FALSE) -> 1.403 | I8: =VLOOKUP($A8,'UN Treasury'!$A$1:$BQ$224,_xlfn.XMATCH(I$1,'UN Treasury'!$A$1:$BQ$1,-1,1),FALSE) -> 1.497 | ... BQ8: =VLOOKUP($A8,'UN Treasury'!$A$1:$BQ$224,_xlfn.XMATCH(BQ$1,'UN Treasury'!$A$1:$BQ$1,-1,1),FALSE) -> 1.294
A9: AWG | B9: =VLOOKUP($A9,'UN Treasury'!$A$1:$BQ$224,_xlfn.XMATCH(B$1,'UN Treasury'!$A$1:$BQ$1,-1,1),FALSE) -> 1.79 | C9: =VLOOKUP($A9,'UN Treasury'!$A$1:$BQ$224,_xlfn.XMATCH(C$1,'UN Treasury'!$A$1:$BQ$1,-1,1),FALSE) -> 1.79 | D9: =VLOOKUP($A9,'UN Treasury'!$A$1:$BQ$224,_xlfn.XMATCH(D$1,'UN Treasury'!$A$1:$BQ$1,-1,1),FALSE) -> 1.79 | E9: =VLOOKUP($A9,'UN Treasury'!$A$1:$BQ$224,_xlfn.XMATCH(E$1,'UN Treasury'!$A$1:$BQ$1,-1,1),FALSE) -> 1.79 | F9: =VLOOKUP($A9,'UN Treasury'!$A$1:$BQ$224,_xlfn.XMATCH(F$1,'UN Treasury'!$A$1:$BQ$1,-1,1),FALSE) -> 1.79 | G9: =VLOOKUP($A9,'UN Treasury'!$A$1:$BQ$224,_xlfn.XMATCH(G$1,'UN Treasury'!$A$1:$BQ$1,-1,1),FALSE) -> 1.79 | H9: =VLOOKUP($A9,'UN Treasury'!$A$1:$BQ$224,_xlfn.XMATCH(H$1,'UN Treasury'!$A$1:$BQ$1,-1,1),FALSE) -> 1.79 | I9: =VLOOKUP($A9,'UN Treasury'!$A$1:$BQ$224,_xlfn.XMATCH(I$1,'UN Treasury'!$A$1:$BQ$1,-1,1),FALSE) -> 1.79 | ... BQ9: =VLOOKUP($A9,'UN Treasury'!$A$1:$BQ$224,_xlfn.XMATCH(BQ$1,'UN Treasury'!$A$1:$BQ$1,-1,1),FALSE) -> 1.79
A10: AZN | B10: =VLOOKUP($A10,'UN Treasury'!$A$1:$BQ$224,_xlfn.XMATCH(B$1,'UN Treasury'!$A$1:$BQ$1,-1,1),FALSE) -> 1.698 | C10: =VLOOKUP($A10,'UN Treasury'!$A$1:$BQ$224,_xlfn.XMATCH(C$1,'UN Treasury'!$A$1:$BQ$1,-1,1),FALSE) -> 1.698 | D10: =VLOOKUP($A10,'UN Treasury'!$A$1:$BQ$224,_xlfn.XMATCH(D$1,'UN Treasury'!$A$1:$BQ$1,-1,1),FALSE) -> 1.699 | E10: =VLOOKUP($A10,'UN Treasury'!$A$1:$BQ$224,_xlfn.XMATCH(E$1,'UN Treasury'!$A$1:$BQ$1,-1,1),FALSE) -> 1.698 | F10: =VLOOKUP($A10,'UN Treasury'!$A$1:$BQ$224,_xlfn.XMATCH(F$1,'UN Treasury'!$A$1:$BQ$1,-1,1),FALSE) -> 1.698 | G10: =VLOOKUP($A10,'UN Treasury'!$A$1:$BQ$224,_xlfn.XMATCH(G$1,'UN Treasury'!$A$1:$BQ$1,-1,1),FALSE) -> 1.698 | H10: =VLOOKUP($A10,'UN Treasury'!$A$1:$BQ$224,_xlfn.XMATCH(H$1,'UN Treasury'!$A$1:$BQ$1,-1,1),FALSE) -> 1.698 | I10: =VLOOKUP($A10,'UN Treasury'!$A$1:$BQ$224,_xlfn.XMATCH(I$1,'UN Treasury'!$A$1:$BQ$1,-1,1),FALSE) -> 1.698 | ... BQ10: =VLOOKUP($A10,'UN Treasury'!$A$1:$BQ$224,_xlfn.XMATCH(BQ$1,'UN Treasury'!$A$1:$BQ$1,-1,1),FALSE) -> 1.693
A11: BAM | B11: =VLOOKUP($A11,'UN Treasury'!$A$1:$BQ$224,_xlfn.XMATCH(B$1,'UN Treasury'!$A$1:$BQ$1,-1,1),FALSE) -> 1.695 | C11: =VLOOKUP($A11,'UN Treasury'!$A$1:$BQ$224,_xlfn.XMATCH(C$1,'UN Treasury'!$A$1:$BQ$1,-1,1),FALSE) -> 1.712 | D11: =VLOOKUP($A11,'UN Treasury'!$A$1:$BQ$224,_xlfn.XMATCH(D$1,'UN Treasury'!$A$1:$BQ$1,-1,1),FALSE) -> 1.697 | E11: =VLOOKUP($A11,'UN Treasury'!$A$1:$BQ$224,_xlfn.XMATCH(E$1,'UN Treasury'!$A$1:$BQ$1,-1,1),FALSE) -> 1.67 | F11: =VLOOKUP($A11,'UN Treasury'!$A$1:$BQ$224,_xlfn.XMATCH(F$1,'UN Treasury'!$A$1:$BQ$1,-1,1),FALSE) -> 1.67 | G11: =VLOOKUP($A11,'UN Treasury'!$A$1:$BQ$224,_xlfn.XMATCH(G$1,'UN Treasury'!$A$1:$BQ$1,-1,1),FALSE) -> 1.696 | H11: =VLOOKUP($A11,'UN Treasury'!$A$1:$BQ$224,_xlfn.XMATCH(H$1,'UN Treasury'!$A$1:$BQ$1,-1,1),FALSE) -> 1.645 | I11: =VLOOKUP($A11,'UN Treasury'!$A$1:$BQ$224,_xlfn.XMATCH(I$1,'UN Treasury'!$A$1:$BQ$1,-1,1),FALSE) -> 1.679 | ... BQ11: =VLOOKUP($A11,'UN Treasury'!$A$1:$BQ$224,_xlfn.XMATCH(BQ$1,'UN Treasury'!$A$1:$BQ$1,-1,1),FALSE) -> 1.608
A12: BBD | B12: =VLOOKUP($A12,'UN Treasury'!$A$1:$BQ$224,_xlfn.XMATCH(B$1,'UN Treasury'!$A$1:$BQ$1,-1,1),FALSE) -> 2 | C12: =VLOOKUP($A12,'UN Treasury'!$A$1:$BQ$224,_xlfn.XMATCH(C$1,'UN Treasury'!$A$1:$BQ$1,-1,1),FALSE) -> 2 | D12: =VLOOKUP($A12,'UN Treasury'!$A$1:$BQ$224,_xlfn.XMATCH(D$1,'UN Treasury'!$A$1:$BQ$1,-1,1),FALSE) -> 2 | E12: =VLOOKUP($A12,'UN Treasury'!$A$1:$BQ$224,_xlfn.XMATCH(E$1,'UN Treasury'!$A$1:$BQ$1,-1,1),FALSE) -> 2 | F12: =VLOOKUP($A12,'UN Treasury'!$A$1:$BQ$224,_xlfn.XMATCH(F$1,'UN Treasury'!$A$1:$BQ$1,-1,1),FALSE) -> 2 | G12: =VLOOKUP($A12,'UN Treasury'!$A$1:$BQ$224,_xlfn.XMATCH(G$1,'UN Treasury'!$A$1:$BQ$1,-1,1),FALSE) -> 2 | H12: =VLOOKUP($A12,'UN Treasury'!$A$1:$BQ$224,_xlfn.XMATCH(H$1,'UN Treasury'!$A$1:$BQ$1,-1,1),FALSE) -> 2 | I12: =VLOOKUP($A12,'UN Treasury'!$A$1:$BQ$224,_xlfn.XMATCH(I$1,'UN Treasury'!$A$1:$BQ$1,-1,1),FALSE) -> 2 | ... BQ12: =VLOOKUP($A12,'UN Treasury'!$A$1:$BQ$224,_xlfn.XMATCH(BQ$1,'UN Treasury'!$A$1:$BQ$1,-1,1),FALSE) -> 2
A13: BDT | B13: =VLOOKUP($A13,'UN Treasury'!$A$1:$BQ$224,_xlfn.XMATCH(B$1,'UN Treasury'!$A$1:$BQ$1,-1,1),FALSE) -> 122.889 | C13: =VLOOKUP($A13,'UN Treasury'!$A$1:$BQ$224,_xlfn.XMATCH(C$1,'UN Treasury'!$A$1:$BQ$1,-1,1),FALSE) -> 122.58 | D13: =VLOOKUP($A13,'UN Treasury'!$A$1:$BQ$224,_xlfn.XMATCH(D$1,'UN Treasury'!$A$1:$BQ$1,-1,1),FALSE) -> 122.511 | E13: =VLOOKUP($A13,'UN Treasury'!$A$1:$BQ$224,_xlfn.XMATCH(E$1,'UN Treasury'!$A$1:$BQ$1,-1,1),FALSE) -> 122.237 | F13: =VLOOKUP($A13,'UN Treasury'!$A$1:$BQ$224,_xlfn.XMATCH(F$1,'UN Treasury'!$A$1:$BQ$1,-1,1),FALSE) -> 122.503 | G13: =VLOOKUP($A13,'UN Treasury'!$A$1:$BQ$224,_xlfn.XMATCH(G$1,'UN Treasury'!$A$1:$BQ$1,-1,1),FALSE) -> 122.276 | H13: =VLOOKUP($A13,'UN Treasury'!$A$1:$BQ$224,_xlfn.XMATCH(H$1,'UN Treasury'!$A$1:$BQ$1,-1,1),FALSE) -> 122.029 | I13: =VLOOKUP($A13,'UN Treasury'!$A$1:$BQ$224,_xlfn.XMATCH(I$1,'UN Treasury'!$A$1:$BQ$1,-1,1),FALSE) -> 122.029 | ... BQ13: =VLOOKUP($A13,'UN Treasury'!$A$1:$BQ$224,_xlfn.XMATCH(BQ$1,'UN Treasury'!$A$1:$BQ$1,-1,1),FALSE) -> 84.4611
... A152: ZWG | B152: =VLOOKUP($A152,'UN Treasury'!$A$1:$BQ$224,_xlfn.XMATCH(B$1,'UN Treasury'!$A$1:$BQ$1,-1,1),FALSE) -> 25.701 | C152: =VLOOKUP($A152,'UN Treasury'!$A$1:$BQ$224,_xlfn.XMATCH(C$1,'UN Treasury'!$A$1:$BQ$1,-1,1),FALSE) -> 25.933 | D152: =VLOOKUP($A152,'UN Treasury'!$A$1:$BQ$224,_xlfn.XMATCH(D$1,'UN Treasury'!$A$1:$BQ$1,-1,1),FALSE) -> 25.765 | E152: =VLOOKUP($A152,'UN Treasury'!$A$1:$BQ$224,_xlfn.XMATCH(E$1,'UN Treasury'!$A$1:$BQ$1,-1,1),FALSE) -> 24.646 | F152: =VLOOKUP($A152,'UN Treasury'!$A$1:$BQ$224,_xlfn.XMATCH(F$1,'UN Treasury'!$A$1:$BQ$1,-1,1),FALSE) -> 24.6 | G152: =VLOOKUP($A152,'UN Treasury'!$A$1:$BQ$224,_xlfn.XMATCH(G$1,'UN Treasury'!$A$1:$BQ$1,-1,1),FALSE) -> 24.852 | H152: =VLOOKUP($A152,'UN Treasury'!$A$1:$BQ$224,_xlfn.XMATCH(H$1,'UN Treasury'!$A$1:$BQ$1,-1,1),FALSE) -> 25.001 | I152: =VLOOKUP($A152,'UN Treasury'!$A$1:$BQ$224,_xlfn.XMATCH(I$1,'UN Treasury'!$A$1:$BQ$1,-1,1),FALSE) -> 25.218 | ... BQ152: =VLOOKUP($A152,'UN Treasury'!$A$1:$BQ$224,_xlfn.XMATCH(BQ$1,'UN Treasury'!$A$1:$BQ$1,-1,1),FALSE) -> 79.74

Sheet UN Treasury
B1: 46249 | C1: 46218 | D1: 46188 | E1: 46157 | F1: 46127 | G1: 46096 | H1: 46068 | I1: 46037 | J1: 46006 | K1: 45976 | L1: 45945 | M1: 45915 | N1: 45884 | O1: 45853 | P1: 45823 | Q1: 45792 | R1: 45762 | S1: 45731 | T1: 45703 | U1: 45672 | V1: 45641 | W1: 45611 | X1: 45580 | Y1: 45550 | Z1: 45519 | AA1: 45488 | AB1: 45458 | AC1: 45427 | AD1: 45397 | AE1: 45366 | AF1: 45337 | AG1: 45306 | AH1: 45275 | AI1: 45245 | AJ1: 45214 | AK1: 45184 | AL1: 45153 | AM1: 45122 | AN1: 45092 | AO1: 45061 | AP1: 45031 | AQ1: 45000 | AR1: 44972 | AS1: 44941 | AT1: 44910 | AU1: 44880 | AV1: 44848 | AW1: 44819 | AX1: 44788 | AY1: 44757 | AZ1: 44727 | BA1: 44694 | BB1: 44665 | BC1: 44635 | BD1: 44607 | BE1: 44575 | BF1: 44545 | BG1: 44515 | BH1: 44470 | BI1: 44454 | BJ1: 44409 | BK1: 44392 | BL1: 44348 | BM1: 44317 | BN1: 44301 | BO1: 44270 | BP1: 44242 | BQ1: 44211
A2: AFN | B2: 65.008 | C2: 65.446 | D2: 63.944 | E2: 64.05 | F2: 64.394 | G2: 63.489 | H2: 63.717 | I2: 66.079 | J2: 66.095 | K2: 65.835 | L2: 65.964 | M2: 67.587 | N2: 67.597 | O2: 69.852 | P2: 69.669 | Q2: 69.488 | R2: 72.326 | S2: 70.34 | T2: 72.32 | U2: 70.448 | V2: 69.419 | W2: 67.23 | X2: 67.419 | Y2: 69.419 | Z2: 70.211 | AA2: 70.458 | AB2: 69.597 | AC2: 71.596 | AD2: 70.419 | AE2: 70.736 | AF2: 73.131 | AG2: 69.647 | AH2: 68.488 | AI2: 71.627 | AJ2: 74.458 | AK2: 78.924 | AL2: 84.6 | AM2: 85.388 | AN2: 85.605 | AO2: 86.85 | AP2: 85.457 | AQ2: 87.071 | AR2: 89.119 | AS2: 88.73 | AT2: 87.48 | AU2: 88.312 | AV2: 88.18 | AW2: 88.13 | AX2: 90.13 | AY2: 87.994 | AZ2: 88.722 | BA2: 87.27 | BB2: 87.82 | BC2: 91.62 | BD2: 92.01 | BE2: 104 | BF2: 112.45 | BG2: 90.38 | BH2: 87.88 | BI2: 86.045 | BJ2: 80.087 | BK2: 79.15 | BL2: 78.07 | BM2: 77.4 | BN2: 77.34 | BO2: 77.3 | BP2: 77.3 | BQ2: 77.05
A3: ALL | B3: 80.07 | C3: 82.08 | D3: 82 | E3: 81.08 | F3: 81.46 | G3: 82.96 | H3: 80.69 | I3: 82.37 | J3: 81.77 | K3: 81.08 | L3: 80.77 | M3: 81 | N3: 80.98 | O3: 81.06 | P3: 83.27 | Q3: 84.92 | R3: 87.54 | S3: 89.08 | T3: 93.41 | U3: 92.59 | V3: 90.56 | W3: 88.7 | X3: 87.66 | Y3: 87.26 | Z3: 89.29 | AA3: 90.24 | AB3: 92.35 | AC3: 91.46 | AD3: 91.92 | AE3: 92.55 | AF3: 94.13 | AG3: 93.1 | AH3: 91.7 | AI3: 95.58 | AJ3: 98.01 | AK3: 98.12 | AL3: 94.41 | AM3: 93.51 | AN3: 97.41 | AO3: 99 | AP3: 100.8 | AQ3: 105.24 | AR3: 105.77 | AS3: 109.71 | AT3: 109.01 | AU3: 114.51 | AV3: 118.03 | AW3: 116.54 | AX3: 112.18 | AY3: 114 | AZ3: 109.83 | BA3: 112 | BB3: 109.07 | BC3: 114.13 | BD3: 103.96 | BE3: 104.9 | BF3: 105.18 | BG3: 102.18 | BH3: 101.15 | BI3: 101.39 | BJ3: 101.47 | BK3: 100.59 | BL3: 98.48 | BM3: 100.8 | BN3: 101.73 | BO3: 99.67 | BP3: 99.15 | BQ3: 98.9
A4: DZD | B4: 132.678 | C4: 132.82 | D4: 133.135 | E4: 132.069 | F4: 131.904 | G4: 131.597 | H4: 129.035 | I4: 129.592 | J4: 129.27 | K4: 130.078 | L4: 129.993 | M4: 129.268 | N4: 129.3 | O4: 129.505 | P4: 130.919 | Q4: 133.198 | R4: 131.463 | S4: 132.92 | T4: 135.329 | U4: 135.898 | V4: 133.457 | W4: 133.293 | X4: 132.869 | Y4: 132.19 | Z4: 134.13 | AA4: 133.77 | AB4: 134.25 | AC4: 134.043 | AD4: 134.354 | AE4: 134.141 | AF4: 134.135 | AG4: 134.076 | AH4: 134.173 | AI4: 134.468 | AJ4: 136.756 | AK4: 136.591 | AL4: 135.324 | AM4: 134.434 | AN4: 135.625 | AO4: 135.227 | AP4: 135.053 | AQ4: 135.911 | AR4: 136.301 | AS4: 136.414 | AT4: 137.046 | AU4: 138.584 | AV4: 139.996 | AW4: 140.35 | AX4: 142.402 | AY4: 146.512 | AZ4: 145.981 | BA4: 144.973 | BB4: 142.812 | BC4: 142.396 | BD4: 140.118 | BE4: 138.733 | BF4: 138.43 | BG4: 136.447 | BH4: 136.378 | BI4: 134.77 | BJ4: 134.137 | BK4: 133.999 | BL4: 132.977 | BM4: 133.014 | BN4: 133.765 | BO4: 131.78 | BP4: 132.413 | BQ4: 131.672
A5: USD | B5: 1 | C5: 1 | D5: 1 | E5: 1 | F5: 1 | G5: 1 | H5: 1 | I5: 1 | J5: 1 | K5: 1 | L5: 1 | M5: 1 | N5: 1 | O5: 1 | P5: 1 | Q5: 1 | R5: 1 | S5: 1 | T5: 1 | U5: 1 | V5: 1 | W5: 1 | X5: 1 | Y5: 1 | Z5: 1 | AA5: 1 | AB5: 1 | AC5: 1 | AD5: 1 | AE5: 1 | AF5: 1 | AG5: 1 | AH5: 1 | AI5: 1 | AJ5: 1 | AK5: 1 | AL5: 1 | AM5: 1 | AN5: 1 | AO5: 1 | AP5: 1 | AQ5: 1 | AR5: 1 | AS5: 1 | AT5: 1 | AU5: 1 | AV5: 1 | AW5: 1 | AX5: 1 | AY5: 1 | AZ5: 1 | BA5: 1 | BB5: 1 | BC5: 1 | BD5: 1 | BE5: 1 | BF5: 1 | BG5: 1 | BH5: 1 | BI5: 1 | BJ5: 1 | BK5: 1 | BL5: 1 | BM5: 1 | BN5: 1 | BO5: 1 | BP5: 1 | BQ5: 1
A6: EUR | B6: 0.867 | C6: 0.875 | D6: 0.868 | E6: 0.854 | F6: 0.854 | G6: 0.867 | H6: 0.841 | I6: 0.858 | J6: 0.852 | K6: 0.865 | L6: 0.865 | M6: 0.853 | N6: 0.855 | O6: 0.856 | P6: 0.872 | Q6: 0.897 | R6: 0.88 | S6: 0.918 | T6: 0.967 | U6: 0.98 | V6: 0.953 | W6: 0.943 | X6: 0.914 | Y6: 0.908 | Z6: 0.913 | AA6: 0.918 | AB6: 0.923 | AC6: 0.926 | AD6: 0.932 | AE6: 0.914 | AF6: 0.933 | AG6: 0.913 | AH6: 0.927 | AI6: 0.937 | AJ6: 0.941 | AK6: 0.931 | AL6: 0.913 | AM6: 0.902 | AN6: 0.927 | AO6: 0.917 | AP6: 0.911 | AQ6: 0.934 | AR6: 0.933 | AS6: 0.929 | AT6: 0.938 | AU6: 0.972 | AV6: 1.032 | AW6: 0.997 | AX6: 0.965 | AY6: 0.996 | AZ6: 0.958 | BA6: 0.947 | BB6: 0.92 | BC6: 0.913 | BD6: 0.878 | BE6: 0.876 | BF6: 0.888 | BG6: 0.872 | BH6: 0.86 | BI6: 0.847 | BJ6: 0.841 | BK6: 0.838 | BL6: 0.82 | BM6: 0.826 | BN6: 0.853 | BO6: 0.837 | BP6: 0.824 | BQ6: 0.822
A7: AOA | B7: 912.792 | C7: 912.629 | D7: 913.116 | E7: 913.116 | F7: 912.131 | G7: 912.131 | H7: 912.253 | I7: 911.968 | J7: 912.144 | K7: 912.085 | L7: 911.978 | M7: 911.955 | N7: 911.955 | O7: 911.955 | P7: 911.955 | Q7: 911.955 | R7: 912 | S7: 912 | T7: 912 | U7: 912 | V7: 924.216 | W7: 909.051 | X7: 905 | Y7: 920.378 | Z7: 878.071 | AA7: 871.261 | AB7: 852.484 | AC7: 834.06 | AD7: 832.633 | AE7: 832.631 | AF7: 828.261 | AG7: 828.724 | AH7: 828.783 | AI7: 827.07 | AJ7: 825.798 | AK7: 825.13 | AL7: 824.896 | AM7: 823.665 | AN7: 635.051 | AO7: 507.483 | AP7: 505.882 | AQ7: 503.992 | AR7: 504.318 | AS7: 503.865 | AT7: 504.734 | AU7: 482.99 | AV7: 433.164 | AW7: 423.86 | AX7: 424.298 | AY7: 425.105 | AZ7: 426.445 | BA7: 400.772 | BB7: 432.575 | BC7: 470.436 | BD7: 521.695 | BE7: 585 | BF7: 585 | BG7: 597.033 | BH7: 603.33 | BI7: 643.121 | BJ7: 643.121 | BK7: 643.121 | BL7: 643.121 | BM7: 649 | BN7: 621.172 | BO7: 635.762 | BP7: 651.325 | BQ7: 650.283
A8: XCD | B8: 2.7 | C8: 2.7 | D8: 2.7 | E8: 2.7 | F8: 2.7 | G8: 2.7 | H8: 2.7 | I8: 2.7 | J8: 2.7 | K8: 2.7 | L8: 2.7 | M8: 2.7 | N8: 2.7 | O8: 2.7 | P8: 2.7 | Q8: 2.7 | R8: 2.7 | S8: 2.7 | T8: 2.7 | U8: 2.7 | V8: 2.7 | W8: 2.7 | X8: 2.7 | Y8: 2.7 | Z8: 2.7 | AA8: 2.7 | AB8: 2.7 | AC8: 2.7 | AD8: 2.7 | AE8: 2.7 | AF8: 2.7 | AG8: 2.7 | AH8: 2.7 | AI8: 2.7 | AJ8: 2.7 | AK8: 2.7 | AL8: 2.7 | AM8: 2.7 | AN8: 2.7 | AO8: 2.7 | AP8: 2.7 | AQ8: 2.7 | AR8: 2.7 | AS8: 2.7 | AT8: 2.7 | AU8: 2.7 | AV8: 2.7 | AW8: 2.7 | AX8: 2.7 | AY8: 2.7 | AZ8: 2.7 | BA8: 2.7 | BB8: 2.7 | BC8: 2.7 | BD8: 2.7 | BE8: 2.7 | BF8: 2.7 | BG8: 2.7 | BH8: 2.7 | BI8: 2.7 | BJ8: 2.7 | BK8: 2.7 | BL8: 2.7 | BM8: 2.7 | BN8: 2.7 | BO8: 2.7 | BP8: 2.7 | BQ8: 2.7
A9: XCD | B9: 2.7 | C9: 2.7 | D9: 2.7 | E9: 2.7 | F9: 2.7 | G9: 2.7 | H9: 2.7 | I9: 2.7 | J9: 2.7 | K9: 2.7 | L9: 2.7 | M9: 2.7 | N9: 2.7 | O9: 2.7 | P9: 2.7 | Q9: 2.7 | R9: 2.7 | S9: 2.7 | T9: 2.7 | U9: 2.7 | V9: 2.7 | W9: 2.7 | X9: 2.7 | Y9: 2.7 | Z9: 2.7 | AA9: 2.7 | AB9: 2.7 | AC9: 2.7 | AD9: 2.7 | AE9: 2.7 | AF9: 2.7 | AG9: 2.7 | AH9: 2.7 | AI9: 2.7 | AJ9: 2.7 | AK9: 2.7 | AL9: 2.7 | AM9: 2.7 | AN9: 2.7 | AO9: 2.7 | AP9: 2.7 | AQ9: 2.7 | AR9: 2.7 | AS9: 2.7 | AT9: 2.7 | AU9: 2.7 | AV9: 2.7 | AW9: 2.7 | AX9: 2.7 | AY9: 2.7 | AZ9: 2.7 | BA9: 2.7 | BB9: 2.7 | BC9: 2.7 | BD9: 2.7 | BE9: 2.7 | BF9: 2.7 | BG9: 2.7 | BH9: 2.7 | BI9: 2.7 | BJ9: 2.7 | BK9: 2.7 | BL9: 2.7 | BM9: 2.7 | BN9: 2.7 | BO9: 2.7 | BP9: 2.7 | BQ9: 2.7
A10: ARS | B10: 1491.972 | C10: 1488.32 | D10: 1426.94 | E10: 1385.666 | F10: 1368.873 | G10: 1399.774 | H10: 1391.37 | I10: 1467 | J10: 1437.493 | K10: 1411.492 | L10: 1347.648 | M10: 1423.515 | N10: 1322 | O10: 1254.985 | P10: 1181.117 | Q10: 1126.25 | R10: 1075.66 | S10: 1066 | T10: 1056.07 | U10: 1039.12 | V10: 1016.59 | W10: 998.137 | X10: 974.562 | Y10: 958.246 | Z10: 939.487 | AA10: 919.336 | AB10: 902.184 | AC10: 884.237 | AD10: 865.677 | AE10: 849.522 | AF10: 831.288 | AG10: 815.4 | AH10: 799.95 | AI10: 350.005 | AJ10: 350.021 | AK10: 349.969 | AL10: 287.2 | AM10: 263.867 | AN10: 247.257 | AO10: 228.96 | AP10: 214.186 | AQ10: 200.647 | AR10: 191.64 | AS10: 180.682 | AT10: 171.745 | AU10: 160.724 | AV10: 150.973 | AW10: 142.57 | AX10: 134.21 | AY10: 127.79 | AZ10: 122.286 | BA10: 117.064 | BB10: 112.724 | BC10: 108.88 | BD10: 106.101 | BE10: 103.607 | BF10: 100.929 | BG10: 99.691 | BH10: 98.7 | BI10: 97.711 | BJ10: 96.648 | BK10: 95.672 | BL10: 94.517 | BM10: 93.504 | BN10: 91.96 | BO10: 89.751 | BP10: 87.205 | BQ10: 84.019
A11: AMD | B11: 365 | C11: 366.33 | D11: 367 | E11: 367.25 | F11: 375.13 | G11: 375.8 | H11: 376 | I11: 379.5 | J11: 380.02 | K11: 381 | L11: 381 | M11: 381.4 | N11: 382.13 | O11: 383.13 | P11: 382.08 | Q11: 386.5 | R11: 389.83 | S11: 392 | T11: 394 | U11: 393.86 | V11: 390 | W11: 385.6 | X11: 385.6 | Y11: 386 | Z11: 386 | AA11: 385.75 | AB11: 386 | AC11: 385.75 | AD11: 391.25 | AE11: 401.13 | AF11: 401 | AG11: 402 | AH11: 400.2 | AI11: 400 | AJ11: 392.8 | AK11: 383.45 | AL11: 384.1 | AM11: 383 | AN11: 383.25 | AO11: 383.25 | AP11: 385 | AQ11: 385 | AR11: 391.5 | AS11: 393 | AT11: 391.7 | AU11: 392 | AV11: 399.8 | AW11: 401.2 | AX11: 402 | AY11: 409.1 | AZ11: 411.69 | BA11: 455.63 | BB11: 466.9 | BC11: 510.13 | BD11: 476.91 | BE11: 477.4 | BF11: 482.52 | BG11: 474.9 | BH11: 482.25 | BI11: 490.5 | BJ11: 481.25 | BK11: 494.05 | BL11: 518.3 | BM11: 518.25 | BN11: 528.88 | BO11: 525.13 | BP11: 516.5 | BQ11: 519.62
A12: AWG | B12: 1.79 | C12: 1.79 | D12: 1.79 | E12: 1.79 | F12: 1.79 | G12: 1.79 | H12: 1.79 | I12: 1.79 | J12: 1.79 | K12: 1.79 | L12: 1.79 | M12: 1.79 | N12: 1.79 | O12: 1.79 | P12: 1.79 | Q12: 1.79 | R12: 1.79 | S12: 1.79 | T12: 1.79 | U12: 1.79 | V12: 1.79 | W12: 1.79 | X12: 1.79 | Y12: 1.79 | Z12: 1.79 | AA12: 1.79 | AB12: 1.79 | AC12: 1.79 | AD12: 1.79 | AE12: 1.79 | AF12: 1.79 | AG12: 1.79 | AH12: 1.79 | AI12: 1.79 | AJ12: 1.79 | AK12: 1.79 | AL12: 1.79 | AM12: 1.79 | AN12: 1.79 | AO12: 1.79 | AP12: 1.79 | AQ12: 1.79 | AR12: 1.79 | AS12: 1.79 | AT12: 1.79 | AU12: 1.79 | AV12: 1.79 | AW12: 1.79 | AX12: 1.79 | AY12: 1.79 | AZ12: 1.79 | BA12: 1.79 | BB12: 1.79 | BC12: 1.79 | BD12: 1.79 | BE12: 1.79 | BF12: 1.79 | BG12: 1.79 | BH12: 1.79 | BI12: 1.79 | BJ12: 1.79 | BK12: 1.7828 | BL12: 1.7864 | BM12: 1.79 | BN12: 1.79 | BO12: 1.79 | BP12: 1.79 | BQ12: 1.79
A13: AUD | B13: 1.417 | C13: 1.441 | D13: 1.432 | E13: 1.38 | F13: 1.415 | G13: 1.408 | H13: 1.403 | I13: 1.497 | J13: 1.499 | K13: 1.53 | L13: 1.535 | M13: 1.509 | N13: 1.527 | O13: 1.52 | P13: 1.534 | Q13: 1.555 | R13: 1.591 | S13: 1.59 | T13: 1.599 | U13: 1.624 | V13: 1.572 | W13: 1.537 | X13: 1.484 | Y13: 1.504 | Z13: 1.513 | AA13: 1.473 | AB13: 1.494 | AC13: 1.51 | AD13: 1.53 | AE13: 1.511 | AF13: 1.546 | AG13: 1.498 | AH13: 1.522 | AI13: 1.571 | AJ13: 1.556 | AK13: 1.557 | AL13: 1.538 | AM13: 1.477 | AN13: 1.477 | AO13: 1.493 | AP13: 1.493 | AQ13: 1.501 | AR13: 1.437 | AS13: 1.448 | AT13: 1.451 | AU13: 1.497 | AV13: 1.598 | AW13: 1.472 | AX13: 1.403 | AY13: 1.481 | AZ13: 1.436 | BA13: 1.423 | BB13: 1.339 | BC13: 1.365 | BD13: 1.394 | BE13: 1.376 | BF13: 1.401 | BG13: 1.369 | BH13: 1.39 | BI13: 1.357 | BJ13: 1.353 | BK13: 1.322 | BL13: 1.291 | BM13: 1.287 | BN13: 1.314 | BO13: 1.289 | BP13: 1.288 | BQ13: 1.294
... A52: CUP | B52: 24 | C52: 24 | D52: 24 | E52: 24 | F52: 24 | G52: 24 | H52: 24 | I52: 24 | J52: 24 | K52: 24 | L52: 24 | M52: 24 | N52: 24 | O52: 24 | P52: 24 | Q52: 24 | R52: 24 | S52: 24 | T52: 24 | U52: 24 | V52: 24 | W52: 24 | X52: 24 | Y52: 24 | Z52: 24 | AA52: 24 | AB52: 24 | AC52: 24 | AD52: 24 | AE52: 24 | AF52: 24 | AG52: 24 | AH52: 24 | AI52: 24 | AJ52: 24 | AK52: 24 | AL52: 24 | AM52: 24 | AN52: 24 | AO52: 24 | AP52: 24 | AQ52: 24 | AR52: 24 | AS52: 24 | AT52: 24 | AU52: 24 | AV52: 24 | AW52: 24 | AX52: 24 | AY52: 24 | AZ52: 24 | BA52: 24 | BB52: 24 | BC52: 24 | BD52: 24 | BE52: 24 | BF52: 24 | BG52: 24 | BH52: 24 | BI52: 24 | BJ52: 24 | BK52: 24 | BL52: 24 | BM52: 24 | BN52: 24 | BO52: 24 | BP52: 24 | BQ52: 1
A53: XCG | B53: 1.79 | C53: 1.79 | D53: 1.79 | E53: 1.79 | F53: 1.79 | G53: 1.79 | H53: 1.79 | I53: 1.79 | J53: 1.79 | K53: 1.79 | L53: 1.79 | M53: 1.79 | N53: 1.79 | O53: 1.79 | P53: 1.79 | Q53: 1.79 | R53: 1.79
A54: EUR | B54: 0.867 | C54: 0.875 | D54: 0.868 | E54: 0.854 | F54: 0.854 | G54: 0.867 | H54: 0.841 | I54: 0.858 | J54: 0.852 | K54: 0.865 | L54: 0.865 | M54: 0.853 | N54: 0.855 | O54: 0.856 | P54: 0.872 | Q54: 0.897 | R54: 0.88 | S54: 0.918 | T54: 0.967 | U54: 0.98 | V54: 0.953 | W54: 0.943 | X54: 0.914 | Y54: 0.908 | Z54: 0.913 | AA54: 0.918 | AB54: 0.923 | AC54: 0.926 | AD54: 0.932 | AE54: 0.914 | AF54: 0.933 | AG54: 0.913 | AH54: 0.927 | AI54: 0.937 | AJ54: 0.941 | AK54: 0.931 | AL54: 0.913 | AM54: 0.902 | AN54: 0.927 | AO54: 0.917 | AP54: 0.911 | AQ54: 0.934 | AR54: 0.933 | AS54: 0.929 | AT54: 0.938 | AU54: 0.972 | AV54: 1.032 | AW54: 0.997 | AX54: 0.965 | AY54: 0.996 | AZ54: 0.958 | BA54: 0.947 | BB54: 0.92 | BC54: 0.913 | BD54: 0.878 | BE54: 0.876 | BF54: 0.888 | BG54: 0.872 | BH54: 0.86 | BI54: 0.847 | BJ54: 0.841 | BK54: 0.838 | BL54: 0.82 | BM54: 0.826 | BN54: 0.853 | BO54: 0.837 | BP54: 0.824 | BQ54: 0.822
A55: CZK | B55: 20.989 | C55: 21.226 | D55: 20.996 | E55: 20.788 | F55: 20.806 | G55: 21.179 | H55: 20.398 | I55: 20.795 | J55: 20.602 | K55: 20.958 | L55: 21.04 | M55: 20.79 | N55: 20.9 | O55: 21.11 | P55: 21.6 | Q55: 22.39 | R55: 22.13 | S55: 22.98 | T55: 24.23 | U55: 24.69 | V55: 23.91 | W55: 23.85 | X55: 23.11 | Y55: 22.76 | Z55: 22.99 | AA55: 23.3 | AB55: 22.75 | AC55: 22.96 | AD55: 23.63 | AE55: 23.08 | AF55: 23.65 | AG55: 22.51 | AH55: 22.72 | AI55: 23.03 | AJ55: 23.09 | AK55: 22.76 | AL55: 21.99 | AM55: 21.47 | AN55: 22.06 | AO55: 21.56 | AP55: 21.28 | AQ55: 22.15 | AR55: 22.17 | AS55: 22.32 | AT55: 22.8 | AU55: 23.6 | AV55: 25.35 | AW55: 24.47 | AX55: 23.5 | AY55: 24.24 | AZ55: 23.69 | BA55: 23.93 | BB55: 22.46 | BC55: 22.94 | BD55: 21.42 | BE55: 21.34 | BF55: 22.72 | BG55: 22.02 | BH55: 21.93 | BI55: 21.48 | BJ55: 21.46 | BK55: 21.32 | BL55: 20.85 | BM55: 21.37 | BN55: 22.29 | BO55: 21.9 | BP55: 21.22 | BQ55: 21.51
A56: DKK | B56: 6.479 | C56: 6.542 | D56: 6.487 | E56: 6.381 | F56: 6.381 | G56: 6.48 | H56: 6.286 | I56: 6.415 | J56: 6.36 | K56: 6.457 | L56: 6.458 | M56: 6.364 | N56: 6.377 | O56: 6.383 | P56: 6.504 | Q56: 6.692 | R56: 6.571 | S56: 6.85 | T56: 7.21 | U56: 7.309 | V56: 7.104 | W56: 7.035 | X56: 6.82 | Y56: 6.773 | Z56: 6.811 | AA56: 6.854 | AB56: 6.884 | AC56: 6.906 | AD56: 6.95 | AE56: 6.817 | AF56: 6.952 | AG56: 6.808 | AH56: 6.91 | AI56: 6.99 | AJ56: 7.015 | AK56: 6.945 | AL56: 6.799 | AM56: 6.719 | AN56: 6.911 | AO56: 6.827 | AP56: 6.786 | AQ56: 6.951 | AR56: 6.952 | AS56: 6.908 | AT56: 6.979 | AU56: 7.23 | AV56: 7.675 | AW56: 7.412 | AX56: 7.181 | AY56: 7.413 | AZ56: 7.125 | BA56: 7.046 | BB56: 6.84 | BC56: 6.789 | BD56: 6.53 | BE56: 6.516 | BF56: 6.601 | BG56: 6.486 | BH56: 6.393 | BI56: 6.302 | BJ56: 6.256 | BK56: 6.234 | BL56: 6.096 | BM56: 6.142 | BN56: 6.345 | BO56: 6.227 | BP56: 6.128 | BQ56: 6.116
A57: DJF | B57: 177 | C57: 177 | D57: 177 | E57: 177 | F57: 177 | G57: 177 | H57: 177 | I57: 177 | J57: 177 | K57: 177 | L57: 177 | M57: 177 | N57: 177 | O57: 177 | P57: 177 | Q57: 177 | R57: 177 | S57: 177 | T57: 177 | U57: 177 | V57: 177 | W57: 177 | X57: 177 | Y57: 177 | Z57: 177 | AA57: 177 | AB57: 177 | AC57: 177 | AD57: 177 | AE57: 177 | AF57: 177 | AG57: 177 | AH57: 177 | AI57: 177 | AJ57: 177 | AK57: 177 | AL57: 177 | AM57: 177 | AN57: 177 | AO57: 177 | AP57: 177 | AQ57: 177 | AR57: 177 | AS57: 177 | AT57: 177 | AU57: 177 | AV57: 177 | AW57: 177 | AX57: 177 | AY57: 177 | AZ57: 177 | BA57: 177 | BB57: 177 | BC57: 177 | BD57: 177 | BE57: 177 | BF57: 177 | BG57: 177 | BH57: 177 | BI57: 177 | BJ57: 177 | BK57: 177 | BL57: 177 | BM57: 177 | BN57: 177 | BO57: 177 | BP57: 177 | BQ57: 177
A58: XCD | B58: 2.7 | C58: 2.7 | D58: 2.7 | E58: 2.7 | F58: 2.7 | G58: 2.7 | H58: 2.7 | I58: 2.7 | J58: 2.7 | K58: 2.7 | L58: 2.7 | M58: 2.7 | N58: 2.7 | O58: 2.7 | P58: 2.7 | Q58: 2.7 | R58: 2.7 | S58: 2.7 | T58: 2.7 | U58: 2.7 | V58: 2.7 | W58: 2.7 | X58: 2.7 | Y58: 2.7 | Z58: 2.7 | AA58: 2.7 | AB58: 2.7 | AC58: 2.7 | AD58: 2.7 | AE58: 2.7 | AF58: 2.7 | AG58: 2.7 | AH58: 2.7 | AI58: 2.7 | AJ58: 2.7 | AK58: 2.7 | AL58: 2.7 | AM58: 2.7 | AN58: 2.7 | AO58: 2.7 | AP58: 2.7 | AQ58: 2.7 | AR58: 2.7 | AS58: 2.7 | AT58: 2.7 | AU58: 2.7 | AV58: 2.7 | AW58: 2.7 | AX58: 2.7 | AY58: 2.7 | AZ58: 2.7 | BA58: 2.7 | BB58: 2.7 | BC58: 2.7 | BD58: 2.7 | BE58: 2.7 | BF58: 2.7 | BG58: 2.7 | BH58: 2.7 | BI58: 2.7 | BJ58: 2.7 | BK58: 2.7 | BL58: 2.7 | BM58: 2.7 | BN58: 2.7 | BO58: 2.7 | BP58: 2.7 | BQ58: 2.7
A59: DOP | B59: 58.089 | C59: 58.481 | D59: 58.45 | E59: 59.216 | F59: 59.433 | G59: 60.853 | H59: 62.397 | I59: 63.4 | J59: 63.36 | K59: 64.02 | L59: 62.851 | M59: 63.323 | N59: 61.493 | O59: 59.891 | P59: 58.819 | Q59: 58.543 | R59: 61.124 | S59: 62.248 | T59: 61.658 | U59: 61.044 | V59: 60.34 | W59: 60.035 | X59: 59.87 | Y59: 59.55 | Z59: 59.443 | AA59: 59 | AB59: 59.119 | AC59: 58.278 | AD59: 58.967 | AE59: 58.577 | AF59: 58.451 | AG59: 58.446 | AH59: 56.65 | AI59: 56.542 | AJ59: 56.485 | AK59: 56.447 | AL59: 56.31 | AM59: 55.433 | AN59: 54.314 | AO59: 54.286 | AP59: 54.538 | AQ59: 54.506 | AR59: 55.871 | AS59: 56.042 | AT59: 54.716 | AU59: 53.943 | AV59: 53.507 | AW59: 53.217 | AX59: 53.785 | AY59: 54.354 | AZ59: 54.8 | BA59: 54.962 | BB59: 54.804 | BC59: 54.7 | BD59: 56.946 | BE59: 57.402 | BF59: 56.48 | BG59: 56.271 | BH59: 55.976 | BI59: 56.778 | BJ59: 56.663 | BK59: 56.835 | BL59: 56.68 | BM59: 56.6 | BN59: 56.76 | BO59: 57.689 | BP59: 57.599 | BQ59: 57.604
A60: USD | B60: 1 | C60: 1 | D60: 1 | E60: 1 | F60: 1 | G60: 1 | H60: 1 | I60: 1 | J60: 1 | K60: 1 | L60: 1 | M60: 1 | N60: 1 | O60: 1 | P60: 1 | Q60: 1 | R60: 1 | S60: 1 | T60: 1 | U60: 1 | V60: 1 | W60: 1 | X60: 1 | Y60: 1 | Z60: 1 | AA60: 1 | AB60: 1 | AC60: 1 | AD60: 1 | AE60: 1 | AF60: 1 | AG60: 1 | AH60: 1 | AI60: 1 | AJ60: 1 | AK60: 1 | AL60: 1 | AM60: 1 | AN60: 1 | AO60: 1 | AP60: 1 | AQ60: 1 | AR60: 1 | AS60: 1 | AT60: 1 | AU60: 1 | AV60: 1 | AW60: 1 | AX60: 1 | AY60: 1 | AZ60: 1 | BA60: 1 | BB60: 1 | BC60: 1 | BD60: 1 | BE60: 1 | BF60: 1 | BG60: 1 | BH60: 1 | BI60: 1 | BJ60: 1 | BK60: 1 | BL60: 1 | BM60: 1 | BN60: 1 | BO60: 1 | BP60: 1 | BQ60: 1
A61: USD | B61: 1 | C61: 1 | D61: 1 | E61: 1 | F61: 1 | G61: 1 | H61: 1 | I61: 1 | J61: 1 | K61: 1 | L61: 1 | M61: 1 | N61: 1 | O61: 1 | P61: 1 | Q61: 1 | R61: 1 | S61: 1 | T61: 1 | U61: 1 | V61: 1 | W61: 1 | X61: 1 | Y61: 1 | Z61: 1 | AA61: 1 | AB61: 1 | AC61: 1 | AD61: 1 | AE61: 1 | AF61: 1 | AG61: 1 | AH61: 1 | AI61: 1 | AJ61: 1 | AK61: 1 | AL61: 1 | AM61: 1 | AN61: 1 | AO61: 1 | AP61: 1 | AQ61: 1 | AR61: 1 | AS61: 1 | AT61: 1 | AU61: 1 | AV61: 1 | AW61: 1 | AX61: 1 | AY61: 1 | AZ61: 1 | BA61: 1 | BB61: 1 | BC61: 1 | BD61: 1 | BE61: 1 | BF61: 1 | BG61: 1 | BH61: 1 | BI61: 1 | BJ61: 1 | BK61: 1 | BL61: 1 | BM61: 1 | BN61: 1 | BO61: 1 | BP61: 1 | BQ61: 1
A62: EGP | B62: 50.23 | C62: 50.17 | D62: 51.93 | E62: 52.866 | F62: 53.11 | G62: 52.402 | H62: 46.79 | I62: 47.096 | J62: 47.486 | K62: 47.168 | L62: 47.653 | M62: 48.15 | N62: 48.3 | O62: 49.475 | P62: 49.457 | Q62: 50.4 | R62: 51.288 | S62: 50.629 | T62: 50.57 | U62: 50.46 | V62: 50.6 | W62: 49.26 | X62: 48.533 | Y62: 48.33 | Z62: 49.305 | AA62: 47.95 | AB62: 47.644 | AC62: 47 | AD62: 47.512 | AE62: 48.4 | AF62: 30.789 | AG62: 30.85 | AH62: 30.85 | AI62: 30.85 | AJ62: 30.85 | AK62: 30.843 | AL62: 30.863 | AM62: 30.899 | AN62: 30.861 | AO62: 30.875 | AP62: 30.862 | AQ62: 30.86 | AR62: 30.4 | AS62: 29.75 | AT62: 24.592 | AU62: 24.348 | AV62: 19.641 | AW62: 19.306 | AX62: 19.09 | AY62: 18.845 | AZ62: 18.673 | BA62: 18.361 | BB62: 18.458 | BC62: 15.658 | BD62: 15.67 | BE62: 15.688 | BF62: 15.669 | BG62: 15.665 | BH62: 15.664 | BI62: 15.652 | BJ62: 15.703 | BK62: 15.628 | BL62: 15.629 | BM62: 15.625 | BN62: 15.697 | BO62: 15.649 | BP62: 15.675 | BQ62: 15.72
A63: USD | B63: 1 | C63: 1 | D63: 1 | E63: 1 | F63: 1 | G63: 1 | H63: 1 | I63: 1 | J63: 1 | K63: 1 | L63: 1 | M63: 1 | N63: 1 | O63: 1 | P63: 1 | Q63: 1 | R63: 1 | S63: 1 | T63: 1 | U63: 1 | V63: 1 | W63: 1 | X63: 1 | Y63: 1 | Z63: 1 | AA63: 1 | AB63: 1 | AC63: 1 | AD63: 1 | AE63: 1 | AF63: 1 | AG63: 1 | AH63: 1 | AI63: 1 | AJ63: 1 | AK63: 1 | AL63: 1 | AM63: 1 | AN63: 1 | AO63: 1 | AP63: 1 | AQ63: 1 | AR63: 1 | AS63: 1 | AT63: 1 | AU63: 1 | AV63: 1 | AW63: 1 | AX63: 1 | AY63: 1 | AZ63: 1 | BA63: 1 | BB63: 1 | BC63: 1 | BD63: 1 | BE63: 1 | BF63: 1 | BG63: 1 | BH63: 1 | BI63: 1 | BJ63: 1 | BK63: 1 | BL63: 1 | BM63: 1 | BN63: 1 | BO63: 1 | BP63: 1 | BQ63: 1
A64: XAF | B64: 568.519 | C64: 574.041 | D64: 569.308 | E64: 560.168 | F64: 560.168 | G64: 568.815 | H64: 551.874 | I64: 563.053 | J64: 558.594 | K64: 567.241 | L64: 567.241 | M64: 559.308 | N64: 560.551 | O64: 561.175 | P64: 571.989 | Q64: 588.461 | R64: 577.325 | S64: 602.403 | T64: 634.081 | U64: 642.654 | V64: 624.84 | W64: 618.594 | X64: 599.65 | Y64: 595.35 | Z64: 598.719 | AA64: 602.459 | AB64: 605.462 | AC64: 607.143 | AD64: 611.159 | AE64: 599.65 | AF64: 611.729 | AG64: 598.883 | AH64: 607.987 | AI64: 614.71 | AJ64: 617.139 | AK64: 610.647 | AL64: 598.61 | AM64: 591.432 | AN64: 608.269 | AO64: 601.244 | AP64: 597.465 | AQ64: 612.472 | AR64: 612.129 | AS64: 609.286 | AT64: 615.402 | AU64: 637.656 | AV64: 676.733 | AW64: 653.799 | AX64: 633.224 | AY64: 653.409 | AZ64: 628.131 | BA64: 621.348 | BB64: 603.345 | BC64: 598.61 | BD64: 575.704 | BE64: 574.494 | BF64: 582.193 | BG64: 572.089 | BH64: 563.973 | BI64: 555.896 | BJ64: 551.734 | BK64: 549.884 | BL64: 537.714 | BM64: 541.845 | BN64: 559.69 | BO64: 549.24 | BP64: 540.461 | BQ64: 539.261
A65: ERN | B65: 15 | C65: 15 | D65: 15 | E65: 15 | F65: 15 | G65: 15 | H65: 15 | I65: 15 | J65: 15 | K65: 15 | L65: 15 | M65: 15 | N65: 15 | O65: 15 | P65: 15 | Q65: 15 | R65: 15 | S65: 15 | T65: 15 | U65: 15 | V65: 15 | W65: 15 | X65: 15 | Y65: 15 | Z65: 15 | AA65: 15 | AB65: 15 | AC65: 15 | AD65: 15 | AE65: 15 | AF65: 15 | AG65: 15 | AH65: 15 | AI65: 15 | AJ65: 15 | AK65: 15 | AL65: 15 | AM65: 15 | AN65: 15 | AO65: 15 | AP65: 15 | AQ65: 15 | AR65: 15 | AS65: 15 | AT65: 15 | AU65: 15 | AV65: 15 | AW65: 15 | AX65: 15 | AY65: 15 | AZ65: 15 | BA65: 15 | BB65: 15 | BC65: 15 | BD65: 15 | BE65: 15 | BF65: 15 | BG65: 15 | BH65: 15 | BI65: 15 | BJ65: 15 | BK65: 15 | BL65: 15 | BM65: 15 | BN65: 15 | BO65: 15 | BP65: 15 | BQ65: 15
... A181: SGD | B181: 1.28 | C181: 1.292 | D181: 1.289 | E181: 1.273 | F181: 1.275 | G181: 1.277 | H181: 1.261 | I181: 1.289 | J181: 1.291 | K181: 1.303 | L181: 1.299 | M181: 1.283 | N181: 1.28 | O181: 1.28 | P181: 1.285 | Q181: 1.303 | R181: 1.318 | S181: 1.334 | T181: 1.356 | U181: 1.373 | V181: 1.343 | W181: 1.339 | X181: 1.306 | Y181: 1.304 | Z181: 1.32 | AA181: 1.342 | AB181: 1.345 | AC181: 1.352 | AD181: 1.353 | AE181: 1.333 | AF181: 1.35 | AG181: 1.332 | AH181: 1.342 | AI181: 1.361 | AJ181: 1.362 | AK181: 1.361 | AL181: 1.352 | AM181: 1.333 | AN181: 1.341 | AO181: 1.331 | AP181: 1.328 | AQ181: 1.349 | AR181: 1.33 | AS181: 1.331 | AT181: 1.344 | AU181: 1.376 | AV181: 1.437 | AW181: 1.404 | AX181: 1.367 | AY181: 1.407 | AZ181: 1.39 | BA181: 1.385 | BB181: 1.363 | BC181: 1.36 | BD181: 1.343 | BE181: 1.348 | BF181: 1.37 | BG181: 1.354 | BH181: 1.359 | BI181: 1.342 | BJ181: 1.353 | BK181: 1.344 | BL181: 1.324 | BM181: 1.327 | BN181: 1.348 | BO181: 1.341 | BP181: 1.324 | BQ181: 1.326
A182: XCG | B182: 1.79 | C182: 1.79 | D182: 1.79 | E182: 1.79 | F182: 1.79 | G182: 1.79 | H182: 1.79 | I182: 1.79 | J182: 1.79 | K182: 1.79 | L182: 1.79 | M182: 1.79 | N182: 1.79 | O182: 1.79 | P182: 1.79 | Q182: 1.79 | R182: 1.79
A183: EUR | B183: 0.867 | C183: 0.875 | D183: 0.868 | E183: 0.854 | F183: 0.854 | G183: 0.867 | H183: 0.841 | I183: 0.858 | J183: 0.852 | K183: 0.865 | L183: 0.865 | M183: 0.853 | N183: 0.855 | O183: 0.856 | P183: 0.872 | Q183: 0.897 | R183: 0.88 | S183: 0.918 | T183: 0.967 | U183: 0.98 | V183: 0.953 | W183: 0.943 | X183: 0.914 | Y183: 0.908 | Z183: 0.913 | AA183: 0.918 | AB183: 0.923 | AC183: 0.926 | AD183: 0.932 | AE183: 0.914 | AF183: 0.933 | AG183: 0.913 | AH183: 0.927 | AI183: 0.937 | AJ183: 0.941 | AK183: 0.931 | AL183: 0.913 | AM183: 0.902 | AN183: 0.927 | AO183: 0.917 | AP183: 0.911 | AQ183: 0.934 | AR183: 0.933 | AS183: 0.929 | AT183: 0.938 | AU183: 0.972 | AV183: 1.032 | AW183: 0.997 | AX183: 0.965 | AY183: 0.996 | AZ183: 0.958 | BA183: 0.947 | BB183: 0.92 | BC183: 0.913 | BD183: 0.878 | BE183: 0.876 | BF183: 0.888 | BG183: 0.872 | BH183: 0.86 | BI183: 0.847 | BJ183: 0.841 | BK183: 0.838 | BL183: 0.82 | BM183: 0.826 | BN183: 0.853 | BO183: 0.837 | BP183: 0.824 | BQ183: 0.822
A184: EUR | B184: 0.867 | C184: 0.875 | D184: 0.868 | E184: 0.854 | F184: 0.854 | G184: 0.867 | H184: 0.841 | I184: 0.858 | J184: 0.852 | K184: 0.865 | L184: 0.865 | M184: 0.853 | N184: 0.855 | O184: 0.856 | P184: 0.872 | Q184: 0.897 | R184: 0.88 | S184: 0.918 | T184: 0.967 | U184: 0.98 | V184: 0.953 | W184: 0.943 | X184: 0.914 | Y184: 0.908 | Z184: 0.913 | AA184: 0.918 | AB184: 0.923 | AC184: 0.926 | AD184: 0.932 | AE184: 0.914 | AF184: 0.933 | AG184: 0.913 | AH184: 0.927 | AI184: 0.937 | AJ184: 0.941 | AK184: 0.931 | AL184: 0.913 | AM184: 0.902 | AN184: 0.927 | AO184: 0.917 | AP184: 0.911 | AQ184: 0.934 | AR184: 0.933 | AS184: 0.929 | AT184: 0.938 | AU184: 0.972 | AV184: 1.032 | AW184: 0.997 | AX184: 0.965 | AY184: 0.996 | AZ184: 0.958 | BA184: 0.947 | BB184: 0.92 | BC184: 0.913 | BD184: 0.878 | BE184: 0.876 | BF184: 0.888 | BG184: 0.872 | BH184: 0.86 | BI184: 0.847 | BJ184: 0.841 | BK184: 0.838 | BL184: 0.82 | BM184: 0.826 | BN184: 0.853 | BO184: 0.837 | BP184: 0.824 | BQ184: 0.822
A185: SBD | B185: 7.918 | C185: 7.968 | D185: 7.949 | E185: 7.899 | F185: 7.943 | G185: 7.918 | H185: 7.911 | I185: 8.006 | J185: 8.052 | K185: 8.117 | L185: 8.117 | M185: 8.091 | N185: 8.11 | O185: 8.217 | P185: 8.217 | Q185: 8.217 | R185: 8.217 | S185: 8.326 | T185: 8.333 | U185: 8.375 | V185: 8.299 | W185: 8.244 | X185: 8.203 | Y185: 8.244 | Z185: 8.347 | AA185: 8.306 | AB185: 8.333 | AC185: 8.347 | AD185: 8.177 | AE185: 8.177 | AF185: 8.177 | AG185: 8.177 | AH185: 8.177 | AI185: 8.177 | AJ185: 8.17 | AK185: 8.163 | AL185: 8.163 | AM185: 8.15 | AN185: 8.157 | AO185: 8.237 | AP185: 8.19 | AQ185: 8.117 | AR185: 8.13 | AS185: 8.137 | AT185: 8.157 | AU185: 8.097 | AV185: 8.065 | AW185: 8.019 | AX185: 8.097 | AY185: 8.097 | AZ185: 7.994 | BA185: 7.955 | BB185: 7.93 | BC185: 7.949 | BD185: 7.968 | BE185: 7.949 | BF185: 7.924 | BG185: 7.899 | BH185: 7.918 | BI185: 7.918 | BJ185: 7.893 | BK185: 7.893 | BL185: 7.825 | BM185: 7.893 | BN185: 7.886 | BO185: 8.006 | BP185: 7.831 | BQ185: 7.862
A186: SOS | B186: 24300 | C186: 24300 | D186: 24300 | E186: 24300 | F186: 24300 | G186: 24300 | H186: 24300 | I186: 24300 | J186: 24300 | K186: 24300 | L186: 24300 | M186: 24300 | N186: 24300 | O186: 24300 | P186: 24300 | Q186: 24300 | R186: 24300 | S186: 24300 | T186: 24300 | U186: 24300 | V186: 24300 | W186: 24300 | X186: 24300 | Y186: 24300 | Z186: 24300 | AA186: 24300 | AB186: 24300 | AC186: 24300 | AD186: 24300 | AE186: 24300 | AF186: 24300 | AG186: 24300 | AH186: 24300 | AI186: 24300 | AJ186: 24300 | AK186: 24300 | AL186: 24300 | AM186: 24300 | AN186: 24300 | AO186: 24300 | AP186: 24300 | AQ186: 24300 | AR186: 24300 | AS186: 24300 | AT186: 24300 | AU186: 24300 | AV186: 24300 | AW186: 24300 | AX186: 24300 | AY186: 24300 | AZ186: 24300 | BA186: 24300 | BB186: 24300 | BC186: 24300 | BD186: 24300 | BE186: 24300 | BF186: 24300 | BG186: 24300 | BH186: 24300 | BI186: 24300 | BJ186: 24300 | BK186: 24300 | BL186: 24300 | BM186: 24300 | BN186: 24300 | BO186: 24300 | BP186: 24300 | BQ186: 24300
A187: ZAR | B187: 16.131 | C187: 16.356 | D187: 16.522 | E187: 16.457 | F187: 16.501 | G187: 16.675 | H187: 15.827 | I187: 16.433 | J187: 16.891 | K187: 17.086 | L187: 17.312 | M187: 17.445 | N187: 17.523 | O187: 17.912 | P187: 17.712 | Q187: 18.421 | R187: 19.183 | S187: 18.374 | T187: 18.533 | U187: 19.072 | V187: 17.757 | W187: 18.071 | X187: 17.463 | Y187: 17.932 | Z187: 18.15 | AA187: 17.96 | AB187: 18.467 | AC187: 18.299 | AD187: 18.733 | AE187: 18.64 | AF187: 19.055 | AG187: 18.65 | AH187: 19.035 | AI187: 18.785 | AJ187: 18.826 | AK187: 18.824 | AL187: 18.926 | AM187: 18.244 | AN187: 18.592 | AO187: 19.242 | AP187: 18.363 | AQ187: 18.198 | AR187: 17.84 | AS187: 16.961 | AT187: 17.351 | AU187: 17.285 | AV187: 18.267 | AW187: 17.346 | AX187: 16.142 | AY187: 16.997 | AZ187: 16.134 | BA187: 16.058 | BB187: 14.504 | BC187: 15.023 | BD187: 15.112 | BE187: 15.377 | BF187: 16.153 | BG187: 15.255 | BH187: 15.146 | BI187: 14.137 | BJ187: 14.606 | BK187: 14.24 | BL187: 13.733 | BM187: 14.356 | BN187: 14.935 | BO187: 14.93 | BP187: 14.628 | BQ187: 15.241
A188: SSP | B188: 5660.86 | C188: 4807.022 | D188: 4714.135 | E188: 4701.956 | F188: 4603.544 | G188: 4568.5 | H188: 4550.419 | I188: 4546.887 | J188: 4555.528 | K188: 4583.584 | L188: 4592.5396 | M188: 4561.1828 | N188: 4540.3542 | O188: 4531.433 | P188: 4529.775 | Q188: 4497.255 | R188: 4471.077 | S188: 4467.88 | T188: 4393.12 | U188: 4088.574 | V188: 3811.2399 | W188: 3326.308 | X188: 2993.977 | Y188: 3087.782 | Z188: 2290.94 | AA188: 1571.264 | AB188: 1561.427 | AC188: 1558.966 | AD188: 1555.628 | AE188: 1596.757 | AF188: 1095.928 | AG188: 1082.532 | AH188: 1065.437 | AI188: 1044.443 | AJ188: 1015.76 | AK188: 1006.135 | AL188: 1008.426 | AM188: 922.618 | AN188: 966.581 | AO188: 909.768 | AP188: 857.382 | AQ188: 787.498 | AR188: 754.6895 | AS188: 677.972 | AT188: 663.32 | AU188: 619.782 | AV188: 614.67 | AW188: 651.332 | AX188: 640.083 | AY188: 524.96 | AZ188: 483.434 | BA188: 431.543 | BB188: 425.973 | BC188: 430.9 | BD188: 433.016 | BE188: 424.478 | BF188: 409 | BG188: 410.256 | BH188: 404.011 | BI188: 411.799 | BJ188: 398.452 | BK188: 351.1262 | BL188: 414.59 | BM188: 393.2883 | BN188: 177.812 | BO188: 177.37 | BP188: 177.37 | BQ188: 177.124
A189: EUR | B189: 0.867 | C189: 0.875 | D189: 0.868 | E189: 0.854 | F189: 0.854 | G189: 0.867 | H189: 0.841 | I189: 0.858 | J189: 0.852 | K189: 0.865 | L189: 0.865 | M189: 0.853 | N189: 0.855 | O189: 0.856 | P189: 0.872 | Q189: 0.897 | R189: 0.88 | S189: 0.918 | T189: 0.967 | U189: 0.98 | V189: 0.953 | W189: 0.943 | X189: 0.914 | Y189: 0.908 | Z189: 0.913 | AA189: 0.918 | AB189: 0.923 | AC189: 0.926 | AD189: 0.932 | AE189: 0.914 | AF189: 0.933 | AG189: 0.913 | AH189: 0.927 | AI189: 0.937 | AJ189: 0.941 | AK189: 0.931 | AL189: 0.913 | AM189: 0.902 | AN189: 0.927 | AO189: 0.917 | AP189: 0.911 | AQ189: 0.934 | AR189: 0.933 | AS189: 0.929 | AT189: 0.938 | AU189: 0.972 | AV189: 1.032 | AW189: 0.997 | AX189: 0.965 | AY189: 0.996 | AZ189: 0.958 | BA189: 0.947 | BB189: 0.92 | BC189: 0.913 | BD189: 0.878 | BE189: 0.876 | BF189: 0.888 | BG189: 0.872 | BH189: 0.86 | BI189: 0.847 | BJ189: 0.841 | BK189: 0.838 | BL189: 0.82 | BM189: 0.826 | BN189: 0.853 | BO189: 0.837 | BP189: 0.824 | BQ189: 0.822
A190: LKR | B190: 333.47 | C190: 335.69 | D190: 332.58 | E190: 324.32 | F190: 315.34 | G190: 310.85 | H190: 309.27 | I190: 308.98 | J190: 308.52 | K190: 303.86 | L190: 302.26 | M190: 301.5 | N190: 300.85 | O190: 300.39 | P190: 298.83 | Q190: 298.63 | R190: 297.8 | S190: 295.3 | T190: 296.6 | U190: 294.42 | V190: 289.57 | W190: 291.86 | X190: 292.38 | Y190: 300.55 | Z190: 298.76 | AA190: 302.36 | AB190: 302.42 | AC190: 299.21 | AD190: 298.1 | AE190: 305.36 | AF190: 312.25 | AG190: 321.2 | AH190: 325.94 | AI190: 325.66 | AJ190: 323.28 | AK190: 321.21 | AL190: 318.07 | AM190: 313.69 | AN190: 304.92 | AO190: 308.66 | AP190: 318.68 | AQ190: 321.27 | AR190: 363.09 | AS190: 363.42 | AT190: 362.22 | AU190: 362.94 | AV190: 361.64 | AW190: 358.79 | AX190: 357.6 | AY190: 354.12 | AZ190: 355.27 | BA190: 361.19 | BB190: 315.13 | BC190: 250.09 | BD190: 200.9 | BE190: 200 | BF190: 202.3 | BG190: 200.8 | BH190: 198.98 | BI190: 199.35 | BJ190: 199 | BK190: 198.5 | BL190: 198.1 | BM190: 196.11 | BN190: 198.6 | BO190: 193.35 | BP190: 191.86 | BQ190: 187.54
A191: XCD | B191: 2.7 | C191: 2.7 | D191: 2.7 | E191: 2.7 | F191: 2.7 | G191: 2.7 | H191: 2.7 | I191: 2.7 | J191: 2.7 | K191: 2.7 | L191: 2.7 | M191: 2.7 | N191: 2.7 | O191: 2.7 | P191: 2.7 | Q191: 2.7 | R191: 2.7 | S191: 2.7 | T191: 2.7 | U191: 2.7 | V191: 2.7 | W191: 2.7 | X191: 2.7 | Y191: 2.7 | Z191: 2.7 | AA191: 2.7 | AB191: 2.7 | AC191: 2.7 | AD191: 2.7 | AE191: 2.7 | AF191: 2.7 | AG191: 2.7 | AH191: 2.7 | AI191: 2.7 | AJ191: 2.7 | AK191: 2.7 | AL191: 2.7 | AM191: 2.7 | AN191: 2.7 | AO191: 2.7 | AP191: 2.7 | AQ191: 2.7 | AR191: 2.7 | AS191: 2.7 | AT191: 2.7 | AU191: 2.7 | AV191: 2.7 | AW191: 2.7 | AX191: 2.7 | AY191: 2.7 | AZ191: 2.7 | BA191: 2.7 | BB191: 2.7 | BC191: 2.7 | BD191: 2.7 | BE191: 2.7 | BF191: 2.7 | BG191: 2.7 | BH191: 2.7 | BI191: 2.7 | BJ191: 2.7 | BK191: 2.7 | BL191: 2.7 | BM191: 2.7 | BN191: 2.7 | BO191: 2.7 | BP191: 2.7 | BQ191: 2.7
A192: SDG | B192: 4300 | C192: 4300 | D192: 3800 | E192: 3800 | F192: 3450 | G192: 3350 | H192: 3349.999 | I192: 2400 | J192: 2400 | K192: 2400 | L192: 2400 | M192: 2400 | N192: 2400 | O192: 2140 | P192: 2140 | Q192: 2020 | R192: 2020 | S192: 2020 | T192: 1990 | U192: 1987 | V192: 1987 | W192: 1987 | X192: 1982 | Y192: 1950 | Z192: 1850 | AA192: 1840 | AB192: 1650 | AC192: 1255 | AD192: 1090 | AE192: 1075 | AF192: 1035 | AG192: 910 | AH192: 810 | AI192: 760 | AJ192: 695 | AK192: 621 | AL192: 590 | AM192: 568.9 | AN192: 573 | AO192: 593 | AP192: 593 | AQ192: 587.5 | AR192: 579 | AS192: 579 | AT192: 578 | AU192: 578.5 | AV192: 577 | AW192: 574 | AX192: 568 | AY192: 567.5 | AZ192: 566 | BA192: 567 | BB192: 563 | BC192: 590 | BD192: 457 | BE192: 447.5 | BF192: 446 | BG192: 448 | BH192: 448 | BI192: 445 | BJ192: 446.5 | BK192: 441 | BL192: 420 | BM192: 381.5 | BN192: 380.5 | BO192: 376 | BP192: 55 | BQ192: 55
A193: SRD | B193: 37.477 | C193: 37.304 | D193: 37.026 | E193: 36.915 | F193: 37.284 | G193: 37.433 | H193: 37.868 | I193: 38.049 | J193: 38.538 | K193: 38.814 | L193: 39.063 | M193: 39.455 | N193: 37.76 | O193: 37.49 | P193: 36.836 | Q193: 36.794 | R193: 36.822 | S193: 35.844 | T193: 35.167 | U193: 35.134 | V193: 35.096 | W193: 35.33 | X193: 32.026 | Y193: 28.773 | Z193: 28.927 | AA193: 29.779 | AB193: 31.349 | AC193: 32.517 | AD193: 34.07 | AE193: 35.152 | AF193: 36.443 | AG193: 36.833 | AH193: 37.1 | AI193: 38.162 | AJ193: 38.134 | AK193: 38.392 | AL193: 38.471 | AM193: 37.732 | AN193: 37.765 | AO193: 37.552 | AP193: 37.038 | AQ193: 34.091 | AR193: 32.066 | AS193: 31.8 | AT193: 31.688 | AU193: 30.214 | AV193: 27.98 | AW193: 26.794 | AX193: 24.025 | AY193: 22.4 | AZ193: 21.7 | BA193: 21.4 | BB193: 21.25 | BC193: 21.25 | BD193: 21.25 | BE193: 21.1 | BF193: 21.25 | BG193: 21.2 | BH193: 21.2 | BI193: 21.1 | BJ193: 21 | BK193: 21 | BL193: 20.07 | BM193: 16 | BN193: 16 | BO193: 15.5 | BP193: 14.02 | BQ193: 14.02
A194: SEK | B194: 9.555 | C194: 9.645 | D194: 9.545 | E194: 9.326 | F194: 9.243 | G194: 9.309 | H194: 8.884 | I194: 9.202 | J194: 9.245 | K194: 9.468 | L194: 9.516 | M194: 9.335 | N194: 9.543 | O194: 9.537 | P194: 9.573 | Q194: 9.726 | R194: 9.791 | S194: 10.095 | T194: 10.925 | U194: 11.28 | V194: 10.963 | W194: 10.932 | X194: 10.376 | Y194: 10.389 | Z194: 10.516 | AA194: 10.451 | AB194: 10.295 | AC194: 10.833 | AD194: 10.743 | AE194: 10.223 | AF194: 10.541 | AG194: 10.264 | AH194: 10.46 | AI194: 10.877 | AJ194: 10.88 | AK194: 11.105 | AL194: 10.828 | AM194: 10.467 | AN194: 10.751 | AO194: 10.316 | AP194: 10.319 | AQ194: 10.674 | AR194: 10.398 | AS194: 10.457 | AT194: 10.177 | AU194: 10.398 | AV194: 11.349 | AW194: 10.602 | AX194: 10.006 | AY194: 10.566 | AZ194: 10.165 | BA194: 9.969 | BB194: 9.47 | BC194: 9.729 | BD194: 9.271 | BE194: 8.965 | BF194: 9.098 | BG194: 8.71 | BH194: 8.767 | BI194: 8.623 | BJ194: 8.552 | BK194: 8.469 | BL194: 8.299 | BM194: 8.369 | BN194: 8.757 | BO194: 8.486 | BP194: 8.32 | BQ194: 8.343
... A224: ZWG | B224: 25.701 | C224: 25.933 | D224: 25.765 | E224: 24.646 | F224: 24.6 | G224: 24.852 | H224: 25.001 | I224: 25.218 | J224: 25.46 | K224: 26.392 | L224: 26.648 | M224: 26.729 | N224: 26.76 | O224: 26.891 | P224: 26.953 | Q224: 26.834 | R224: 26.79 | S224: 26.641 | T224: 26.407 | U224: 25.883 | V224: 25.647 | W224: 25.589 | X224: 26.069 | Y224: 13.891 | Z224: 13.782 | AA224: 13.761 | AB224: 13.431 | AC224: 13.665 | AD224: 20945.169 | AE224: 16878.373 | AF224: 11450.664 | AG224: 6908.986 | AH224: 5839.243 | AI224: 5739.522 | AJ224: 5592.962 | AK224: 4648.386 | AL224: 4559.741 | AM224: 5297.503 | AN224: 4868.511 | AO224: 1125.667 | AP224: 944.713 | AQ224: 907.924 | AR224: 796.63 | AS224: 686.572 | AT224: 645.414 | AU224: 620.464 | AV224: 611.75 | AW224: 567.511 | AX224: 459.037 | AY224: 375.522 | AZ224: 317.198 | BA224: 270.101 | BB224: 142.225 | BC224: 126.903 | BD224: 115.9 | BE224: 105.949 | BF224: 103.054 | BG224: 90.8 | BH224: 84.5 | BI224: 83.8 | BJ224: 83.7 | BK224: 83.24 | BL224: 82.7 | BM224: 82.5 | BN224: 82.2 | BO224: 81.9 | BP224: 80.05 | BQ224: 79.74

Sheet Reference
A1: Month_Number | B1: Month_List | C1: DS_Country_List | D1: DS_Currency_List | E1: InsideOutsideList | G1: ItemCategoryList | H1: Alcohol_and_Tobacco | I1: Clothing_and_Footwear | J1: Education | K1: Food_and_Non_Alcoholic_Beverages | L1: Furniture_Household_and_Routine_Home_Maintenance | M1: Health_Out_of_Pocket | N1: Housing | O1: Information_and_Communication | P1: Insurance_and_Financial_Services | Q1: Other | R1: Personal_and_Miscellaneous_Goods_and_Services | S1: Recreation_and_Culture | T1: Restaurants_and_Accommodation_Services | U1: Transport | W1: Item_List_Number | X1: Time_Span | Y1: Item_List | AA1: Summary_View_List | AB1: Summary_View_Explainer
A2: 1 | B2: Jan | C2: Afghanistan | D2: AFN | E2: Inside | G2: Alcohol and Tobacco | H2: Alcoholic Beverages | I2: Cleaning, Repair, Tailoring and Hire of Clothing | J2: Non-Tertiary: Tuition and Enrolment Fees | K2: Food Purchased in Markets | L2: Domestic Service | M2: Assistive Products | N2: Rent or Rent Equivalent | O2: Information and Communication Equipment | P2: Financial Services | Q2: Other Monthly Expenditures | R2: Electric Appliances for Personal Care | S2: Cultural Services | T2: Accommodation Services | U2: Air Travel | W2: 3 | X2: M | Y2: Alcoholic Beverages | AA2: Expenditures from Last 30 Days (USD) | AB2: Values displayed are the total expenses entered in the Data Table from past 30 days
A3: 2 | B3: Feb | C3: Albania | D3: ALL | E3: Outside | G3: Clothing and Footwear | H3: Tobacco and Tobacco Products | I3: Clothing Garments | J3: Non-Tertiary: Boarding and Accommodation | K3: Non-Alcoholic Beverages Purchased in Markets | L3: Furniture | M3: In-Patient Care Services | N3: Utilities | O3: Information and Communication Services | P3: Insurance Connected with Dwelling | Q3: Other Yearly Expenditures | R3: Hairdressing Salons and Personal Grooming Establishments | S3: Games, Toys and Hobby-Related Articles | T3: Canteens, Cafeterias and Refectories | U3: Car 1 (Net of Purchase/Sale) | W3: 4 | X3: M | Y3: Tobacco and Tobacco Products | AA3: Expenditures from Last 30 Days (Local Currency) | AB3: Values displayed are the total expenses entered in the Data Table from past 30 days
A4: 3 | B4: Mar | C4: Algeria | D4: DZD | G4: Education | I4: Other Clothing and Accessories | J4: Non-Tertiary: Canteens and Cafeterias | L4: Glassware, Tableware, and Utensils | M4: Medical Products | P4: Insurance Connected with Health (supplementary medical insurance) | Q4: Remittances Except Medical and Educational Expenses | R4: Jewelry and Watches | S4: Garden Products, Plants and Flowers | T4: Restaurants, Cafes and Similar Eating Facilities | U4: Car 2 (Net of Purchase/Sale) | W4: 5 | X4: M | Y4: Cleaning, Repair, Tailoring and Hire of Clothing | AA4: All Expenditures (USD) | AB4: Values displayed are the total of all expenses entered in the Data Table
A5: 4 | B5: Apr | C5: Angola | D5: AOA | G5: Food and Non Alcoholic Beverages | I5: Shoes and Footwear | J5: Non-Tertiary: Books | L5: Household Textiles | M5: Medicine | P5: Insurance Connected with Transport | R5: Other Appliances, Articles and Products for Personal Care | S5: Major Recreational Durables | U5: Fuels and Lubricants for Personal Transport Equipment | W5: 26 | X5: Y | Y5: Clothing Garments | AA5: All Expenditures (Local Currency) | AB5: Values displayed are the total of all expenses entered in the Data Table
A6: 5 | B6: May | C6: Anguilla | D6: XCD | G6: Furniture Household and Routine Home Maintenance | J6: Non-Tertiary: Transport to/from School | L6: Major Household Appliances | M6: Outpatient Care Services | R6: Other Personal Effects | S6: Newspapers, Books and Stationery | U6: Maintenance and Repair of Personal Transport Equipment | W6: 27 | X6: Y | Y6: Other Clothing and Accessories | AA6: Estimated Monthly Expenditures (USD) | AB6: Values displayed are an estimate of monthly expenses based on total of monthly expenses from past 30 days, yearly expensees from past year divided by 12, and infrequent expenses from past 5 years divided by 60.
A7: 6 | B7: Jun | C7: Antigua and Barbuda | D7: XCD | G7: Health Out of Pocket | J7: Non-Tertiary: Childcare Services | L7: Non-Durable Household Goods | R7: Other Services | S7: Package Holidays | U7: Other Services Related to Personal Transport Equipment | W7: 28 | X7: Y | Y7: Shoes and Footwear | AA7: Estimated Monthly Expenditures (Local Currency) | AB7: Values displayed are an estimate of monthly expenses based on total of monthly expenses from past 30 days, yearly expensees from past year divided by 12, and infrequent expenses from past 5 years divided by 60.
A8: 7 | B8: Jul | C8: Argentina | D8: ARS | G8: Housing | J8: Non-Tertiary: Recreation and Culture | L8: Small Household Appliances | R8: Social Protection | S8: Pets and Pet Products | U8: Other Transport of Goods | W8: 52a | X8: Y | Y8: Non-Tertiary: Tuition and Enrolment Fees
A9: 8 | B9: Aug | C9: Armenia | D9: AMD | G9: Information and Communication | J9: Tertiary: Tuition and Enrolment Fees | L9: Tools and Equipment for House and Garden | S9: Recreational and Sporting Services | U9: Other Vehicle 1 (Net of Purchase/Sale) | W9: 52b | X9: Y | Y9: Non-Tertiary: Boarding and Accommodation
A10: 9 | B10: Sep | C10: Aruba | D10: AWG | G10: Insurance and Financial Services | J10: Tertiary: Boarding and Accommodation | S10: Sport, Camping and Open-Air Equipment | U10: Other Vehicle 2 (Net of Purchase/Sale) | W10: 52c | X10: Y | Y10: Non-Tertiary: Canteens and Cafeterias
A11: 10 | B11: Oct | C11: Australia | D11: AUD | G11: Other | J11: Tertiary: Canteens and Cafeterias | S11: Veterinary and Other Services for Pets | U11: Parts and Accessories for Personal Transport Equipment | W11: 52d | X11: Y | Y11: Non-Tertiary: Books
A12: 11 | B12: Nov | C12: Austria | D12: EUR | G12: Personal and Miscellaneous Goods and Services | J12: Tertiary: Books | U12: Postal and Courier Services | W12: 52e | X12: Y | Y12: Non-Tertiary: Transport to/from School
A13: 12 | B13: Dec | C13: Azerbaijan | D13: AZN | G13: Recreation and Culture | J13: Tertiary: Transport to/from School | U13: Public Transport and Taxi Services | W13: 52f | X13: Y | Y13: Non-Tertiary: Childcare Services
C14: Bahamas | D14: BSD | G14: Restaurants and Accommodation Services | J14: Tertiary: Childcare Services | W14: 52g | X14: Y | Y14: Non-Tertiary: Recreation and Culture
C15: Bahrain | D15: BHD | G15: Transport | J15: Tertiary: Recreation and Culture | W15: 53a | X15: Y | Y15: Tertiary: Tuition and Enrolment Fees
C16: Bangladesh | D16: BDT | J16: Unclassified: Tuition and Enrolment Fees | W16: 53b | X16: Y | Y16: Tertiary: Boarding and Accommodation
C17: Barbados | D17: BBD | W17: 53c | X17: Y | Y17: Tertiary: Canteens and Cafeterias
C18: Belarus | D18: BYN | W18: 53d | X18: Y | Y18: Tertiary: Books
C19: Belgium | D19: EUR | W19: 53e | X19: Y | Y19: Tertiary: Transport to/from School
C20: Belize | D20: BZD | W20: 53f | X20: Y | Y20: Tertiary: Childcare Services
C21: Benin | D21: XOF | W21: 53g | X21: Y | Y21: Tertiary: Recreation and Culture
C22: Bermuda | D22: BMD | W22: 54a | X22: Y | Y22: Unclassified: Tuition and Enrolment Fees
C23: Bhutan | D23: BTN | W23: 1 | X23: M | Y23: Food Purchased in Markets
C24: Bolivia | D24: BOB | W24: 2 | X24: M | Y24: Non-Alcoholic Beverages Purchased in Markets
C25: Bonaire | D25: USD | W25: 29 | X25: Y | Y25: Furniture
C26: Bosnia and Herzegovina | D26: BAM | W26: 32 | X26: Y | Y26: Glassware, Tableware, and Utensils
C27: Botswana | D27: BWP | W27: 30 | X27: Y | Y27: Household Textiles
C28: Brazil | D28: BRL | W28: 55 | X28: 5Y | Y28: Major Household Appliances
C29: British Virgin Islands | D29: USD | W29: 6 | X29: M | Y29: Non-Durable Household Goods
C30: Bulgaria | D30: EUR | W30: 31 | X30: Y | Y30: Small Household Appliances
C31: Burkina Faso | D31: XOF | W31: 33 | X31: Y | Y31: Tools and Equipment for House and Garden
C32: Burundi | D32: BIF | W32: 35 | X32: Y | Y32: Assistive Products
C33: Cabo Verde | D33: CVE | W33: 37 | X33: Y | Y33: In-Patient Care Services
C34: Cambodia | D34: KHR | W34: 34 | X34: Y | Y34: Medical Products
... C36: Canada | D36: CAD | W36: 36 | X36: Y | Y36: Outpatient Care Services
C37: Cayman Islands | D37: KYD | W37: H.D | X37: M | Y37: Domestic Service
C38: Central African Republic | D38: XAF | W38: H.R | X38: M | Y38: Rent or Rent Equivalent
C39: Chad | D39: XAF | W39: H.U | X39: M | Y39: Utilities
C40: Chile | D40: CLP | W40: 42 | X40: Y | Y40: Information and Communication Equipment
C41: China | D41: CNY | W41: 12 | X41: M | Y41: Information and Communication Services
C42: China, Hong Kong (SAR) | D42: HKD | W42: 48 | X42: Y | Y42: Financial services
C43: China, Macao (SAR) | D43: MOP | W43: 22 | X43: M | Y43: Insurance connected with dwelling
C44: Colombia | D44: COP | W44: 20 | X44: M | Y44: Insurance connected with health (supplementary medical insurance)
C45: Comoros | D45: KMF | W45: 21 | X45: M | Y45: Insurance connected with transport
C46: Congo | D46: XAF | W46: 25 | X46: M | Y46: Other Monthly Expenditures
C47: Cook Islands | D47: NZD | W47: 51 | X47: Y | Y47: Other Yearly Expenditures
C48: Costa Rica | D48: CRC | W48: 24 | X48: M | Y48: Remittances except medical and educational expenses
C49: Côte d'Ivoire | D49: XOF | W49: 49a | X49: Y | Y49: Electric appliances for personal care
C50: Croatia | D50: EUR | W50: 23 | X50: M | Y50: Hairdressing salons and personal grooming establishments
C51: Cuba | D51: CUP | W51: 57 | X51: 5Y | Y51: Jewelry and watches
C52: Cyprus | D52: EUR | W52: 49b | X52: Y | Y52: Other appliances, articles and products for personal care
C53: Czechia | D53: CZK | W53: 50b | X53: Y | Y53: Other personal effects
C54: Democratic People's Republic of Korea | D54: KPW | W54: 50c | X54: Y | Y54: Other services
C55: Democratic Republic of the Congo | D55: CDF | W55: 50a | X55: Y | Y55: Social protection
C56: Denmark | D56: DKK | W56: 15 | X56: M | Y56: Cultural services
C57: Djibouti | D57: DJF | W57: 44 | X57: Y | Y57: Games, toys and hobby-related articles
C58: Dominica | D58: XCD | W58: 45 | X58: Y | Y58: Garden products, plants and flowers
C59: Dominican Republic | D59: DOP | W59: 56 | X59: 5Y | Y59: Major recreational durables
C60: Ecuador | D60: USD | W60: 17 | X60: M | Y60: Newspapers, books and stationery
C61: Egypt | D61: EGP | W61: 46 | X61: Y | Y61: Package holidays
C62: El Salvador | D62: USD | W62: 13 | X62: M | Y62: Pets and pet products
C63: Equatorial Guinea | D63: XAF | W63: 16 | X63: M | Y63: Recreational and sporting services
C64: Eritrea | D64: ERN | W64: 43 | X64: Y | Y64: Sport, camping and open-air equipment
C65: Estonia | D65: EUR | W65: 14 | X65: M | Y65: Veterinary and other services for pets
C66: Eswatini | D66: SZL | W66: 47 | X66: Y | Y66: Accommodation services
C67: Ethiopia | D67: ETB | W67: 19 | X67: M | Y67: Canteens, cafeterias and refectories
... C69: Finland | D69: EUR | W69: 41 | X69: Y | Y69: Air Travel
C70: France | D70: EUR | W70: 58a | X70: 5Y | Y70: Car 1 (Net of Purchase/Sale)
C71: French Guiana | D71: EUR | W71: 58b | X71: 5Y | Y71: Car 2 (Net of Purchase/Sale)
C72: Gabon | D72: XAF | W72: 8 | X72: M | Y72: Fuels and Lubricants for Personal Transport Equipment
C73: Gambia | D73: GMD | W73: 39 | X73: Y | Y73: Maintenance and Repair of Personal Transport Equipment
C74: Georgia | D74: GEL | W74: 40 | X74: Y | Y74: Other Services Related to Personal Transport Equipment
C75: Germany | D75: EUR | W75: 11 | X75: M | Y75: Other Transport of Goods
C76: Ghana | D76: GHS | W76: 59a | X76: 5Y | Y76: Other vehicle 1 (Net of Purchase/Sale)
C77: Gibraltar | D77: GIP | W77: 59b | X77: 5Y | Y77: Other vehicle 2 (Net of Purchase/Sale)
C78: Greece | D78: EUR | W78: 38 | X78: Y | Y78: Parts and Accessories for Personal Transport Equipment
C79: Grenada | D79: XCD | W79: 10 | X79: M | Y79: Postal and Courier Services
C80: Guatemala | D80: GTQ | W80: 9 | X80: M | Y80: Public Transport and Taxi Services
C81: Guinea | D81: GNF
C82: Guinea Bissau | D82: XOF
C83: Guyana | D83: GYD
C84: Haiti | D84: HTG
C85: Honduras | D85: HNL
C86: Hungary | D86: HUF
C87: Iceland | D87: ISK
C88: India | D88: INR
C89: Indonesia | D89: IDR
C90: Iran | D90: IRR
C91: Iraq | D91: IQD
C92: Ireland | D92: EUR
... C206: Zimbabwe | D206: ZWG

Sheet Summary Table Toggle
B2: EXPENDITURES IN US DOLLAR | C2: 3 | D2: 4 | E2: 1 | F2: 2 | G2: 5 | H2: 6
B3: Category | C3: Past Month USD | D3: Past Month LC | E3: Total Expense USD | F3: Total Expense LC | G3: Estimated Monthly USD | H3: Estimated Monthly LC
B4: Food and Non Alcoholic Beverages | C4: =SUMIFS('Data Table'!$J:$J,'Data Table'!$B:$B,"<="&TODAY(),'Data Table'!$C:$C,$B4)-SUMIFS('Data Table'!$J:$J,'Data Table'!$B:$B,"<="&(TODAY()-30),'Data Table'!C:C,$B4) -> 141.14326 | D4: =C4*(VLOOKUP((_xlfn.XLOOKUP(DSCountry,DS_Country_List,DS_Currency_List)),'FX Rates'!$A$1:$BQ$152,2)) -> 200 | E4: =SUMIF('Data Table'!$C:$C,$B4,'Data Table'!$J:$J) -> 141.14326 | F4: =E4*(VLOOKUP((_xlfn.XLOOKUP(DSCountry,DS_Country_List,DS_Currency_List)),'FX Rates'!$A$1:$BQ$152,2)) -> 200 | G4: =SUMIFS('Data Table'!J:J,'Data Table'!B:B,"<="&TODAY(),'Data Table'!I:I,"M",'Data Table'!C:C,$B4)-SUMIFS('Data Table'!J:J,'Data Table'!B:B,"<="&(TODAY()-30),'Data Table'!I:I,"M",'Data Table'!C:C,$B4)+(SUMIFS('Data Table'!J:J,'Data Table'!B:B,"<="&TODAY(),'Data Table'!I:I,"Y",'Data Table'!C:C,$B4)/12)-(SUMIFS('Data Table'!J:J,'Data Table'!B:B,"<="&(TODAY()-365),'Data Table'!I:I,"Y",'Data Table'!C:C,$B4)/12)+(SUMIFS('Data Table'!J:J,'Data Table'!B:B,"<="&TODAY(),'Data Table'!I:I,"5Y",'Data Table'!C:C,$B4)/60-SUMIFS('Data Table'!J:J,'Data Table'!B:B,"<="&(TODAY()-1826),'Data Table'!I:I,"5Y",'Data Table'!C:C,$B4)/60) -> 141.14326 | H4: =G4*(VLOOKUP((_xlfn.XLOOKUP(DSCountry,DS_Country_List,DS_Currency_List)),'FX Rates'!$A$1:$BQ$152,2)) -> 200
B5: Alcohol and Tobacco | C5: =SUMIFS('Data Table'!$J:$J,'Data Table'!$B:$B,"<="&TODAY(),'Data Table'!$C:$C,$B5)-SUMIFS('Data Table'!$J:$J,'Data Table'!$B:$B,"<="&(TODAY()-30),'Data Table'!C:C,$B5) -> 0 | D5: =C5*(VLOOKUP((_xlfn.XLOOKUP(DSCountry,DS_Country_List,DS_Currency_List)),'FX Rates'!$A$1:$BQ$152,2)) -> 0 | E5: =SUMIF('Data Table'!$C:$C,$B5,'Data Table'!$J:$J) -> 0 | F5: =E5*(VLOOKUP((_xlfn.XLOOKUP(DSCountry,DS_Country_List,DS_Currency_List)),'FX Rates'!$A$1:$BQ$152,2)) -> 0 | G5: =SUMIFS('Data Table'!J:J,'Data Table'!B:B,"<="&TODAY(),'Data Table'!I:I,"M",'Data Table'!C:C,$B5)-SUMIFS('Data Table'!J:J,'Data Table'!B:B,"<="&(TODAY()-30),'Data Table'!I:I,"M",'Data Table'!C:C,$B5)+(SUMIFS('Data Table'!J:J,'Data Table'!B:B,"<="&TODAY(),'Data Table'!I:I,"Y",'Data Table'!C:C,$B5)/12)-(SUMIFS('Data Table'!J:J,'Data Table'!B:B,"<="&(TODAY()-365),'Data Table'!I:I,"Y",'Data Table'!C:C,$B5)/12)+(SUMIFS('Data Table'!J:J,'Data Table'!B:B,"<="&TODAY(),'Data Table'!I:I,"5Y",'Data Table'!C:C,$B5)/60-SUMIFS('Data Table'!J:J,'Data Table'!B:B,"<="&(TODAY()-1826),'Data Table'!I:I,"5Y",'Data Table'!C:C,$B5)/60) -> 0 | H5: =G5*(VLOOKUP((_xlfn.XLOOKUP(DSCountry,DS_Country_List,DS_Currency_List)),'FX Rates'!$A$1:$BQ$152,2)) -> 0
B6: Clothing and Footwear | C6: =SUMIFS('Data Table'!$J:$J,'Data Table'!$B:$B,"<="&TODAY(),'Data Table'!$C:$C,$B6)-SUMIFS('Data Table'!$J:$J,'Data Table'!$B:$B,"<="&(TODAY()-30),'Data Table'!C:C,$B6) -> 0 | D6: =C6*(VLOOKUP((_xlfn.XLOOKUP(DSCountry,DS_Country_List,DS_Currency_List)),'FX Rates'!$A$1:$BQ$152,2)) -> 0 | E6: =SUMIF('Data Table'!$C:$C,$B6,'Data Table'!$J:$J) -> 0 | F6: =E6*(VLOOKUP((_xlfn.XLOOKUP(DSCountry,DS_Country_List,DS_Currency_List)),'FX Rates'!$A$1:$BQ$152,2)) -> 0 | G6: =SUMIFS('Data Table'!J:J,'Data Table'!B:B,"<="&TODAY(),'Data Table'!I:I,"M",'Data Table'!C:C,$B6)-SUMIFS('Data Table'!J:J,'Data Table'!B:B,"<="&(TODAY()-30),'Data Table'!I:I,"M",'Data Table'!C:C,$B6)+(SUMIFS('Data Table'!J:J,'Data Table'!B:B,"<="&TODAY(),'Data Table'!I:I,"Y",'Data Table'!C:C,$B6)/12)-(SUMIFS('Data Table'!J:J,'Data Table'!B:B,"<="&(TODAY()-365),'Data Table'!I:I,"Y",'Data Table'!C:C,$B6)/12)+(SUMIFS('Data Table'!J:J,'Data Table'!B:B,"<="&TODAY(),'Data Table'!I:I,"5Y",'Data Table'!C:C,$B6)/60-SUMIFS('Data Table'!J:J,'Data Table'!B:B,"<="&(TODAY()-1826),'Data Table'!I:I,"5Y",'Data Table'!C:C,$B6)/60) -> 0 | H6: =G6*(VLOOKUP((_xlfn.XLOOKUP(DSCountry,DS_Country_List,DS_Currency_List)),'FX Rates'!$A$1:$BQ$152,2)) -> 0
B7: Housing | C7: =SUMIFS('Data Table'!$J:$J,'Data Table'!$B:$B,"<="&TODAY(),'Data Table'!$C:$C,$B7)-SUMIFS('Data Table'!$J:$J,'Data Table'!$B:$B,"<="&(TODAY()-30),'Data Table'!C:C,$B7) -> 0 | D7: =C7*(VLOOKUP((_xlfn.XLOOKUP(DSCountry,DS_Country_List,DS_Currency_List)),'FX Rates'!$A$1:$BQ$152,2)) -> 0 | E7: =SUMIF('Data Table'!$C:$C,$B7,'Data Table'!$J:$J) -> 0 | F7: =E7*(VLOOKUP((_xlfn.XLOOKUP(DSCountry,DS_Country_List,DS_Currency_List)),'FX Rates'!$A$1:$BQ$152,2)) -> 0 | G7: =SUMIFS('Data Table'!J:J,'Data Table'!B:B,"<="&TODAY(),'Data Table'!I:I,"M",'Data Table'!C:C,$B7)-SUMIFS('Data Table'!J:J,'Data Table'!B:B,"<="&(TODAY()-30),'Data Table'!I:I,"M",'Data Table'!C:C,$B7)+(SUMIFS('Data Table'!J:J,'Data Table'!B:B,"<="&TODAY(),'Data Table'!I:I,"Y",'Data Table'!C:C,$B7)/12)-(SUMIFS('Data Table'!J:J,'Data Table'!B:B,"<="&(TODAY()-365),'Data Table'!I:I,"Y",'Data Table'!C:C,$B7)/12)+(SUMIFS('Data Table'!J:J,'Data Table'!B:B,"<="&TODAY(),'Data Table'!I:I,"5Y",'Data Table'!C:C,$B7)/60-SUMIFS('Data Table'!J:J,'Data Table'!B:B,"<="&(TODAY()-1826),'Data Table'!I:I,"5Y",'Data Table'!C:C,$B7)/60) -> 0 | H7: =G7*(VLOOKUP((_xlfn.XLOOKUP(DSCountry,DS_Country_List,DS_Currency_List)),'FX Rates'!$A$1:$BQ$152,2)) -> 0
B8: Furniture Household and Routine Home Maintenance | C8: =SUMIFS('Data Table'!$J:$J,'Data Table'!$B:$B,"<="&TODAY(),'Data Table'!$C:$C,$B8)-SUMIFS('Data Table'!$J:$J,'Data Table'!$B:$B,"<="&(TODAY()-30),'Data Table'!C:C,$B8) -> 0 | D8: =C8*(VLOOKUP((_xlfn.XLOOKUP(DSCountry,DS_Country_List,DS_Currency_List)),'FX Rates'!$A$1:$BQ$152,2)) -> 0 | E8: =SUMIF('Data Table'!$C:$C,$B8,'Data Table'!$J:$J) -> 0 | F8: =E8*(VLOOKUP((_xlfn.XLOOKUP(DSCountry,DS_Country_List,DS_Currency_List)),'FX Rates'!$A$1:$BQ$152,2)) -> 0 | G8: =SUMIFS('Data Table'!J:J,'Data Table'!B:B,"<="&TODAY(),'Data Table'!I:I,"M",'Data Table'!C:C,$B8)-SUMIFS('Data Table'!J:J,'Data Table'!B:B,"<="&(TODAY()-30),'Data Table'!I:I,"M",'Data Table'!C:C,$B8)+(SUMIFS('Data Table'!J:J,'Data Table'!B:B,"<="&TODAY(),'Data Table'!I:I,"Y",'Data Table'!C:C,$B8)/12)-(SUMIFS('Data Table'!J:J,'Data Table'!B:B,"<="&(TODAY()-365),'Data Table'!I:I,"Y",'Data Table'!C:C,$B8)/12)+(SUMIFS('Data Table'!J:J,'Data Table'!B:B,"<="&TODAY(),'Data Table'!I:I,"5Y",'Data Table'!C:C,$B8)/60-SUMIFS('Data Table'!J:J,'Data Table'!B:B,"<="&(TODAY()-1826),'Data Table'!I:I,"5Y",'Data Table'!C:C,$B8)/60) -> 0 | H8: =G8*(VLOOKUP((_xlfn.XLOOKUP(DSCountry,DS_Country_List,DS_Currency_List)),'FX Rates'!$A$1:$BQ$152,2)) -> 0
B9: Health Out of Pocket | C9: =SUMIFS('Data Table'!$J:$J,'Data Table'!$B:$B,"<="&TODAY(),'Data Table'!$C:$C,$B9)-SUMIFS('Data Table'!$J:$J,'Data Table'!$B:$B,"<="&(TODAY()-30),'Data Table'!C:C,$B9) -> 0 | D9: =C9*(VLOOKUP((_xlfn.XLOOKUP(DSCountry,DS_Country_List,DS_Currency_List)),'FX Rates'!$A$1:$BQ$152,2)) -> 0 | E9: =SUMIF('Data Table'!$C:$C,$B9,'Data Table'!$J:$J) -> 0 | F9: =E9*(VLOOKUP((_xlfn.XLOOKUP(DSCountry,DS_Country_List,DS_Currency_List)),'FX Rates'!$A$1:$BQ$152,2)) -> 0 | G9: =SUMIFS('Data Table'!J:J,'Data Table'!B:B,"<="&TODAY(),'Data Table'!I:I,"M",'Data Table'!C:C,$B9)-SUMIFS('Data Table'!J:J,'Data Table'!B:B,"<="&(TODAY()-30),'Data Table'!I:I,"M",'Data Table'!C:C,$B9)+(SUMIFS('Data Table'!J:J,'Data Table'!B:B,"<="&TODAY(),'Data Table'!I:I,"Y",'Data Table'!C:C,$B9)/12)-(SUMIFS('Data Table'!J:J,'Data Table'!B:B,"<="&(TODAY()-365),'Data Table'!I:I,"Y",'Data Table'!C:C,$B9)/12)+(SUMIFS('Data Table'!J:J,'Data Table'!B:B,"<="&TODAY(),'Data Table'!I:I,"5Y",'Data Table'!C:C,$B9)/60-SUMIFS('Data Table'!J:J,'Data Table'!B:B,"<="&(TODAY()-1826),'Data Table'!I:I,"5Y",'Data Table'!C:C,$B9)/60) -> 0 | H9: =G9*(VLOOKUP((_xlfn.XLOOKUP(DSCountry,DS_Country_List,DS_Currency_List)),'FX Rates'!$A$1:$BQ$152,2)) -> 0
B10: Transport | C10: =SUMIFS('Data Table'!$J:$J,'Data Table'!$B:$B,"<="&TODAY(),'Data Table'!$C:$C,$B10)-SUMIFS('Data Table'!$J:$J,'Data Table'!$B:$B,"<="&(TODAY()-30),'Data Table'!C:C,$B10) -> 0 | D10: =C10*(VLOOKUP((_xlfn.XLOOKUP(DSCountry,DS_Country_List,DS_Currency_List)),'FX Rates'!$A$1:$BQ$152,2)) -> 0 | E10: =SUMIF('Data Table'!$C:$C,$B10,'Data Table'!$J:$J) -> 0 | F10: =E10*(VLOOKUP((_xlfn.XLOOKUP(DSCountry,DS_Country_List,DS_Currency_List)),'FX Rates'!$A$1:$BQ$152,2)) -> 0 | G10: =SUMIFS('Data Table'!J:J,'Data Table'!B:B,"<="&TODAY(),'Data Table'!I:I,"M",'Data Table'!C:C,$B10)-SUMIFS('Data Table'!J:J,'Data Table'!B:B,"<="&(TODAY()-30),'Data Table'!I:I,"M",'Data Table'!C:C,$B10)+(SUMIFS('Data Table'!J:J,'Data Table'!B:B,"<="&TODAY(),'Data Table'!I:I,"Y",'Data Table'!C:C,$B10)/12)-(SUMIFS('Data Table'!J:J,'Data Table'!B:B,"<="&(TODAY()-365),'Data Table'!I:I,"Y",'Data Table'!C:C,$B10)/12)+(SUMIFS('Data Table'!J:J,'Data Table'!B:B,"<="&TODAY(),'Data Table'!I:I,"5Y",'Data Table'!C:C,$B10)/60-SUMIFS('Data Table'!J:J,'Data Table'!B:B,"<="&(TODAY()-1826),'Data Table'!I:I,"5Y",'Data Table'!C:C,$B10)/60) -> 0 | H10: =G10*(VLOOKUP((_xlfn.XLOOKUP(DSCountry,DS_Country_List,DS_Currency_List)),'FX Rates'!$A$1:$BQ$152,2)) -> 0
B11: Information and Communication | C11: =SUMIFS('Data Table'!$J:$J,'Data Table'!$B:$B,"<="&TODAY(),'Data Table'!$C:$C,$B11)-SUMIFS('Data Table'!$J:$J,'Data Table'!$B:$B,"<="&(TODAY()-30),'Data Table'!C:C,$B11) -> 0 | D11: =C11*(VLOOKUP((_xlfn.XLOOKUP(DSCountry,DS_Country_List,DS_Currency_List)),'FX Rates'!$A$1:$BQ$152,2)) -> 0 | E11: =SUMIF('Data Table'!$C:$C,$B11,'Data Table'!$J:$J) -> 0 | F11: =E11*(VLOOKUP((_xlfn.XLOOKUP(DSCountry,DS_Country_List,DS_Currency_List)),'FX Rates'!$A$1:$BQ$152,2)) -> 0 | G11: =SUMIFS('Data Table'!J:J,'Data Table'!B:B,"<="&TODAY(),'Data Table'!I:I,"M",'Data Table'!C:C,$B11)-SUMIFS('Data Table'!J:J,'Data Table'!B:B,"<="&(TODAY()-30),'Data Table'!I:I,"M",'Data Table'!C:C,$B11)+(SUMIFS('Data Table'!J:J,'Data Table'!B:B,"<="&TODAY(),'Data Table'!I:I,"Y",'Data Table'!C:C,$B11)/12)-(SUMIFS('Data Table'!J:J,'Data Table'!B:B,"<="&(TODAY()-365),'Data Table'!I:I,"Y",'Data Table'!C:C,$B11)/12)+(SUMIFS('Data Table'!J:J,'Data Table'!B:B,"<="&TODAY(),'Data Table'!I:I,"5Y",'Data Table'!C:C,$B11)/60-SUMIFS('Data Table'!J:J,'Data Table'!B:B,"<="&(TODAY()-1826),'Data Table'!I:I,"5Y",'Data Table'!C:C,$B11)/60) -> 0 | H11: =G11*(VLOOKUP((_xlfn.XLOOKUP(DSCountry,DS_Country_List,DS_Currency_List)),'FX Rates'!$A$1:$BQ$152,2)) -> 0
B12: Recreation and Culture | C12: =SUMIFS('Data Table'!$J:$J,'Data Table'!$B:$B,"<="&TODAY(),'Data Table'!$C:$C,$B12)-SUMIFS('Data Table'!$J:$J,'Data Table'!$B:$B,"<="&(TODAY()-30),'Data Table'!C:C,$B12) -> 0 | D12: =C12*(VLOOKUP((_xlfn.XLOOKUP(DSCountry,DS_Country_List,DS_Currency_List)),'FX Rates'!$A$1:$BQ$152,2)) -> 0 | E12: =SUMIF('Data Table'!$C:$C,$B12,'Data Table'!$J:$J) -> 0 | F12: =E12*(VLOOKUP((_xlfn.XLOOKUP(DSCountry,DS_Country_List,DS_Currency_List)),'FX Rates'!$A$1:$BQ$152,2)) -> 0 | G12: =SUMIFS('Data Table'!J:J,'Data Table'!B:B,"<="&TODAY(),'Data Table'!I:I,"M",'Data Table'!C:C,$B12)-SUMIFS('Data Table'!J:J,'Data Table'!B:B,"<="&(TODAY()-30),'Data Table'!I:I,"M",'Data Table'!C:C,$B12)+(SUMIFS('Data Table'!J:J,'Data Table'!B:B,"<="&TODAY(),'Data Table'!I:I,"Y",'Data Table'!C:C,$B12)/12)-(SUMIFS('Data Table'!J:J,'Data Table'!B:B,"<="&(TODAY()-365),'Data Table'!I:I,"Y",'Data Table'!C:C,$B12)/12)+(SUMIFS('Data Table'!J:J,'Data Table'!B:B,"<="&TODAY(),'Data Table'!I:I,"5Y",'Data Table'!C:C,$B12)/60-SUMIFS('Data Table'!J:J,'Data Table'!B:B,"<="&(TODAY()-1826),'Data Table'!I:I,"5Y",'Data Table'!C:C,$B12)/60) -> 0 | H12: =G12*(VLOOKUP((_xlfn.XLOOKUP(DSCountry,DS_Country_List,DS_Currency_List)),'FX Rates'!$A$1:$BQ$152,2)) -> 0
B13: Education | C13: =SUMIFS('Data Table'!$J:$J,'Data Table'!$B:$B,"<="&TODAY(),'Data Table'!$C:$C,$B13)-SUMIFS('Data Table'!$J:$J,'Data Table'!$B:$B,"<="&(TODAY()-30),'Data Table'!C:C,$B13) -> 0 | D13: =C13*(VLOOKUP((_xlfn.XLOOKUP(DSCountry,DS_Country_List,DS_Currency_List)),'FX Rates'!$A$1:$BQ$152,2)) -> 0 | E13: =SUMIF('Data Table'!$C:$C,$B13,'Data Table'!$J:$J) -> 0 | F13: =E13*(VLOOKUP((_xlfn.XLOOKUP(DSCountry,DS_Country_List,DS_Currency_List)),'FX Rates'!$A$1:$BQ$152,2)) -> 0 | G13: =SUMIFS('Data Table'!J:J,'Data Table'!B:B,"<="&TODAY(),'Data Table'!I:I,"M",'Data Table'!C:C,$B13)-SUMIFS('Data Table'!J:J,'Data Table'!B:B,"<="&(TODAY()-30),'Data Table'!I:I,"M",'Data Table'!C:C,$B13)+(SUMIFS('Data Table'!J:J,'Data Table'!B:B,"<="&TODAY(),'Data Table'!I:I,"Y",'Data Table'!C:C,$B13)/12)-(SUMIFS('Data Table'!J:J,'Data Table'!B:B,"<="&(TODAY()-365),'Data Table'!I:I,"Y",'Data Table'!C:C,$B13)/12)+(SUMIFS('Data Table'!J:J,'Data Table'!B:B,"<="&TODAY(),'Data Table'!I:I,"5Y",'Data Table'!C:C,$B13)/60-SUMIFS('Data Table'!J:J,'Data Table'!B:B,"<="&(TODAY()-1826),'Data Table'!I:I,"5Y",'Data Table'!C:C,$B13)/60) -> 0 | H13: =G13*(VLOOKUP((_xlfn.XLOOKUP(DSCountry,DS_Country_List,DS_Currency_List)),'FX Rates'!$A$1:$BQ$152,2)) -> 0
B14: Restaurants and Accommodation Services | C14: =SUMIFS('Data Table'!$J:$J,'Data Table'!$B:$B,"<="&TODAY(),'Data Table'!$C:$C,$B14)-SUMIFS('Data Table'!$J:$J,'Data Table'!$B:$B,"<="&(TODAY()-30),'Data Table'!C:C,$B14) -> 0 | D14: =C14*(VLOOKUP((_xlfn.XLOOKUP(DSCountry,DS_Country_List,DS_Currency_List)),'FX Rates'!$A$1:$BQ$152,2)) -> 0 | E14: =SUMIF('Data Table'!$C:$C,$B14,'Data Table'!$J:$J) -> 0 | F14: =E14*(VLOOKUP((_xlfn.XLOOKUP(DSCountry,DS_Country_List,DS_Currency_List)),'FX Rates'!$A$1:$BQ$152,2)) -> 0 | G14: =SUMIFS('Data Table'!J:J,'Data Table'!B:B,"<="&TODAY(),'Data Table'!I:I,"M",'Data Table'!C:C,$B14)-SUMIFS('Data Table'!J:J,'Data Table'!B:B,"<="&(TODAY()-30),'Data Table'!I:I,"M",'Data Table'!C:C,$B14)+(SUMIFS('Data Table'!J:J,'Data Table'!B:B,"<="&TODAY(),'Data Table'!I:I,"Y",'Data Table'!C:C,$B14)/12)-(SUMIFS('Data Table'!J:J,'Data Table'!B:B,"<="&(TODAY()-365),'Data Table'!I:I,"Y",'Data Table'!C:C,$B14)/12)+(SUMIFS('Data Table'!J:J,'Data Table'!B:B,"<="&TODAY(),'Data Table'!I:I,"5Y",'Data Table'!C:C,$B14)/60-SUMIFS('Data Table'!J:J,'Data Table'!B:B,"<="&(TODAY()-1826),'Data Table'!I:I,"5Y",'Data Table'!C:C,$B14)/60) -> 0 | H14: =G14*(VLOOKUP((_xlfn.XLOOKUP(DSCountry,DS_Country_List,DS_Currency_List)),'FX Rates'!$A$1:$BQ$152,2)) -> 0
B15: Insurance and Financial Services | C15: =SUMIFS('Data Table'!$J:$J,'Data Table'!$B:$B,"<="&TODAY(),'Data Table'!$C:$C,$B15)-SUMIFS('Data Table'!$J:$J,'Data Table'!$B:$B,"<="&(TODAY()-30),'Data Table'!C:C,$B15) -> 0 | D15: =C15*(VLOOKUP((_xlfn.XLOOKUP(DSCountry,DS_Country_List,DS_Currency_List)),'FX Rates'!$A$1:$BQ$152,2)) -> 0 | E15: =SUMIF('Data Table'!$C:$C,$B15,'Data Table'!$J:$J) -> 0 | F15: =E15*(VLOOKUP((_xlfn.XLOOKUP(DSCountry,DS_Country_List,DS_Currency_List)),'FX Rates'!$A$1:$BQ$152,2)) -> 0 | G15: =SUMIFS('Data Table'!J:J,'Data Table'!B:B,"<="&TODAY(),'Data Table'!I:I,"M",'Data Table'!C:C,$B15)-SUMIFS('Data Table'!J:J,'Data Table'!B:B,"<="&(TODAY()-30),'Data Table'!I:I,"M",'Data Table'!C:C,$B15)+(SUMIFS('Data Table'!J:J,'Data Table'!B:B,"<="&TODAY(),'Data Table'!I:I,"Y",'Data Table'!C:C,$B15)/12)-(SUMIFS('Data Table'!J:J,'Data Table'!B:B,"<="&(TODAY()-365),'Data Table'!I:I,"Y",'Data Table'!C:C,$B15)/12)+(SUMIFS('Data Table'!J:J,'Data Table'!B:B,"<="&TODAY(),'Data Table'!I:I,"5Y",'Data Table'!C:C,$B15)/60-SUMIFS('Data Table'!J:J,'Data Table'!B:B,"<="&(TODAY()-1826),'Data Table'!I:I,"5Y",'Data Table'!C:C,$B15)/60) -> 0 | H15: =G15*(VLOOKUP((_xlfn.XLOOKUP(DSCountry,DS_Country_List,DS_Currency_List)),'FX Rates'!$A$1:$BQ$152,2)) -> 0
... B17: Other | C17: =SUMIFS('Data Table'!$J:$J,'Data Table'!$B:$B,"<="&TODAY(),'Data Table'!$C:$C,$B17)-SUMIFS('Data Table'!$J:$J,'Data Table'!$B:$B,"<="&(TODAY()-30),'Data Table'!C:C,$B17) -> 0 | D17: =C17*(VLOOKUP((_xlfn.XLOOKUP(DSCountry,DS_Country_List,DS_Currency_List)),'FX Rates'!$A$1:$BQ$152,2)) -> 0 | E17: =SUMIF('Data Table'!$C:$C,$B17,'Data Table'!$J:$J) -> 0 | F17: =E17*(VLOOKUP((_xlfn.XLOOKUP(DSCountry,DS_Country_List,DS_Currency_List)),'FX Rates'!$A$1:$BQ$152,2)) -> 0 | G17: =SUMIFS('Data Table'!J:J,'Data Table'!B:B,"<="&TODAY(),'Data Table'!I:I,"M",'Data Table'!C:C,$B17)-SUMIFS('Data Table'!J:J,'Data Table'!B:B,"<="&(TODAY()-30),'Data Table'!I:I,"M",'Data Table'!C:C,$B17)+(SUMIFS('Data Table'!J:J,'Data Table'!B:B,"<="&TODAY(),'Data Table'!I:I,"Y",'Data Table'!C:C,$B17)/12)-(SUMIFS('Data Table'!J:J,'Data Table'!B:B,"<="&(TODAY()-365),'Data Table'!I:I,"Y",'Data Table'!C:C,$B17)/12)+(SUMIFS('Data Table'!J:J,'Data Table'!B:B,"<="&TODAY(),'Data Table'!I:I,"5Y",'Data Table'!C:C,$B17)/60-SUMIFS('Data Table'!J:J,'Data Table'!B:B,"<="&(TODAY()-1826),'Data Table'!I:I,"5Y",'Data Table'!C:C,$B17)/60) -> 0 | H17: =G17*(VLOOKUP((_xlfn.XLOOKUP(DSCountry,DS_Country_List,DS_Currency_List)),'FX Rates'!$A$1:$BQ$152,2)) -> 0
B18: TOTAL | C18: =SUM(C$4:C$17) -> 141.14326 | D18: =SUM(D$4:D$17) -> 200 | E18: =SUM(E$4:E$17) -> 141.14326 | F18: =SUM(F$4:F$17) -> 200 | G18: =SUM(G$4:G$17) -> 141.14326 | H18: =SUM(H$4:H$17) -> 200
